Workbook

Sheet 材料价格
A1: 材料清单报价单 | E1: 成本汇总 | K1: 3#
A2: 材料 | B2: 单价 | C2: 备注 | E2: 序号 | F2: 窗型 | G2: 面积 | H2: 成本单价 | I2: 成本合价 | K2: ='3#楼工程量统计'!N4 -> 序号 | L2: ='3#楼工程量统计'!O4 -> 窗型 | M2: ='3#楼工程量统计'!P4 -> 面积 | N2: ='3#楼工程量统计'!Q4 -> 成本单价 | O2: ='3#楼工程量统计'!R4 -> 成本合价
A3: 40*20*2.0钢副框 | B3: 7.5 | E3: 1 | F3: 65F铝合金门 | G3: =M3+M14+M25+M36+M47 -> 5489.078 | H3: =I3/G3 -> 1497.9923 | I3: =O3+O14+O25+O36+O47 -> 8222596.5 | J3: =H3+20 -> 1517.9923 | K3: ='3#楼工程量统计'!N5 -> 1 | L3: ='3#楼工程量统计'!O5 -> 65F铝合金门 | M3: ='3#楼工程量统计'!P5 -> 1719.353 | N3: ='3#楼工程量统计'!Q5 -> 1627.2159 | O3: ='3#楼工程量统计'!R5 -> 2797758.6
A4: 铝锭价格 | B4: =21030*1.05 -> 22081.5 | C4: 2025.10.24 | E4: 2 | F4: 65F铝合金窗 | G4: =M4+M15+M26+M37+M48 -> 5125.196 | H4: =I4/G4 -> 1475.3155 | I4: =O4+O15+O26+O37+O48 -> 7561281.3 | J4: =H4+20 -> 1495.3155 | K4: ='3#楼工程量统计'!N6 -> 2 | L4: ='3#楼工程量统计'!O6 -> 65F铝合金窗 | M4: ='3#楼工程量统计'!P6 -> 2933.396 | N4: ='3#楼工程量统计'!Q6 -> 1427.8592 | O4: ='3#楼工程量统计'!R6 -> 4188476.5
A5: 26mm II/IC | B5: 24000 | C5: 氟碳三涂·进口条 | E5: 3 | F5: 125铝合金幕墙 | G5: =M5+M16+M27+M38+M49 -> 791.39 | H5: =I5/G5 -> 1362.8416 | I5: =O5+O16+O27+O38+O49 -> 1078539.3 | J5: =H5+20 -> 1382.8416 | K5: ='3#楼工程量统计'!N7 -> 3 | L5: ='3#楼工程量统计'!O7 -> 125铝合金幕墙 | M5: ='3#楼工程量统计'!P7 -> 111.48 | N5: ='3#楼工程量统计'!Q7 -> 1855.04 | O5: ='3#楼工程量统计'!R7 -> 206799.86
A6: 普铝加工费 | B6: 17700 | C6: 1.8mm壁厚 | E6: 4 | F6: 铝合金百叶窗 | G6: =M6+M17+M28+M39+M50 -> 1121.338 | H6: =I6/G6 -> 971.62762 | I6: =O6+O17+O28+O39+O50 -> 1089523 | J6: =H6+20 -> 991.62762 | K6: ='3#楼工程量统计'!N8 -> 4 | L6: ='3#楼工程量统计'!O8 -> 铝合金百叶窗 | M6: ='3#楼工程量统计'!P8 -> 114.528 | N6: ='3#楼工程量统计'!Q8 -> 794 | O6: ='3#楼工程量统计'!R8 -> 90935.232
A7: 幕墙加工费 | B7: 19200 | E7: 5 | F7: 通透格栅 | G7: =M7+M18+M29+M40+M51 -> 174.42 | H7: =I7/G7 -> 1117.43 | I7: =O7+O18+O29+O40+O51 -> 194902.14 | J7: =H7+20 -> 1137.43 | K7: ='3#楼工程量统计'!N9 -> 5 | L7: ='3#楼工程量统计'!O9 -> 通透格栅 | M7: ='3#楼工程量统计'!P9 -> 0 | N7: ='3#楼工程量统计'!Q9 -> 0 | O7: ='3#楼工程量统计'!R9 -> 0
A8: 百叶加工费 | B8: 73 | E8: 6 | F8: 防蚊隐形纱窗 | G8: =M8+M19+M30+M41+M52 -> 1238.2944 | H8: 133 | I8: =O8+O19+O30+O41+O52 -> 0 | K8: ='3#楼工程量统计'!N10 -> 6 | L8: ='3#楼工程量统计'!O10 -> 防蚊纱窗 | M8: ='3#楼工程量统计'!P10 -> 702.1864 | N8: ='3#楼工程量统计'!Q10 -> 0 | O8: ='3#楼工程量统计'!R10 -> 0
A9: 白料加工费 | B9: 2900 | E9: 7 | F9: 阳台铝合金栏杆m | G9: =M9+M20+M31+M42+M53 -> 1765.5 | H9: 550 | I9: =O9+O20+O31+O42+O53 -> 0 | J9: =H9+20 -> 570 | K9: ='3#楼工程量统计'!N11 -> 7 | L9: ='3#楼工程量统计'!O11 -> 阳台铝合金栏杆m | M9: ='3#楼工程量统计'!P11 -> 128.4 | N9: ='3#楼工程量统计'!Q11 -> 0 | O9: ='3#楼工程量统计'!R11 -> 0
A10: 6单银Low-E+12A+6 | B10: =48+65+35 -> 148 | E10: 8 | F10: 穿孔铝单板 | G10: =M10+M21+M32+M43+M54 -> 345 | H10: 600 | I10: =O10+O21+O32+O43+O54 -> 0 | J10: =H10+20 -> 620 | K10: ='3#楼工程量统计'!N12 -> 8 | L10: ='3#楼工程量统计'!O12 -> 穿孔铝单板 | M10: ='3#楼工程量统计'!P12 -> 0 | N10: ='3#楼工程量统计'!Q12 -> 0 | O10: ='3#楼工程量统计'!R12 -> 0
A11: 8单银Low-E+12Ar+8+12A+8mm | B11: 312 | C11: 均质处理 | E11: 9 | G11: =SUM(G3:G10) -> 16050.216 | H11: =I11/G11 -> 1130.6291 | I11: =SUM(I3:I10) -> 18146842 | K11: ='3#楼工程量统计'!N13 -> 9 | L11: ='3#楼工程量统计'!O13 -> 0 | M11: ='3#楼工程量统计'!P13 -> 4878.757 | N11: ='3#楼工程量统计'!Q13 -> 1492.9971 | O11: ='3#楼工程量统计'!R13 -> 7283970.2
A12: 10单银Low-E+12Ar+10+12A+10mm | B12: 395 | C12: 超白 海阳顺达 | K12: 4#
A13: 12单银Low-E+12Ar+12+12A+12mm | B13: 470 | C13: 超白 海阳顺达 | K13: ='4#楼工程量统计'!N3 -> 序号 | L13: ='4#楼工程量统计'!O3 -> 窗型 | M13: ='4#楼工程量统计'!P3 -> 面积 | N13: ='4#楼工程量统计'!Q3 -> 成本单价 | O13: ='4#楼工程量统计'!R3 -> 成本合价
A14: 内开内倒窗（隐藏式） | B14: =145+8 -> 153 | C14: 坚朗(打logo) | K14: ='4#楼工程量统计'!N4 -> 1 | L14: ='4#楼工程量统计'!O4 -> 65F铝合金门 | M14: ='4#楼工程量统计'!P4 -> 107.78 | N14: ='4#楼工程量统计'!Q4 -> 1184.9823 | O14: ='4#楼工程量统计'!R4 -> 127717.39
A15: 内平开窗（隐藏式） | B15: =72+8 -> 80 | C15: 坚朗 | K15: ='4#楼工程量统计'!N5 -> 2 | L15: ='4#楼工程量统计'!O5 -> 65F铝合金窗 | M15: ='4#楼工程量统计'!P5 -> 644.52 | N15: ='4#楼工程量统计'!Q5 -> 1537.8533 | O15: ='4#楼工程量统计'!R5 -> 991177.19
A16: 外平开窗 | B16: =80+8 -> 88 | C16: 坚朗 | K16: ='4#楼工程量统计'!N6 -> 3 | L16: ='4#楼工程量统计'!O6 -> 125铝合金幕墙 | M16: ='4#楼工程量统计'!P6 -> 0 | N16: ='4#楼工程量统计'!Q6 -> 0 | O16: ='4#楼工程量统计'!R6 -> 0
A17: 外悬窗 | B17: =107+8 -> 115 | C17: 坚朗 | K17: ='4#楼工程量统计'!N7 -> 4 | L17: ='4#楼工程量统计'!O7 -> 铝合金百叶窗 | M17: ='4#楼工程量统计'!P7 -> 18.38 | N17: ='4#楼工程量统计'!Q7 -> 964 | O17: ='4#楼工程量统计'!R7 -> 17718.32
A18: 平开电动开窗器(安装） | B18: =1150+200 -> 1350 | C18: 坚朗 | K18: ='4#楼工程量统计'!N8 -> 5 | L18: ='4#楼工程量统计'!O8 -> 通透格栅 | M18: ='4#楼工程量统计'!P8 -> 0 | N18: ='4#楼工程量统计'!Q8 -> 0 | O18: ='4#楼工程量统计'!R8 -> 0
A19: 单开门 | B19: 230 | C19: 坚朗 | K19: ='4#楼工程量统计'!N9 -> 6 | L19: ='4#楼工程量统计'!O9 -> 防蚊纱窗 | M19: ='4#楼工程量统计'!P9 -> 123.818 | N19: ='4#楼工程量统计'!Q9 -> 0 | O19: ='4#楼工程量统计'!R9 -> 0
A20: 对开门 | B20: 335 | C20: 坚朗 | K20: ='4#楼工程量统计'!N10 -> 7 | L20: ='4#楼工程量统计'!O10 -> 阳台铝合金栏杆m | M20: ='4#楼工程量统计'!P10 -> 0 | N20: ='4#楼工程量统计'!Q10 -> 0 | O20: ='4#楼工程量统计'!R10 -> 0
K21: ='4#楼工程量统计'!N11 -> 8 | L21: ='4#楼工程量统计'!O11 -> 穿孔铝单板 | M21: ='4#楼工程量统计'!P11 -> 0 | N21: ='4#楼工程量统计'!Q11 -> 0 | O21: ='4#楼工程量统计'!R11 -> 0
K22: ='4#楼工程量统计'!N12 -> 9 | L22: ='4#楼工程量统计'!O12 -> 0 | M22: ='4#楼工程量统计'!P12 -> 770.68 | N22: ='4#楼工程量统计'!Q12 -> 1474.8182 | O22: ='4#楼工程量统计'!R12 -> 1136612.9
A23: 通透格栅 | B23: 700 | K23: 5#
A24: 中性硅酮密封胶（500ml)耐火胶 | B24: =23.6/500*300 -> 14.16 | C24: 安泰 | K24: ='5#楼工程量统计'!M4 -> 序号 | L24: ='5#楼工程量统计'!N4 -> 窗型 | M24: ='5#楼工程量统计'!O4 -> 面积 | N24: ='5#楼工程量统计'!P4 -> 成本单价 | O24: ='5#楼工程量统计'!Q4 -> 成本合价
A25: 中性硅酮密封胶（500ml) | B25: =14.2/500*300 -> 8.52 | C25: 安泰 | K25: ='5#楼工程量统计'!M5 -> 1 | L25: ='5#楼工程量统计'!N5 -> 65F铝合金门 | M25: ='5#楼工程量统计'!O5 -> 1236.605 | N25: ='5#楼工程量统计'!P5 -> 1406.672 | O25: ='5#楼工程量统计'!Q5 -> 1739497.6
A26: 发泡胶 | B26: 23 | C26: 固诺 | K26: ='5#楼工程量统计'!M6 -> 2 | L26: ='5#楼工程量统计'!N6 -> 65F铝合金窗 | M26: ='5#楼工程量统计'!O6 -> 174.03 | N26: ='5#楼工程量统计'!P6 -> 1589.7681 | O26: ='5#楼工程量统计'!Q6 -> 276667.34
A27: 内平开金刚纱窗 | K27: ='5#楼工程量统计'!M7 -> 3 | L27: ='5#楼工程量统计'!N7 -> 125铝合金幕墙 | M27: ='5#楼工程量统计'!O7 -> 211.68 | N27: ='5#楼工程量统计'!P7 -> 1118.645 | O27: ='5#楼工程量统计'!Q7 -> 236794.77
A28: 隐形纱窗 | B28: 118 | K28: ='5#楼工程量统计'!M8 -> 4 | L28: ='5#楼工程量统计'!N8 -> 铝合金百叶窗 | M28: ='5#楼工程量统计'!O8 -> 329.84 | N28: ='5#楼工程量统计'!P8 -> 1004 | O28: ='5#楼工程量统计'!Q8 -> 331159.36
K29: ='5#楼工程量统计'!M9 -> 5 | L29: ='5#楼工程量统计'!N9 -> 通透格栅 | M29: ='5#楼工程量统计'!O9 -> 0 | N29: ='5#楼工程量统计'!P9 -> 0 | O29: ='5#楼工程量统计'!Q9 -> 0
K30: ='5#楼工程量统计'!M10 -> 6 | L30: ='5#楼工程量统计'!N10 -> 防蚊纱窗 | M30: ='5#楼工程量统计'!O10 -> 121.6 | N30: ='5#楼工程量统计'!P10 -> 0 | O30: ='5#楼工程量统计'!Q10 -> 0
K31: ='5#楼工程量统计'!M11 -> 7 | L31: ='5#楼工程量统计'!N11 -> 阳台铝合金栏杆m | M31: ='5#楼工程量统计'!O11 -> 483.3 | N31: ='5#楼工程量统计'!P11 -> 0 | O31: ='5#楼工程量统计'!Q11 -> 0
K32: ='5#楼工程量统计'!M12 -> 8 | L32: ='5#楼工程量统计'!N12 -> 穿孔铝单板 | M32: ='5#楼工程量统计'!O12 -> 135 | N32: ='5#楼工程量统计'!P12 -> 0 | O32: ='5#楼工程量统计'!Q12 -> 0
K33: ='5#楼工程量统计'!M13 -> 9 | L33: ='5#楼工程量统计'!N13 -> 0 | M33: ='5#楼工程量统计'!O13 -> 1952.155 | N33: ='5#楼工程量统计'!P13 -> 1323.7264 | O33: ='5#楼工程量统计'!Q13 -> 2584119.1
K34: 6#
K35: ='6#楼工程量统计 '!M4 -> 序号 | L35: ='6#楼工程量统计 '!N4 -> 窗型 | M35: ='6#楼工程量统计 '!O4 -> 面积 | N35: ='6#楼工程量统计 '!P4 -> 成本单价 | O35: ='6#楼工程量统计 '!Q4 -> 成本合价
K36: ='6#楼工程量统计 '!M5 -> 1 | L36: ='6#楼工程量统计 '!N5 -> 65F铝合金门 | M36: ='6#楼工程量统计 '!O5 -> 2384.43 | N36: ='6#楼工程量统计 '!P5 -> 1463.4744 | O36: ='6#楼工程量统计 '!Q5 -> 3489552.3
K37: ='6#楼工程量统计 '!M6 -> 2 | L37: ='6#楼工程量统计 '!N6 -> 65F铝合金窗 | M37: ='6#楼工程量统计 '!O6 -> 393.89 | N37: ='6#楼工程量统计 '!P6 -> 1594.5882 | O37: ='6#楼工程量统计 '!Q6 -> 628092.36
K38: ='6#楼工程量统计 '!M7 -> 3 | L38: ='6#楼工程量统计 '!N7 -> 125铝合金幕墙 | M38: ='6#楼工程量统计 '!O7 -> 277.83 | N38: ='6#楼工程量统计 '!P7 -> 1105.1281 | O38: ='6#楼工程量统计 '!Q7 -> 307037.74
K39: ='6#楼工程量统计 '!M8 -> 4 | L39: ='6#楼工程量统计 '!N8 -> 铝合金百叶窗 | M39: ='6#楼工程量统计 '!O8 -> 603.76 | N39: ='6#楼工程量统计 '!P8 -> 1004 | O39: ='6#楼工程量统计 '!Q8 -> 606175.04
K40: ='6#楼工程量统计 '!M9 -> 5 | L40: ='6#楼工程量统计 '!N9 -> 通透格栅 | M40: ='6#楼工程量统计 '!O9 -> 0 | N40: ='6#楼工程量统计 '!P9 -> 0 | O40: ='6#楼工程量统计 '!Q9 -> 0
K41: ='6#楼工程量统计 '!M10 -> 6 | L41: ='6#楼工程量统计 '!N10 -> 防蚊纱窗 | M41: ='6#楼工程量统计 '!O10 -> 128 | N41: ='6#楼工程量统计 '!P10 -> 0 | O41: ='6#楼工程量统计 '!Q10 -> 0
K42: ='6#楼工程量统计 '!M11 -> 7 | L42: ='6#楼工程量统计 '!N11 -> 阳台铝合金栏杆m | M42: ='6#楼工程量统计 '!O11 -> 985.8 | N42: ='6#楼工程量统计 '!P11 -> 0 | O42: ='6#楼工程量统计 '!Q11 -> 0
K43: ='6#楼工程量统计 '!M12 -> 8 | L43: ='6#楼工程量统计 '!N12 -> 穿孔铝单板 | M43: ='6#楼工程量统计 '!O12 -> 210 | N43: ='6#楼工程量统计 '!P12 -> 0 | O43: ='6#楼工程量统计 '!Q12 -> 0
K44: ='6#楼工程量统计 '!M13 -> 9 | L44: ='6#楼工程量统计 '!N13 -> 0 | M44: ='6#楼工程量统计 '!O13 -> 3659.91 | N44: ='6#楼工程量统计 '!P13 -> 1374.585 | O44: ='6#楼工程量统计 '!Q13 -> 5030857.4
K45: 8#
K46: ='8#楼工程量统计'!M4 -> 序号 | L46: ='8#楼工程量统计'!N4 -> 窗型 | M46: ='8#楼工程量统计'!O4 -> 面积 | N46: ='8#楼工程量统计'!P4 -> 成本单价 | O46: ='8#楼工程量统计'!Q4 -> 成本合价
K47: ='8#楼工程量统计'!M5 -> 1 | L47: ='8#楼工程量统计'!N5 -> 65F铝合金门 | M47: ='8#楼工程量统计'!O5 -> 40.91 | N47: ='8#楼工程量统计'!P5 -> 1663.91 | O47: ='8#楼工程量统计'!Q5 -> 68070.558
K48: ='8#楼工程量统计'!M6 -> 2 | L48: ='8#楼工程量统计'!N6 -> 65F铝合金窗 | M48: ='8#楼工程量统计'!O6 -> 979.36 | N48: ='8#楼工程量统计'!P6 -> 1507.9929 | O48: ='8#楼工程量统计'!Q6 -> 1476867.9
K49: ='8#楼工程量统计'!M7 -> 3 | L49: ='8#楼工程量统计'!N7 -> 125铝合金幕墙 | M49: ='8#楼工程量统计'!O7 -> 190.4 | N49: ='8#楼工程量统计'!P7 -> 1722.2 | O49: ='8#楼工程量统计'!Q7 -> 327906.88
K50: ='8#楼工程量统计'!M8 -> 4 | L50: ='8#楼工程量统计'!N8 -> 铝合金百叶窗 | M50: ='8#楼工程量统计'!O8 -> 54.83 | N50: ='8#楼工程量统计'!P8 -> 794 | O50: ='8#楼工程量统计'!Q8 -> 43535.02
K51: ='8#楼工程量统计'!M9 -> 5 | L51: ='8#楼工程量统计'!N9 -> 通透格栅 | M51: ='8#楼工程量统计'!O9 -> 174.42 | N51: ='8#楼工程量统计'!P9 -> 1117.43 | O51: ='8#楼工程量统计'!Q9 -> 194902.14
K52: ='8#楼工程量统计'!M10 -> 6 | L52: ='8#楼工程量统计'!N10 -> 防蚊纱窗 | M52: ='8#楼工程量统计'!O10 -> 162.69 | N52: ='8#楼工程量统计'!P10 -> 0 | O52: ='8#楼工程量统计'!Q10 -> 0
K53: ='8#楼工程量统计'!M11 -> 7 | L53: ='8#楼工程量统计'!N11 -> 阳台铝合金栏杆m | M53: ='8#楼工程量统计'!O11 -> 168 | N53: ='8#楼工程量统计'!P11 -> 0 | O53: ='8#楼工程量统计'!Q11 -> 0
K54: ='8#楼工程量统计'!M12 -> 8 | L54: ='8#楼工程量统计'!N12 -> 穿孔铝单板 | M54: ='8#楼工程量统计'!O12 -> 0 | N54: ='8#楼工程量统计'!P12 -> 0 | O54: ='8#楼工程量统计'!Q12 -> 0
K55: ='8#楼工程量统计'!M13 -> 9 | L55: ='8#楼工程量统计'!N13 -> 0 | M55: ='8#楼工程量统计'!O13 -> 1439.92 | N55: ='8#楼工程量统计'!P13 -> 1466.2499 | O55: ='8#楼工程量统计'!Q13 -> 2111282.5

Sheet 汇总表
A1: 成本汇总表
A2: 序号 | B2: 楼号 | C2: 数量 | D2: 面积 | E2: 成本单价 | F2: 成本合价 | G2: 备注
A3: 1 | B3: 3# | C3: ='3#楼工程量统计'!F70 -> 967 | D3: ='3#楼工程量统计'!H70 -> 4878.757
A4: 2 | B4: 4# | C4: ='4#楼工程量统计'!F24 -> 153 | D4: ='4#楼工程量统计'!H24 -> 770.68
A5: 3 | B5: 5# | C5: ='5#楼工程量统计'!F36 -> 550 | D5: ='5#楼工程量统计'!H36 -> 1952.155
A6: 4 | B6: 6# | C6: ='6#楼工程量统计 '!F33 -> 1038 | D6: ='6#楼工程量统计 '!H33 -> 3659.91
A7: 5 | B7: 8# | C7: ='8#楼工程量统计'!F40 -> 286 | D7: ='8#楼工程量统计'!H40 -> 1439.92
A8: 6 | C8: =SUM(C3:C7) -> 2994 | D8: =SUM(D3:D7) -> 12701.422
D10: =D8/C8 -> 4.2422919

Sheet 3#楼工程量统计
A1: 3#工程量统计
A2: 序号 | B2: 类型 | C2: 设计编号 | D2: 洞口宽(mm) | E2: 洞口高(mm) | F2: 数量 | G2: 单樘面积(㎡) | H2: 工程量(㎡) | I2: 成本单价 | K2: 成本合价 | L2: 备注 | M2: 断桥铝合金(6LOW-E+12A+6)
A3: 1 | B3: 外门 | C3: WM1121 | D3: 1100 | E3: 2050 | F3: 1 | G3: 2.125 | H3: =F3*G3 -> 2.125 | I3: ='WM1127'!B371 -> 1663.91 | K3: =I3*H3 -> 3535.8088
A4: 2 | C4: WM1127 | D4: 1100 | E4: 2650 | F4: 288 | G4: 2.785 | H4: =F4*G4 -> 802.08 | I4: ='WM1127'!B371 -> 1663.91 | K4: =I4*H4 -> 1334588.9 | N4: 序号 | O4: 窗型 | P4: 面积 | Q4: 成本单价 | R4: 成本合价
A5: 3 | C5: WM1635 | D5: 1600 | E5: 3500 | F5: 6 | G5: 5.325 | H5: =F5*G5 -> 31.95 | I5: ='WM1127'!B371 -> 1663.91 | K5: =I5*H5 -> 53161.925 | N5: 1 | O5: 65F铝合金门 | P5: =SUM(H3:H20,H47:H52)-P7 -> 1719.353 | Q5: =R5/P5 -> 1627.2159 | R5: =SUM(K3:K20,K47:K52)-R7 -> 2797758.6
A6: 4 | C6: WM1822 | D6: 1800 | E6: 2150 | F6: 4 | G6: 3.52 | H6: =F6*G6 -> 14.08 | I6: ='WM1127'!B371 -> 1663.91 | K6: =I6*H6 -> 23427.853 | N6: 2 | O6: 65F铝合金窗 | P6: =SUM(H21:H46) -> 2933.396 | Q6: =R6/P6 -> 1427.8592 | R6: =SUM(K21:K46) -> 4188476.5
A7: 5 | C7: WM1830 | D7: 1800 | E7: 3000 | F7: 4 | G7: 5.05 | H7: =F7*G7 -> 20.2 | I7: ='WM1127'!B371 -> 1663.91 | K7: =I7*H7 -> 33610.982 | N7: 3 | O7: 125铝合金幕墙 | P7: =H13+H19 -> 111.48 | Q7: =R7/P7 -> 1855.04 | R7: =K13+K19 -> 206799.86
A8: 6 | C8: WM2021 | D8: 2000 | E8: 2150 | F8: 4 | G8: =2.125*2 -> 4.25 | H8: =F8*G8 -> 17 | I8: ='WM1127'!B371 -> 1663.91 | K8: =I8*H8 -> 28286.47 | N8: 4 | O8: 铝合金百叶窗 | P8: =SUM(H53:H67) -> 114.528 | Q8: =R8/P8 -> 794 | R8: =SUM(K53:K67) -> 90935.232
A9: 7 | C9: WM2035 | D9: 2000 | E9: 3500 | F9: 2 | G9: 6.57 | H9: =F9*G9 -> 13.14 | I9: ='WM1127'!B371 -> 1663.91 | K9: =I9*H9 -> 21863.777 | N9: 5 | O9: 通透格栅
A10: 8 | C10: WM2335 | D10: 2300 | E10: 3500 | F10: 4 | G10: 7.48 | H10: =F10*G10 -> 29.92 | I10: ='WM1127'!B371 -> 1663.91 | K10: =I10*H10 -> 49784.187 | N10: 6 | O10: 防蚊纱窗 | P10: =SUM(H68) -> 702.1864
A11: 9 | C11: WM2338 | D11: 2300 | E11: 3800 | F11: 2 | G11: 8.178 | H11: =F11*G11 -> 16.356 | I11: ='WM1127'!B371 -> 1663.91 | K11: =I11*H11 -> 27214.912 | N11: 7 | O11: 阳台铝合金栏杆m | P11: =SUM(H69) -> 128.4
A12: 10 | C12: WM2338-G | D12: 2300 | E12: 3800 | F12: 6 | G12: 8.17 | H12: =F12*G12 -> 49.02 | I12: ='WM1127'!B371 -> 1663.91 | K12: =I12*H12 -> 81564.868 | L12: 上拱窗户优化为固玻，无需开启 | N12: 8 | O12: 穿孔铝单板
A13: 11 | C13: WM2480-G | D13: 2400 | E13: 8000 | F13: 4 | G13: 18.58 | H13: =F13*G13 -> 74.32 | I13: ='WM2480'!G126 -> 1855.04 | K13: =I13*H13 -> 137866.57 | L13: 上拱窗户优化为固玻，无需开启 | M13: 125幕墙 | N13: 9 | P13: =SUM(P5:P9) -> 4878.757 | Q13: =R13/P13 -> 1492.9971 | R13: =SUM(R5:R8) -> 7283970.2
A14: 12 | C14: WM3935 | D14: 3900 | E14: 3500 | F14: 2 | G14: =6.417*2 -> 12.834 | H14: =F14*G14 -> 25.668 | I14: ='WM1127'!B371 -> 1663.91 | K14: =I14*H14 -> 42709.242
A15: 13 | C15: WM5424 | D15: 5400 | E15: 2400 | F15: 4 | G15: =5.4*2.4 -> 12.96 | H15: =F15*G15 -> 51.84 | I15: ='WM1127'!B371 -> 1663.91 | K15: =I15*H15 -> 86257.094
A16: 14 | C16: WM1126-xf | D16: 1100 | E16: 2550 | F16: 2 | G16: 2.675 | H16: =F16*G16 -> 5.35 | I16: ='WM1127'!B371 -> 1663.91 | K16: =I16*H16 -> 8901.9185 | L16: 消防救援口
A17: 15 | C17: WM1127-xf | D17: 1100 | E17: 2650 | F17: 4 | G17: 2.785 | H17: =F17*G17 -> 11.14 | I17: ='WM1127'!B371 -> 1663.91 | K17: =I17*H17 -> 18535.957 | L17: 消防救援口
A18: 16 | C18: WM2035-xf | D18: 2000 | E18: 3500 | F18: 4 | G18: 6.57 | H18: =F18*G18 -> 26.28 | I18: ='WM1127'!B371 -> 1663.91 | K18: =I18*H18 -> 43727.555 | L18: 消防救援口
A19: 17 | C19: WM2480-G-xf | D19: 2400 | E19: 8000 | F19: 2 | G19: 18.58 | H19: =F19*G19 -> 37.16 | I19: ='WM2480'!G126 -> 1855.04 | K19: =I19*H19 -> 68933.286 | L19: 消防救援口，上拱窗户优化为固玻，无需开启 | M19: 125幕墙
A20: 18 | C20: WM3935-xf | D20: 3900 | E20: 3500 | F20: 2 | G20: =6.417*2 -> 12.834 | H20: =F20*G20 -> 25.668 | I20: ='WM1127'!B371 -> 1663.91 | K20: =I20*H20 -> 42709.242 | L20: 消防救援口
A21: 19 | B21: 外窗 | C21: C1014 | D21: 1000 | E21: 1400 | F21: 30 | G21: 1.1 | H21: =F21*G21 -> 33 | I21: ='C1014'!B371 -> 2372.44 | K21: =I21*H21 -> 78290.52
A22: 20 | C22: C1117 | D22: 1100 | E22: 1700 | F22: 22 | G22: 1.74 | H22: =F22*G22 -> 38.28 | I22: ='C1117'!B371 -> 1875.61 | K22: =I22*H22 -> 71798.351
A23: 21 | C23: C1121 | D23: 1100 | E23: 2050 | F23: 12 | G23: 2.125 | H23: =F23*G23 -> 25.5 | I23: ='C1122'!B371 -> 1792.83 | K23: =I23*H23 -> 45717.165
A24: 22 | C24: C1122 | D24: 1100 | E24: 2150 | F24: 8 | G24: 2.125 | H24: =F24*G24 -> 17 | I24: ='C1122'!B371 -> 1792.83 | K24: =I24*H24 -> 30478.11
A25: 23 | C25: C1126 | D25: 1100 | E25: 2550 | F25: 14 | G25: 2.675 | H25: =F25*G25 -> 37.45 | I25: ='C1122'!B371 -> 1792.83 | K25: =I25*H25 -> 67141.483
A26: 24 | C26: C1127 | D26: 1100 | E26: 2650 | F26: 56 | G26: 2.785 | H26: =F26*G26 -> 155.96 | I26: ='C1122'!B371 -> 1792.83 | K26: =I26*H26 -> 279609.77
A27: 25 | C27: C1417 | D27: 1400 | E27: 1700 | F27: 30 | G27: 1.87 | H27: =F27*G27 -> 56.1 | I27: ='C1417'!B371 -> 1810.03 | K27: =I27*H27 -> 101542.68
A28: 26 | C28: C1837 | D28: 1800 | E28: 3700 | F28: 4 | G28: 6.31 | H28: =F28*G28 -> 25.24 | I28: ='C2430'!B371 -> 1459.77 | K28: =I28*H28 -> 36844.595
A29: 27 | C29: C2330 | D29: 2300 | E29: 3000 | F29: 32 | G29: 6.33 | H29: =F29*G29 -> 202.56 | I29: ='C2430'!B371 -> 1459.77 | K29: =I29*H29 -> 295691.01
A30: 28 | C30: C2335 | D30: 2300 | E30: 3500 | F30: 6 | G30: 7.48 | H30: =F30*G30 -> 44.88 | I30: ='C2430'!B371 -> 1459.77 | K30: =I30*H30 -> 65514.478
A31: 29 | C31: C2338 | D31: 2300 | E31: 3800 | F31: 14 | G31: 8.17 | H31: =F31*G31 -> 114.38 | I31: ='C2430'!B371 -> 1459.77 | K31: =I31*H31 -> 166968.49
A32: 30 | C32: C2430 | D32: 2400 | E32: 3000 | F32: 6 | G32: 6.58 | H32: =F32*G32 -> 39.48 | I32: ='C2430'!B371 -> 1459.77 | K32: =I32*H32 -> 57631.72
A33: 31 | C33: C2722 | D33: 2700 | E33: 2150 | F33: 2 | G33: 5.02 | H33: =F33*G33 -> 10.04 | I33: ='C2430'!B371 -> 1459.77 | K33: =I33*H33 -> 14656.091
A34: 32 | C34: C2727 | D34: 2700 | E34: 2700 | F34: 10 | G34: 6.508 | H34: =F34*G34 -> 65.08 | I34: ='C2430'!B371 -> 1459.77 | K34: =I34*H34 -> 95001.832
A35: 33 | C35: C2730 | D35: 2700 | E35: 3000 | F35: 110 | G35: 7.318 | H35: =F35*G35 -> 804.98 | I35: ='C2430'!B371 -> 1459.77 | K35: =I35*H35 -> 1175085.7
A36: 34 | C36: C2735 | D36: 2700 | E36: 3500 | F36: 19 | G36: 8.668 | H36: =F36*G36 -> 164.692 | I36: ='C2430'!B371 -> 1459.77 | K36: =I36*H36 -> 240412.44
A37: 35 | C37: C2730-xf | D37: 2700 | E37: 3000 | F37: 4 | G37: 7.318 | H37: =F37*G37 -> 29.272 | I37: ='C2430'!B371 -> 1459.77 | K37: =I37*H37 -> 42730.387 | L37: 消防救援口
A38: 36 | C38: C2735-G-xf | D38: 2700 | E38: 3500 | F38: 4 | G38: 8.668 | H38: =F38*G38 -> 34.672 | I38: ='C2430'!B371 -> 1459.77 | K38: =I38*H38 -> 50613.145 | L38: 消防救援口，上拱窗户优化为固玻，无需开启
A39: 37 | C39: C2735-BY | D39: 2700 | E39: 3500 | F39: 7 | G39: 8.67 | H39: =F39*G39 -> 60.69 | I39: ='C2735-G'!B371 -> 1219.49 | K39: =I39*H39 -> 74010.848 | L39: 局部采用防雨百叶
A40: 38 | C40: C1830-G | D40: 1800 | E40: 3000 | F40: 4 | G40: 5.05 | H40: =F40*G40 -> 20.2 | I40: ='C2735-G'!B371 -> 1219.49 | K40: =I40*H40 -> 24633.698 | L40: 上拱窗户优化为固玻，无需开启
A41: 39 | C41: C2335-G | D41: 2300 | E41: 3500 | F41: 6 | G41: 7.48 | H41: =F41*G41 -> 44.88 | I41: ='C2430'!B371 -> 1459.77 | K41: =I41*H41 -> 65514.478 | L41: 上拱窗户优化为固玻，无需开启
A42: 40 | C42: C2338-G | D42: 2300 | E42: 3800 | F42: 10 | G42: 8.17 | H42: =F42*G42 -> 81.7 | I42: ='C2735-G'!B371 -> 1219.49 | K42: =I42*H42 -> 99632.333 | L42: 上拱窗户优化为固玻，无需开启
A43: 41 | C43: C2723-G | D43: 2700 | E43: 2300 | F43: 8 | G43: =2.7*2.3 -> 6.21 | H43: =F43*G43 -> 49.68 | I43: ='C2735-G'!B371 -> 1219.49 | K43: =I43*H43 -> 60584.263
A44: 42 | C44: C2735-G | D44: 2700 | E44: 3500 | F44: 64 | G44: 8.668 | H44: =F44*G44 -> 554.752 | I44: ='C2735-G'!B371 -> 1219.49 | K44: =I44*H44 -> 676514.52 | L44: 上拱窗户优化为固玻，无需开启
A45: 43 | C45: C2774-G | D45: 2700 | E45: 7400 | F45: 8 | G45: 19.198 | H45: =F45*G45 -> 153.584 | I45: ='C2735-G'!B371 -> 1219.49 | K45: =I45*H45 -> 187294.15 | L45: 上拱窗户优化为固玻，无需开启
A46: 44 | C46: C2735-G2 | D46: 2700 | E46: 3500 | F46: 8 | G46: 8.668 | H46: =F46*G46 -> 69.344 | I46: ='C2735-G'!B371 -> 1219.49 | K46: =I46*H46 -> 84564.315 | L46: 上拱窗户优化为固玻，无需开启
A47: 45 | B47: 外门联窗 | C47: WMLC2727 | D47: 2700 | E47: 2700 | F47: 4 | G47: 6.508 | H47: =F47*G47 -> 26.032 | I47: =WMLC2730!B371 -> 1554.67 | K47: =I47*H47 -> 40471.169
A48: 46 | C48: WMLC2730 | D48: 2700 | E48: 3000 | F48: 42 | G48: 7.318 | H48: =F48*G48 -> 307.356 | I48: =WMLC2730!B371 -> 1554.67 | K48: =I48*H48 -> 477837.15
A49: 47 | C49: WMLC2735-G | D49: 2700 | E49: 3500 | F49: 2 | G49: 8.668 | H49: =F49*G49 -> 17.336 | I49: =WMLC2730!B371 -> 1554.67 | K49: =I49*H49 -> 26951.759 | L49: 上拱窗户优化为固玻，无需开启
A50: 48 | C50: WMLC2737 | D50: 2700 | E50: 3650 | F50: 6 | G50: 9.07 | H50: =F50*G50 -> 54.42 | I50: =WMLC2730!B371 -> 1554.67 | K50: =I50*H50 -> 84605.141
A51: 49 | C51: WMLC2727-xf | D51: 2700 | E51: 2700 | F51: 4 | G51: 6.508 | H51: =F51*G51 -> 26.032 | I51: =WMLC2730!B371 -> 1554.67 | K51: =I51*H51 -> 40471.169 | L51: 消防救援口
A52: 50 | C52: WMLC2730-xf | D52: 2700 | E52: 3000 | F52: 20 | G52: 7.318 | H52: =F52*G52 -> 146.36 | I52: =WMLC2730!B371 -> 1554.67 | K52: =I52*H52 -> 227541.5 | L52: 消防救援口
A53: 51 | B53: 百叶门窗 | C53: BYC0202 | D53: 200 | E53: 150 | F53: 1 | G53: =0.2*0.15 -> 0.03 | H53: =F53*G53 -> 0.03 | I53: ='BYC1610'!G62 -> 794 | K53: =I53*H53 -> 23.82
A54: 52 | C54: BYC0210 | D54: 200 | E54: 1000 | F54: 2 | G54: =0.2*1 -> 0.2 | H54: =F54*G54 -> 0.4 | I54: ='BYC1610'!G62 -> 794 | K54: =I54*H54 -> 317.6
A55: 53 | C55: BYC0302 | D55: 300 | E55: 200 | F55: 1 | G55: =0.3*0.2 -> 0.06 | H55: =F55*G55 -> 0.06 | I55: ='BYC1610'!G62 -> 794 | K55: =I55*H55 -> 47.64
A56: 54 | C56: BYC0304 | D56: 300 | E56: 400 | F56: 4 | G56: =0.3*0.4 -> 0.12 | H56: =F56*G56 -> 0.48 | I56: ='BYC1610'!G62 -> 794 | K56: =I56*H56 -> 381.12
A57: 55 | C57: BYC0306 | D57: 300 | E57: 600 | F57: 1 | G57: =0.6*0.3 -> 0.18 | H57: =F57*G57 -> 0.18 | I57: ='BYC1610'!G62 -> 794 | K57: =I57*H57 -> 142.92
A58: 56 | C58: BYC1127 | D58: 1100 | E58: 2700 | F58: 4 | G58: 2.785 | H58: =F58*G58 -> 11.14 | I58: ='BYC1610'!G62 -> 794 | K58: =I58*H58 -> 8845.16
A59: 57 | C59: BYC1410 | D59: 1400 | E59: 1000 | F59: 1 | G59: =1.4*1 -> 1.4 | H59: =F59*G59 -> 1.4 | I59: ='BYC1610'!G62 -> 794 | K59: =I59*H59 -> 1111.6
A60: 58 | C60: BYC1510 | D60: 1500 | E60: 1000 | F60: 1 | G60: =1.5*1 -> 1.5 | H60: =F60*G60 -> 1.5 | I60: ='BYC1610'!G62 -> 794 | K60: =I60*H60 -> 1191
A61: 59 | C61: BYC1610 | D61: 1600 | E61: 1000 | F61: 2 | G61: =1.6*1 -> 1.6 | H61: =F61*G61 -> 3.2 | I61: ='BYC1610'!G62 -> 794 | K61: =I61*H61 -> 2540.8
A62: 60 | C62: BYC2707 | D62: 2650 | E62: 700 | F62: 6 | G62: =2.65*0.7 -> 1.855 | H62: =F62*G62 -> 11.13 | I62: ='BYC1610'!G62 -> 794 | K62: =I62*H62 -> 8837.22
A63: 61 | C63: BYC2730 | D63: 2650 | E63: 3000 | F63: 6 | G63: 7.318 | H63: =F63*G63 -> 43.908 | I63: ='BYC1610'!G62 -> 794 | K63: =I63*H63 -> 34862.952
A64: 62 | C64: BYC2907 | D64: 2850 | E64: 700 | F64: 6 | G64: =2.85*0.7 -> 1.995 | H64: =F64*G64 -> 11.97 | I64: ='BYC1610'!G62 -> 794 | K64: =I64*H64 -> 9504.18
A65: 63 | C65: BYC3107 | D65: 3050 | E65: 700 | F65: 6 | G65: =3.05*0.7 -> 2.135 | H65: =F65*G65 -> 12.81 | I65: ='BYC1610'!G62 -> 794 | K65: =I65*H65 -> 10171.14
A66: 64 | C66: BYC7207 | D66: 7200 | E66: 700 | F66: 3 | G66: =7.2*0.7 -> 5.04 | H66: =F66*G66 -> 15.12 | I66: ='BYC1610'!G62 -> 794 | K66: =I66*H66 -> 12005.28
A67: 65 | C67: BYM0610 | D67: 600 | E67: 1000 | F67: 2 | G67: =0.6*1 -> 0.6 | H67: =F67*G67 -> 1.2 | I67: ='BYC1610'!G62 -> 794 | K67: =I67*H67 -> 952.8
A68: 66 | B68: 防蚊纱窗 | G68: 0.48 | H68: =SUM(H21:H52)*20% -> 702.1864
A69: 67 | B69: 阳台铝合金栏杆m | F69: 1 | G69: =57*2+7.2*2 -> 128.4 | H69: =F69*G69 -> 128.4
A70: 68 | B70: 合计 | F70: =SUM(F3:F67) -> 967 | H70: =SUM(H3:H67) -> 4878.757 | I70: =K70/H70 -> 1492.9971 | K70: =SUM(K3:K67) -> 7283970.2

Sheet 4#楼工程量统计
A1: 4#工程量统计
A2: 序号 | B2: 类型 | C2: 设计编号 | D2: 洞口宽(mm) | E2: 洞口高(mm) | F2: 数量 | G2: 单樘面积(㎡) | H2: 工程量(㎡) | I2: 成本单价 | J2: 成本合价 | K2: 备注 | L2: 截图
A3: 1 | B3: 外门 | C3: WM2038 | D3: 2000 | E3: 3800 | F3: 5 | G3: 7.17 | H3: =F3*G3 -> 35.85 | I3: ='WM2038'!B371 -> 1143.12 | J3: =I3*H3 -> 40980.852 | N3: 序号 | O3: 窗型 | P3: 面积 | Q3: 成本单价 | R3: 成本合价
A4: 2 | C4: WM2338 | D4: 2300 | E4: 3800 | F4: 6 | G4: 8.17 | H4: =F4*G4 -> 49.02 | I4: ='WM2038'!B371 -> 1143.12 | J4: =I4*H4 -> 56035.742 | N4: 1 | O4: 65F铝合金门 | P4: =SUM(H3:H7) -> 107.78 | Q4: =R4/P4 -> 1184.9823 | R4: =SUM(J3:J7) -> 127717.39
A5: 3 | C5: WM2038-1 | D5: 2000 | E5: 3800 | F5: 1 | G5: 7.17 | H5: =F5*G5 -> 7.17 | I5: ='WM2038'!B371 -> 1143.12 | J5: =I5*H5 -> 8196.1704 | N5: 2 | O5: 65F铝合金窗 | P5: =SUM(H8:H15) -> 644.52 | Q5: =R5/P5 -> 1537.8533 | R5: =SUM(J8:J15) -> 991177.19
A6: 4 | B6: 外门联窗 | C6: MLC2030 | D6: 200 | E6: 3000 | F6: 2 | G6: 5.57 | H6: =F6*G6 -> 11.14 | I6: ='MLC2030'!B371 -> 1514.75 | J6: =I6*H6 -> 16874.315 | N6: 3 | O6: 125铝合金幕墙
A7: 5 | C7: MLC2522 | D7: 2500 | E7: 2200 | F7: 1 | G7: 4.6 | H7: =F7*G7 -> 4.6 | I7: ='MLC2522'!B371 -> 1223.98 | J7: =I7*H7 -> 5630.308 | N7: 4 | O7: 铝合金百叶窗 | P7: =SUM(H16:H22) -> 18.38 | Q7: =R7/P7 -> 964 | R7: =SUM(J16:J22) -> 17718.32
A8: 6 | B8: 平开窗 | C8: C2030 | D8: 2000 | E8: 3000 | F8: 12 | G8: 5.57 | H8: =F8*G8 -> 66.84 | I8: ='C2330'!B371 -> 1501.59 | J8: =I8*H8 -> 100366.28 | N8: 5 | O8: 通透格栅
A9: 7 | C9: C2038 | D9: 2000 | E9: 3B00 | F9: 5 | G9: 7.17 | H9: =F9*G9 -> 35.85 | I9: ='C2330'!B371 -> 1501.59 | J9: =I9*H9 -> 53832.001 | N9: 6 | O9: 防蚊纱窗 | P9: =SUM(H23) -> 123.818
A10: 8 | C10: C2330 | D10: 2300 | E10: 3000 | F10: 36 | G10: 6.33 | H10: =F10*G10 -> 227.88 | I10: ='C2330'!B371 -> 1501.59 | J10: =I10*H10 -> 342182.33 | N10: 7 | O10: 阳台铝合金栏杆m
A11: 9 | C11: C2338 | D11: 2300 | E11: 3800 | F11: 18 | G11: 8.17 | H11: =F11*G11 -> 147.06 | I11: ='C2330'!B371 -> 1501.59 | J11: =I11*H11 -> 220823.83 | N11: 8 | O11: 穿孔铝单板
A12: 10 | C12: C2038-BY | D12: 2000 | E12: 3800 | F12: 5 | G12: 7.17 | H12: =F12*G12 -> 35.85 | I12: ='C2330'!B371 -> 1501.59 | J12: =I12*H12 -> 53832.001 | N12: 9 | P12: =SUM(P4:P8) -> 770.68 | Q12: =R12/P12 -> 1474.8182 | R12: =SUM(R4:R7) -> 1136612.9
A13: 11 | C13: C2338-BY | D13: 2300 | E13: 3800 | F13: 11 | G13: 8.17 | H13: =F13*G13 -> 89.87 | I13: ='C2330'!B371 -> 1501.59 | J13: =I13*H13 -> 134947.89
A14: 12 | B14: 固定窗 | C14: XC1014 | D14: 1000 | E14: 1400 | F14: 30 | G14: 1.1 | H14: =F14*G14 -> 33 | I14: ='C1014'!B371 -> 2372.44 | J14: =I14*H14 -> 78290.52
A15: 13 | C15: GDC2338 | D15: 2300 | E15: 3800 | F15: 1 | G15: 8.17 | H15: =F15*G15 -> 8.17 | I15: ='GDC2338'!B371 -> 844.84 | J15: =I15*H15 -> 6902.3428
A16: 14 | B16: 百叶门窗 铝合金防雨百叶，通风率不小于70% | C16: BYC0507 | D16: 500 | E16: 700 | F16: 1 | G16: =0.5*0.7 -> 0.35 | H16: =F16*G16 -> 0.35 | I16: ='BYC0809'!G62 -> 964 | J16: =I16*H16 -> 337.4
A17: 15 | C17: BYC0809 | D17: 800 | E17: 900 | F17: 1 | G17: =0.8*0.9 -> 0.72 | H17: =F17*G17 -> 0.72 | I17: ='BYC0809'!G62 -> 964 | J17: =I17*H17 -> 694.08
A18: 16 | C18: BYC0907 | D18: 900 | E18: 700 | F18: 2 | G18: =0.9*0.7 -> 0.63 | H18: =F18*G18 -> 1.26 | I18: ='BYC0809'!G62 -> 964 | J18: =I18*H18 -> 1214.64
A19: 17 | C19: BYC2004 | D19: 2000 | E19: 400 | F19: 5 | G19: =2*0.4 -> 0.8 | H19: =F19*G19 -> 4 | I19: ='BYC0809'!G62 -> 964 | J19: =I19*H19 -> 3856
A20: 18 | C20: BYC2303 | D20: 230 | E20: 300 | F20: 5 | G20: =2.3*0.3 -> 0.69 | H20: =F20*G20 -> 3.45 | I20: ='BYC0809'!G62 -> 964 | J20: =I20*H20 -> 3325.8
A21: 19 | C21: BYC2805 | D21: 2800 | E21: 500 | F21: 2 | G21: =2.8*0.5 -> 1.4 | H21: =F21*G21 -> 2.8 | I21: ='BYC0809'!G62 -> 964 | J21: =I21*H21 -> 2699.2
A22: 20 | C22: BYC2905 | D22: 2900 | E22: 500 | F22: 4 | G22: =2.9*0.5 -> 1.45 | H22: =F22*G22 -> 5.8 | I22: ='BYC0809'!G62 -> 964 | J22: =I22*H22 -> 5591.2
A23: 21 | B23: 防蚊纱窗 | G23: 0.4 | H23: =SUM(H6:H13)*20% -> 123.818 | J23: =I23*H23 -> 0
A24: 22 | B24: 合计 | F24: =SUM(F3:F23) -> 153 | H24: =SUM(H3:H22) -> 770.68 | I24: =J24/H24 -> 1474.8182 | J24: =SUM(J3:J23) -> 1136612.9

Sheet 5#楼工程量统计
A1: 5#工程量统计
A2: 序号 | B2: 类型 | C2: 设计编号 | D2: 洞口宽(mm) | E2: 洞口高(mm) | F2: 数量 | G2: 单樘面积(㎡) | H2: 工程量(㎡) | I2: 成本单价 | J2: 成本合价 | K2: 备注
A3: 1 | B3: 防雨百叶窗 | C3: BYC0304 | D3: 300 | E3: 400 | F3: 6 | G3: =0.3*0.4 -> 0.12 | H3: =F3*G3 -> 0.72 | I3: ='BYC0624'!G62 -> 1004 | J3: =I3*H3 -> 722.88 | K3: 通风率不小于70%
A4: 2 | B4: 防雨百叶窗 | C4: BYC0305 | D4: 300 | E4: 500 | F4: 2 | G4: =0.3*0.5 -> 0.15 | H4: =F4*G4 -> 0.3 | I4: ='BYC0624'!G62 -> 1004 | J4: =I4*H4 -> 301.2 | M4: 序号 | N4: 窗型 | O4: 面积 | P4: 成本单价 | Q4: 成本合价
A5: 3 | B5: 防雨百叶窗 | C5: BYC0404 | D5: 400 | E5: 400 | F5: 3 | G5: =0.4*0.4 -> 0.16 | H5: =F5*G5 -> 0.48 | I5: ='BYC0624'!G62 -> 1004 | J5: =I5*H5 -> 481.92 | M5: 1 | N5: 65F铝合金门 | O5: =SUM(H24:H26,H28:H32) -> 1236.605 | P5: =Q5/O5 -> 1406.672 | Q5: =SUM(J24:J26,J28:J32) -> 1739497.6
A6: 4 | B6: 防雨百叶窗 | C6: BYC0704 | D6: 700 | E6: 400 | F6: 44 | G6: =0.7*0.4 -> 0.28 | H6: =F6*G6 -> 12.32 | I6: ='BYC0624'!G62 -> 1004 | J6: =I6*H6 -> 12369.28 | M6: 2 | N6: 65F铝合金窗 | O6: =SUM(H16:H22) -> 174.03 | P6: =Q6/O6 -> 1589.7681 | Q6: =SUM(J16:J22) -> 276667.34
A7: 5 | B7: 防雨百叶窗 | C7: BYC1212 | D7: 1200 | E7: 1200 | F7: 2 | G7: =1.2*1.2 -> 1.44 | H7: =F7*G7 -> 2.88 | I7: ='BYC0624'!G62 -> 1004 | J7: =I7*H7 -> 2891.52 | M7: 3 | N7: 125铝合金幕墙 | O7: =SUM(H23,H27) -> 211.68 | P7: =Q7/O7 -> 1118.645 | Q7: =SUM(J23,J27) -> 236794.77
A8: 6 | B8: 防雨百叶窗 | C8: BYC1204 | D8: 1200 | E8: 400 | F8: 4 | G8: =1.2*0.4 -> 0.48 | H8: =F8*G8 -> 1.92 | I8: ='BYC0624'!G62 -> 1004 | J8: =I8*H8 -> 1927.68 | M8: 4 | N8: 铝合金百叶窗 | O8: =SUM(H3:H15) -> 329.84 | P8: =Q8/O8 -> 1004 | Q8: =SUM(J3:J15) -> 331159.36
A9: 7 | B9: 防雨百叶窗 | C9: BYC0410 | D9: 400 | E9: 1000 | F9: 15 | G9: =0.4*1 -> 0.4 | H9: =F9*G9 -> 6 | I9: ='BYC0624'!G62 -> 1004 | J9: =I9*H9 -> 6024 | M9: 5 | N9: 通透格栅
A10: 8 | B10: 防雨百叶窗 | C10: BYC1720 | D10: 1700 | E10: 2000 | F10: 1 | G10: =1.7*2 -> 3.4 | H10: =F10*G10 -> 3.4 | I10: ='BYC0624'!G62 -> 1004 | J10: =I10*H10 -> 3413.6 | M10: 6 | N10: 防蚊纱窗 | O10: =SUM(H33) -> 121.6
A11: 9 | B11: 防雨百叶窗 | C11: BYC2338 | D11: 2300 | E11: 3800 | F11: 2 | G11: 8.17 | H11: =F11*G11 -> 16.34 | I11: ='BYC0624'!G62 -> 1004 | J11: =I11*H11 -> 16405.36 | M11: 7 | N11: 阳台铝合金栏杆m | O11: =SUM(H34) -> 483.3
A12: 10 | B12: 防雨百叶窗 | C12: BYC1720-1 | D12: 1650 | E12: 2000 | F12: 1 | G12: =1.65*2 -> 3.3 | H12: =F12*G12 -> 3.3 | I12: ='BYC0624'!G62 -> 1004 | J12: =I12*H12 -> 3313.2 | M12: 8 | N12: 穿孔铝单板 | O12: =SUM(H35) -> 135
A13: 11 | B13: 防雨百叶窗 | C13: BYC1522 | D13: 1500 | E13: 2200 | F13: 1 | G13: =1.5*2.2 -> 3.3 | H13: =F13*G13 -> 3.3 | I13: ='BYC0624'!G62 -> 1004 | J13: =I13*H13 -> 3313.2 | M13: 9 | O13: =SUM(O5:O9) -> 1952.155 | P13: =Q13/O13 -> 1323.7264 | Q13: =SUM(Q5:Q8) -> 2584119.1
A14: 12 | B14: 防雨百叶窗 | C14: BYC2012 | D14: 2000 | E14: 1200 | F14: 1 | G14: =1.2*2 -> 2.4 | H14: =F14*G14 -> 2.4 | I14: ='BYC0624'!G62 -> 1004 | J14: =I14*H14 -> 2409.6
A15: 13 | B15: 防雨百叶门 | C15: BYC0624 | D15: 600 | E15: 2400 | F15: 192 | G15: =0.6*2.4 -> 1.44 | H15: =F15*G15 -> 276.48 | I15: ='BYC0624'!G62 -> 1004 | J15: =I15*H15 -> 277585.92
A16: 14 | B16: 外窗 | C16: C0410 | D16: 400 | E16: 1000 | F16: 9 | G16: =0.4*1 -> 0.4 | H16: =F16*G16 -> 3.6 | I16: ='C0410'!B371 -> 1733.48 | J16: =I16*H16 -> 6240.528
A17: 15 | B17: 外窗 | C17: GDC1212 | D17: 1200 | E17: 1200 | F17: 2 | G17: =1.2*1.2 -> 1.44 | H17: =F17*G17 -> 2.88 | I17: ='GDC1212'!B371 -> 800.5 | J17: =I17*H17 -> 2305.44
A18: 16 | B18: 外窗 | C18: C1217 | D18: 1200 | E18: 1700 | F18: 2 | G18: 1.6 | H18: =F18*G18 -> 3.2 | I18: ='C1014'!B371 -> 2372.44 | J18: =I18*H18 -> 7591.808
A19: 17 | B19: 外窗 | C19: C1938 | D19: 1900 | E19: 3800 | F19: 2 | G19: 6.83 | H19: =F19*G19 -> 13.66 | I19: ='C2330'!B371 -> 1501.59 | J19: =I19*H19 -> 20511.719
A20: 18 | B20: 外窗 | C20: GDC2327 | D20: 2300 | E20: 2650 | F20: 6 | G20: =2.3*2.65 -> 6.095 | H20: =F20*G20 -> 36.57 | I20: ='C2327'!B371 -> 1662.65 | J20: =I20*H20 -> 60803.111
A21: 19 | B21: 外窗 | C21: C2327 | D21: 2300 | E21: 2650 | F21: 8 | G21: =2.3*2.65 -> 6.095 | H21: =F21*G21 -> 48.76 | I21: ='C2327'!B371 -> 1662.65 | J21: =I21*H21 -> 81070.814
A22: 20 | B22: 外窗 | C22: C2338 | D22: 2300 | E22: 3800 | F22: 8 | G22: 8.17 | H22: =F22*G22 -> 65.36 | I22: ='C2330'!B371 -> 1501.59 | J22: =I22*H22 -> 98143.922
A23: 21 | B23: 外窗框 | C23: C2360 | D23: 2300 | E23: 6000 | F23: 12 | G23: 13.23 | H23: =F23*G23 -> 158.76 | I23: ='C2360'!G126 -> 1096.81 | J23: =I23*H23 -> 174129.56 | L23: 125幕墙
A24: 22 | B24: 外门联窗 | C24: MLC2324 | D24: 2300 | E24: 2400 | F24: 190 | G24: =2.3*2.4 -> 5.52 | H24: =F24*G24 -> 1048.8 | I24: ='MLC2324'!B371 -> 1417.48 | J24: =I24*H24 -> 1486653
A25: 23 | B25: 外门联窗 | C25: MLC2327 | D25: 2300 | E25: 2650 | F25: 11 | G25: =2.3*2.65 -> 6.095 | H25: =F25*G25 -> 67.045 | I25: ='MLC2324'!B371 -> 1417.48 | J25: =I25*H25 -> 95034.947
A26: 24 | B26: 外门联窗 | C26: MLC2324A | D26: 2300 | E26: 2400 | F26: 2 | G26: =2.3*2.4 -> 5.52 | H26: =F26*G26 -> 11.04 | I26: ='MLC2324'!B371 -> 1417.48 | J26: =I26*H26 -> 15648.979
A27: 25 | B27: 外门联窗框 | C27: MLC2360 | D27: 2300 | E27: 6000 | F27: 4 | G27: 13.23 | H27: =F27*G27 -> 52.92 | I27: ='MLC2360'!G126 -> 1184.15 | J27: =I27*H27 -> 62665.218 | L27: 125幕墙
A28: 26 | B28: 外门 | C28: WM1122 | D28: 1100 | E28: 2200 | F28: 3 | G28: =1.1*2.2 -> 2.42 | H28: =F28*G28 -> 7.26 | I28: ='WM1325'!B371 -> 1524.32 | J28: =I28*H28 -> 11066.563
A29: 27 | B29: 外门 | C29: WM1222 | D29: 1200 | E29: 2200 | F29: 2 | G29: =1.2*2.2 -> 2.64 | H29: =F29*G29 -> 5.28 | I29: ='WM1325'!B371 -> 1524.32 | J29: =I29*H29 -> 8048.4096
A30: 28 | B30: 外门 | C30: WM1325 | D30: 1300 | E30: 2450 | F30: 2 | G30: =1.3*2.45 -> 3.185 | H30: =F30*G30 -> 6.37 | I30: ='WM1325'!B371 -> 1524.32 | J30: =I30*H30 -> 9709.9184
A31: 29 | B31: 外门 | C31: WM1824 | D31: 1800 | E31: 2400 | F31: 4 | G31: =1.8*2.4 -> 4.32 | H31: =F31*G31 -> 17.28 | I31: ='WM1325'!B371 -> 1524.32 | J31: =I31*H31 -> 26340.25
A32: 30 | B32: 外门 | C32: WM2338 | D32: 2300 | E32: 3800 | F32: 9 | G32: 8.17 | H32: =F32*G32 -> 73.53 | I32: ='WM2338'!B371 -> 1183.13 | J32: =I32*H32 -> 86995.549
A33: 31 | B33: 防蚊纱窗 | C33: MLC2324 | D33: 400 | E33: 800 | F33: =190*2 -> 380 | G33: =0.4*0.8 -> 0.32 | H33: =F33*G33 -> 121.6
A34: 32 | B34: 阳台铝合金栏杆m | F34: 3 | G34: =(160.55+81.1)*2/3 -> 161.1 | H34: =F34*G34 -> 483.3
A35: 33 | B35: =[29]工程量清单计价表!B129 -> 穿孔铝单板 | F35: 18 | G35: 7.5 | H35: =F35*G35 -> 135
A36: 34 | B36: 合计 | F36: =SUM(F3:F32) -> 550 | H36: =SUM(H3:H32) -> 1952.155 | I36: =J36/H36 -> 1323.7264 | J36: =SUM(J3:J32) -> 2584119.1

Sheet 6#楼工程量统计 
A1: 6#工程量统计
A2: 序号 | B2: 类型 | C2: 设计编号 | D2: 洞口宽(mm) | E2: 洞口高(mm) | F2: 数量 | G2: 单樘面积(㎡) | H2: 工程量(㎡) | I2: 成本单价 | J2: 成本合价 | K2: 备注
A3: 1 | B3: 防雨百叶窗 | C3: BYC0304 | D3: 300 | E3: 400 | F3: 14 | G3: =0.3*0.4 -> 0.12 | H3: =F3*G3 -> 1.68 | I3: ='BYC0624'!G62 -> 1004 | J3: =I3*H3 -> 1686.72 | K3: 通风率不小于70%
A4: 2 | B4: 防雨百叶窗 | C4: BYC0504 | D4: 450 | E4: 400 | F4: 2 | G4: =0.45*0.4 -> 0.18 | H4: =F4*G4 -> 0.36 | I4: ='BYC0624'!G62 -> 1004 | J4: =I4*H4 -> 361.44 | M4: 序号 | N4: 窗型 | O4: 面积 | P4: 成本单价 | Q4: 成本合价
A5: 3 | B5: 防雨百叶窗 | C5: BYC0704 | D5: 700 | E5: 400 | F5: 88 | G5: =0.7*0.4 -> 0.28 | H5: =F5*G5 -> 24.64 | I5: ='BYC0624'!G62 -> 1004 | J5: =I5*H5 -> 24738.56 | M5: 1 | N5: 65F铝合金门 | O5: =SUM(H18:H28) -> 2384.43 | P5: =Q5/O5 -> 1463.4744 | Q5: =SUM(J18:J28) -> 3489552.3
A6: 4 | B6: 防雨百叶窗 | C6: BYC1004 | D6: 950 | E6: 400 | F6: 2 | G6: =0.95*0.4 -> 0.38 | H6: =F6*G6 -> 0.76 | I6: ='BYC0624'!G62 -> 1004 | J6: =I6*H6 -> 763.04 | M6: 2 | N6: 65F铝合金窗 | O6: =SUM(H10:H16) -> 393.89 | P6: =Q6/O6 -> 1594.5882 | Q6: =SUM(J10:J16) -> 628092.36
A7: 5 | B7: 防雨百叶窗 | C7: BYC1212 | D7: 1200 | E7: 1200 | F7: 4 | G7: =1.2*1.2 -> 1.44 | H7: =F7*G7 -> 5.76 | I7: ='BYC0624'!G62 -> 1004 | J7: =I7*H7 -> 5783.04 | M7: 3 | N7: 125铝合金幕墙 | O7: =SUM(H17,H29) -> 277.83 | P7: =Q7/O7 -> 1105.1281 | Q7: =SUM(J17,J29) -> 307037.74
A8: 6 | B8: 防雨百叶窗 | C8: BYC2220 | D8: 2200 | E8: 2000 | F8: 4 | G8: =2*2.2 -> 4.4 | H8: =F8*G8 -> 17.6 | I8: ='BYC0624'!G62 -> 1004 | J8: =I8*H8 -> 17670.4 | M8: 4 | N8: 铝合金百叶窗 | O8: =SUM(H3:H9) -> 603.76 | P8: =Q8/O8 -> 1004 | Q8: =SUM(J3:J9) -> 606175.04
A9: 7 | B9: 防雨百叶门 | C9: BYM0624 | D9: 600 | E9: 2400 | F9: 384 | G9: =0.6*2.4 -> 1.44 | H9: =F9*G9 -> 552.96 | I9: ='BYC0624'!G62 -> 1004 | J9: =I9*H9 -> 555171.84 | M9: 5 | N9: 通透格栅
A10: 8 | B10: 外窗 | C10: C0410 | D10: 400 | E10: 1200 | F10: 15 | G10: =0.4*1.2 -> 0.48 | H10: =F10*G10 -> 7.2 | I10: ='C0410'!B371 -> 1733.48 | J10: =I10*H10 -> 12481.056 | M10: 6 | N10: 防蚊纱窗 | O10: =SUM(H30) -> 128
A11: 9 | B11: 外窗 | C11: C1212 | D11: 1200 | E11: 1200 | F11: 4 | G11: =1.2*1.2 -> 1.44 | H11: =F11*G11 -> 5.76 | I11: ='GDC1212'!B371 -> 800.5 | J11: =I11*H11 -> 4610.88 | M11: 7 | N11: 阳台铝合金栏杆m | O11: =SUM(H31) -> 985.8
A12: 10 | B12: 外窗 | C12: C1217 | D12: 1200 | E12: 1700 | F12: 12 | G12: 1.6 | H12: =F12*G12 -> 19.2 | I12: ='C1014'!B371 -> 2372.44 | J12: =I12*H12 -> 45550.848 | M12: 8 | N12: 穿孔铝单板 | O12: =SUM(H32) -> 210
A13: 11 | B13: 外窗 | C13: C1938 | D13: 1900 | E13: 3800 | F13: 4 | G13: 6.83 | H13: =F13*G13 -> 27.32 | I13: ='C2330'!B371 -> 1501.59 | J13: =I13*H13 -> 41023.439 | M13: 9 | O13: =SUM(O5:O9) -> 3659.91 | P13: =Q13/O13 -> 1374.585 | Q13: =SUM(Q5:Q8) -> 5030857.4
A14: 12 | B14: 外窗 | C14: C2127 | D14: 2100 | E14: 2650 | F14: 15 | G14: =2.1*2.65 -> 5.565 | H14: =F14*G14 -> 83.475 | I14: ='C2327'!B371 -> 1662.65 | J14: =I14*H14 -> 138789.71
A15: 13 | B15: 外窗 | C15: C2327 | D15: 2300 | E15: 2650 | F15: 9 | G15: =2.3*2.65 -> 6.095 | H15: =F15*G15 -> 54.855 | I15: ='C2327'!B371 -> 1662.65 | J15: =I15*H15 -> 91204.666
A16: 14 | B16: 外窗 | C16: C2338 | D16: 2300 | E16: 3800 | F16: 24 | G16: 8.17 | H16: =F16*G16 -> 196.08 | I16: ='C2330'!B371 -> 1501.59 | J16: =I16*H16 -> 294431.77
A17: 15 | B17: 外门框 | C17: C2360 | D17: 2300 | E17: 6000 | F17: 19 | G17: 13.23 | H17: =F17*G17 -> 251.37 | I17: ='C2360'!G126 -> 1096.81 | J17: =I17*H17 -> 275705.13 | L17: 125幕墙
A18: 16 | B18: 外门 | C18: WM1122 | D18: 1100 | E18: 2200 | F18: 4 | G18: =1.1*2.2 -> 2.42 | H18: =F18*G18 -> 9.68 | I18: ='WM1325'!B371 -> 1524.32 | J18: =I18*H18 -> 14755.418
A19: 17 | B19: 外门 | C19: WM1522 | D19: 1500 | E19: 2200 | F19: 2 | G19: =1.5*2.2 -> 3.3 | H19: =F19*G19 -> 6.6 | I19: ='WM1325'!B371 -> 1524.32 | J19: =I19*H19 -> 10060.512
A20: 18 | B20: 外门 | C20: WM2324 | D20: 2300 | E20: 2400 | F20: 2 | G20: =2.3*2.4 -> 5.52 | H20: =F20*G20 -> 11.04 | I20: ='WM1325'!B371 -> 1524.32 | J20: =I20*H20 -> 16828.493 | K20: 其中2个为消防救援窗口
A21: 19 | B21: 外门 | C21: WM2338 | D21: 2300 | E21: 3800 | F21: 20 | G21: 8.17 | H21: =F21*G21 -> 163.4 | I21: ='WM2338'!B371 -> 1183.13 | J21: =I21*H21 -> 193323.44
A22: 20 | B22: 外门联窗 | C22: MLC2124 | D22: 2100 | E22: 2400 | F22: 160 | G22: =2.1*2.4 -> 5.04 | H22: =F22*G22 -> 806.4 | I22: ='MLC2124'!B371 -> 1599.79 | J22: =I22*H22 -> 1290070.7
A23: 21 | B23: 外门联窗 | C23: MLC2324 | D23: 2300 | E23: 2400 | F23: =220-F24 -> 180 | G23: =2.3*2.4 -> 5.52 | H23: =F23*G23 -> 993.6 | I23: =MLC2324A!B371 -> 1415.54 | J23: =I23*H23 -> 1406480.5
A24: 22 | B24: 外门联窗 | C24: MLC2324 | D24: 2300 | E24: 2400 | F24: 40 | G24: =2.3*2.4 -> 5.52 | H24: =F24*G24 -> 220.8 | I24: ='MLC2324'!B371 -> 1417.48 | J24: =I24*H24 -> 312979.58 | K24: 40个为消防救援窗口
A25: 23 | B25: 外门联窗 | C25: MLC2127 | D25: 2100 | E25: 2650 | F25: 14 | G25: =2.1*2.65 -> 5.565 | H25: =F25*G25 -> 77.91 | I25: ='MLC2324'!B371 -> 1417.48 | J25: =I25*H25 -> 110435.87
A26: 24 | B26: 外门联窗 | C26: MLC2327 | D26: 2300 | E26: 2650 | F26: 8 | G26: =2.3*2.65 -> 6.095 | H26: =F26*G26 -> 48.76 | I26: ='MLC2324'!B371 -> 1417.48 | J26: =I26*H26 -> 69116.325
A27: 25 | B27: 外门联窗 | C27: MLC2324A | D27: 2300 | E27: 2400 | F27: 4 | G27: =2.3*2.4 -> 5.52 | H27: =F27*G27 -> 22.08 | I27: =MLC2324A!B371 -> 1415.54 | J27: =I27*H27 -> 31255.123
A28: 26 | B28: 外门联窗 | C28: MLC2355 | D28: 2300 | E28: 5500 | F28: 2 | G28: 12.08 | H28: =F28*G28 -> 24.16 | I28: ='MLC2324'!B371 -> 1417.48 | J28: =I28*H28 -> 34246.317 | K28: 此门联窗为消防救援窗口
A29: 27 | B29: 外门联窗框 | C29: MLC2360 | D29: 2300 | E29: 6000 | F29: 2 | G29: 13.23 | H29: =F29*G29 -> 26.46 | I29: ='MLC2360'!G126 -> 1184.15 | J29: =I29*H29 -> 31332.609 | L29: 125幕墙
A30: 28 | B30: 防蚊纱窗 | C30: MLC2124 | D30: 500 | E30: 800 | F30: =160*2 -> 320 | G30: =0.5*0.8 -> 0.4 | H30: =F30*G30 -> 128
A31: 29 | B31: 阳台铝合金栏杆m | F31: 3 | G31: =(329.24+163.66)*2/3 -> 328.6 | H31: =F31*G31 -> 985.8
A32: 30 | B32: =[29]工程量清单计价表!B161 -> 穿孔铝单板 | F32: 28 | G32: 7.5 | H32: =F32*G32 -> 210
A33: 31 | B33: 合计 | F33: =SUM(F3:F29) -> 1038 | H33: =SUM(H3:H29) -> 3659.91 | I33: =J33/H33 -> 1374.585 | J33: =SUM(J3:J29) -> 5030857.4

Sheet 8#楼工程量统计
A1: 8#工程量统计
A2: 序号 | B2: 类型 | C2: 设计编号 | D2: 洞口宽(mm) | E2: 洞口高(mm) | F2: 数量 | G2: 单樘面积(㎡) | H2: 工程量(㎡) | I2: 成本单价 | J2: 成本合价 | K2: 备注
A3: 1 | B3: 外门 | C3: WM1127 | D3: 1100 | E3: 2650 | F3: 4 | G3: 2.785 | H3: =F3*G3 -> 11.14 | I3: ='WM1127'!B371 -> 1663.91 | J3: =I3*H3 -> 18535.957
A4: 2 | C4: WM1130-XF | D4: 1100 | E4: 3000 | F4: 2 | G4: 3.17 | H4: =F4*G4 -> 6.34 | I4: ='WM1127'!B371 -> 1663.91 | J4: =I4*H4 -> 10549.189 | M4: 序号 | N4: 窗型 | O4: 面积 | P4: 成本单价 | Q4: 成本合价
A5: 3 | C5: WM1224 | D5: 1200 | E5: 2400 | F5: 1 | G5: =1.2*2.4 -> 2.88 | H5: =F5*G5 -> 2.88 | I5: ='WM1127'!B371 -> 1663.91 | J5: =I5*H5 -> 4792.0608 | M5: 1 | N5: 65F铝合金门 | O5: =SUM(H3:H6) -> 40.91 | P5: =Q5/O5 -> 1663.91 | Q5: =SUM(J3:J6) -> 68070.558
A6: 4 | C6: WM1840 | D6: 1800 | E6: 4000 | F6: 3 | G6: 6.85 | H6: =F6*G6 -> 20.55 | I6: ='WM1127'!B371 -> 1663.91 | J6: =I6*H6 -> 34193.351 | M6: 2 | N6: 65F铝合金窗 | O6: =SUM(H16:H35) -> 979.36 | P6: =Q6/O6 -> 1507.9929 | Q6: =SUM(J16:J35) -> 1476867.9
A7: 5 | C7: WM2888 | D7: 2800 | E7: 8800 | F7: 4 | G7: 23.8 | H7: =F7*G7 -> 95.2 | I7: ='MLC2888'!G126 -> 1722.2 | J7: =I7*H7 -> 163953.44 | L7: 125幕墙 | M7: 3 | N7: 125铝合金幕墙 | O7: =SUM(H7:H8) -> 190.4 | P7: =Q7/O7 -> 1722.2 | Q7: =SUM(J7:J8) -> 327906.88
A8: 6 | C8: WM2888-w | D8: 2800 | E8: 8800 | F8: 4 | G8: 23.8 | H8: =F8*G8 -> 95.2 | I8: ='MLC2888'!G126 -> 1722.2 | J8: =I8*H8 -> 163953.44 | K8: 无障碍外门 | L8: 125幕墙 | M8: 4 | N8: 铝合金百叶窗 | O8: =SUM(H9:H15) -> 54.83 | P8: =Q8/O8 -> 794 | Q8: =SUM(J9:J15) -> 43535.02
A9: 7 | B9: 百叶窗 铝合金防雨百叶 | C9: BYC0804 | D9: 800 | E9: 350 | F9: 4 | G9: =0.8*0.35 -> 0.28 | H9: =F9*G9 -> 1.12 | I9: ='BYC1610'!G62 -> 794 | J9: =I9*H9 -> 889.28 | M9: 5 | N9: 通透格栅 | O9: =SUM(H36:H37) -> 174.42 | P9: =Q9/O9 -> 1117.43 | Q9: =SUM(J36:J37) -> 194902.14
A10: 8 | C10: BYC1130 | D10: 1100 | E10: 3000 | F10: 5 | G10: 3.17 | H10: =F10*G10 -> 15.85 | I10: ='BYC1610'!G62 -> 794 | J10: =I10*H10 -> 12584.9 | M10: 6 | N10: 防蚊纱窗 | O10: =SUM(H38) -> 162.69
A11: 9 | C11: BYC1209 | D11: 1200 | E11: 900 | F11: 2 | G11: =1.2*0.9 -> 1.08 | H11: =F11*G11 -> 2.16 | I11: ='BYC1610'!G62 -> 794 | J11: =I11*H11 -> 1715.04 | M11: 7 | N11: 阳台铝合金栏杆m | O11: =SUM(H39) -> 168
A12: 10 | C12: BYC1508 | D12: 1500 | E12: 800 | F12: 1 | G12: =1.5*0.8 -> 1.2 | H12: =F12*G12 -> 1.2 | I12: ='BYC1610'!G62 -> 794 | J12: =I12*H12 -> 952.8 | M12: 8 | N12: 穿孔铝单板
A13: 11 | C13: BYC1610 | D13: 1600 | E13: 1000 | F13: 1 | G13: =1.6*1 -> 1.6 | H13: =F13*G13 -> 1.6 | I13: ='BYC1610'!G62 -> 794 | J13: =I13*H13 -> 1270.4 | M13: 9 | O13: =SUM(O5:O9) -> 1439.92 | P13: =Q13/O13 -> 1466.2499 | Q13: =SUM(Q5:Q12) -> 2111282.5
A14: 12 | C14: BYC2435 | D14: 2400 | E14: 3500 | F14: 2 | G14: 7.78 | H14: =F14*G14 -> 15.56 | I14: ='BYC1610'!G62 -> 794 | J14: =I14*H14 -> 12354.64
A15: 13 | C15: BYC2735 | D15: 2700 | E15: 3500 | F15: 2 | G15: 8.67 | H15: =F15*G15 -> 17.34 | I15: ='BYC1610'!G62 -> 794 | J15: =I15*H15 -> 13767.96
A16: 14 | B16: 外窗 | C16: C1014 | D16: 1000 | E16: 1400 | F16: 17 | G16: 1.1 | H16: =F16*G16 -> 18.7 | I16: ='C1014'!B371 -> 2372.44 | J16: =I16*H16 -> 44364.628 | K16: 固定
A17: 15 | C17: C1125 | D17: 1100 | E17: 2450 | F17: 8 | G17: 2.455 | H17: =F17*G17 -> 19.64 | I17: ='C1127'!B371 -> 1558.89 | J17: =I17*H17 -> 30616.6 | K17: 外平开
A18: 16 | C18: C1127 | D18: 1100 | E18: 2650 | F18: 60 | G18: 2.785 | H18: =F18*G18 -> 167.1 | I18: ='C1127'!B371 -> 1558.89 | J18: =I18*H18 -> 260490.52 | K18: 外平开
A19: 17 | C19: C1130 | D19: 1100 | E19: 3000 | F19: 41 | G19: 3.17 | H19: =F19*G19 -> 129.97 | I19: ='C1127'!B371 -> 1558.89 | J19: =I19*H19 -> 202608.93 | K19: 外平开
A20: 18 | C20: C2430 | D20: 2400 | E20: 3000 | F20: 2 | G20: 6.58 | H20: =F20*G20 -> 13.16 | I20: ='C2430'!B371 -> 1459.77 | J20: =I20*H20 -> 19210.573 | K20: 外平开
A21: 19 | C21: C2435 | D21: 2400 | E21: 3500 | F21: 3 | G21: 7.78 | H21: =F21*G21 -> 23.34 | I21: ='C2430'!B371 -> 1459.77 | J21: =I21*H21 -> 34071.032 | K21: 外平开
A22: 20 | C22: C2729 | D22: 2700 | E22: 2900 | F22: 1 | G22: 7.05 | H22: =F22*G22 -> 7.05 | I22: ='C2430'!B371 -> 1459.77 | J22: =I22*H22 -> 10291.378 | K22: 外平开
A23: 21 | C23: C2735 | D23: 2700 | E23: 3500 | F23: 27 | G23: 8.67 | H23: =F23*G23 -> 234.09 | I23: ='C2430'!B371 -> 1459.77 | J23: =I23*H23 -> 341717.56 | K23: 外平开
A24: 22 | C24: C2740 | D24: 2700 | E24: 4000 | F24: 20 | G24: 10.02 | H24: =F24*G24 -> 200.4 | I24: ='C2430'!B371 -> 1459.77 | J24: =I24*H24 -> 292537.91 | K24: 外平开
A25: 23 | B25: 外窗（局部百叶） | C25: C1814-BY | D25: 1800 | E25: 1400 | F25: 1 | G25: =1.8*1.4 -> 2.52 | H25: =F25*G25 -> 2.52 | I25: ='GDC2338'!B371 -> 844.84 | J25: =I25*H25 -> 2128.9968
A26: 24 | C26: C2438-BY | D26: 2400 | E26: 3800 | F26: 2 | G26: 8.5 | H26: =F26*G26 -> 17 | I26: ='GDC2338'!B371 -> 844.84 | J26: =I26*H26 -> 14362.28
A27: 25 | C27: C2735-BY | D27: 2700 | E27: 3500 | F27: 1 | G27: 8.67 | H27: =F27*G27 -> 8.67 | I27: ='GDC2338'!B371 -> 844.84 | J27: =I27*H27 -> 7324.7628
A28: 26 | C28: C2738-BY | D28: 2700 | E28: 3800 | F28: 1 | G28: 9.48 | H28: =F28*G28 -> 9.48 | I28: ='GDC2338'!B371 -> 844.84 | J28: =I28*H28 -> 8009.0832
A29: 27 | C29: C2740-BY | D29: 2700 | E29: 4000 | F29: 1 | G29: 10.02 | H29: =F29*G29 -> 10.02 | I29: ='GDC2338'!B371 -> 844.84 | J29: =I29*H29 -> 8465.2968
A30: 28 | B30: 高窗 | C30: GC2006 | D30: 1950 | E30: 600 | F30: 31 | G30: =1.95*0.6 -> 1.17 | H30: =F30*G30 -> 36.27 | I30: ='GC2006'!B371 -> 2162.9 | J30: =I30*H30 -> 78448.383 | K30: 固定
A31: 29 | C31: GC2009 | D31: 1950 | E31: 900 | F31: 20 | G31: =1.95*0.9 -> 1.755 | H31: =F31*G31 -> 35.1 | I31: ='GC2006'!B371 -> 2162.9 | J31: =I31*H31 -> 75917.79 | K31: 固定
A32: 30 | B32: 固定窗 | C32: GDC1014 | D32: 1000 | E32: 1400 | F32: 4 | G32: 1.1 | H32: =F32*G32 -> 4.4 | I32: ='C1014'!B371 -> 2372.44 | J32: =I32*H32 -> 10438.736
A33: 31 | C33: GDC1838 | D33: 1800 | E33: 3800 | F33: 1 | G33: 6.49 | H33: =F33*G33 -> 6.49 | I33: ='GDC2338'!B371 -> 844.84 | J33: =I33*H33 -> 5483.0116
A34: 32 | C34: GDC2438 | D34: 2400 | E34: 3800 | F34: 2 | G34: 8.5 | H34: =F34*G34 -> 17 | I34: ='GDC2338'!B371 -> 844.84 | J34: =I34*H34 -> 14362.28
A35: 33 | C35: GDC2738 | D35: 2700 | E35: 3800 | F35: 2 | G35: 9.48 | H35: =F35*G35 -> 18.96 | I35: ='GDC2338'!B371 -> 844.84 | J35: =I35*H35 -> 16018.166
A36: 34 | B36: 通透格栅 | C36: GS7638 | D36: 7600 | E36: 3800 | F36: 4 | G36: =7.6*3.8 -> 28.88 | H36: =F36*G36 -> 115.52 | I36: ='GSM7838'!B371 -> 1117.43 | J36: =I36*H36 -> 129085.51
A37: 35 | C37: GSM7838 | D37: 7750 | E37: 3800 | F37: 2 | G37: =7.75*3.8 -> 29.45 | H37: =F37*G37 -> 58.9 | I37: =I36 -> 1117.43 | J37: =I37*H37 -> 65816.627
A38: 36 | B38: 防蚊纱窗 | G38: 0.48 | H38: =SUM(H16:H24)*20% -> 162.69
A39: 37 | B39: 阳台铝合金栏杆m | F39: 1 | G39: =(67.2+58.8)*2*2/3 -> 168 | H39: =F39*G39 -> 168
A40: 38 | B40: 合计 | F40: =SUM(F3:F37) -> 286 | H40: =SUM(H3:H37) -> 1439.92 | J40: =SUM(J3:J39) -> 2111282.5

Sheet 穿孔铝板
A1: 综合单价分析表1.3
A2: 分项名称： | D2: 3.0mm双面氟碳喷涂穿孔铝单板1 | I2: 计量单位 | J2: m2/元
A3: 序号 | B3: 项目名称 | E3: 材质、规格 | F3: 单位 | G3: 单位 含量 | H3: 单价(元) | I3: 合计(元) | J3: 备注
A4: 一 | B4: 直接费 | C4: 材 料 费 | D4: 3.0mm双面氟碳喷涂穿孔铝单板1 | E4: =VLOOKUP(D4,[30]材料表!$B$4:$F$75,2,0) -> 3.0mm，双面氟碳喷涂 | F4: =VLOOKUP(D4,[30]材料表!$B$4:$F$75,3,0) -> m2 | G4: 1.03 | H4: 320 | I4: =G4*H4 -> 329.6
D5: 40*40*3热镀锌钢方通 | E5: =VLOOKUP(D5,[30]材料表!$B$4:$F$75,2,0) -> 40*40*3 | F5: =VLOOKUP(D5,[30]材料表!$B$4:$F$75,3,0) -> kg | G5: 1.36 | H5: 10 | I5: =G5*H5 -> 13.6
D6: L40*4热镀锌角钢 | E6: =VLOOKUP(D6,[30]材料表!$B$4:$F$75,2,0) -> L40*4 | F6: =VLOOKUP(D6,[30]材料表!$B$4:$F$75,3,0) -> kg | G6: 6.84 | H6: 10 | I6: =G6*H6 -> 68.4
D7: L50*5热镀锌角钢 | E7: =VLOOKUP(D7,[30]材料表!$B$4:$F$75,2,0) -> L50*5 | F7: =VLOOKUP(D7,[30]材料表!$B$4:$F$75,3,0) -> kg | G7: 4.39 | H7: 10 | I7: =G7*H7 -> 43.9
D8: 160*80*8后置埋件 | E8: =VLOOKUP(D8,[30]材料表!$B$4:$F$75,2,0) -> 160*80*8 | F8: =VLOOKUP(D8,[30]材料表!$B$4:$F$75,3,0) -> 块 | G8: 1.86 | H8: 35 | I8: =G8*H8 -> 65.1
D9: M12*160化学锚栓 | E9: =VLOOKUP(D9,[30]材料表!$B$4:$F$75,2,0) -> M12*160 | F9: =VLOOKUP(D9,[30]材料表!$B$4:$F$75,3,0) -> 套 | G9: 1.95 | H9: 10 | I9: =G9*H9 -> 19.5
D10: 硅酮耐候密封胶（500ml/支） | E10: =VLOOKUP(D10,[30]材料表!$B$4:$F$75,2,0) -> 500ml/支 | F10: =VLOOKUP(D10,[30]材料表!$B$4:$F$75,3,0) -> 支 | G10: 1.21 | H10: 16.5 | I10: =G10*H10 -> 19.965
D11: 自攻螺钉 | F11: =VLOOKUP(D11,[30]材料表!$B$4:$F$75,3,0) -> 颗 | G11: 25 | H11: 0.01 | I11: =G11*H11 -> 0.25
D12: 其他材料 | F12: =VLOOKUP(D12,[30]材料表!$B$4:$F$75,3,0) -> 项 | G12: 1 | H12: 10 | I12: =G12*H12 -> 10
D13: 防雷处理 | F13: =VLOOKUP(D13,[30]材料表!$B$4:$F$75,3,0) -> 项 | G13: 1 | H13: 5 | I13: =G13*H13 -> 5
D27: 合计 | I27: =SUM(I4:I26) -> 575.315
C28: 人工费 | F28: 元 | I28: 95
C29: 机械费 | F29: 元 | I29: 10
B30: 本项小计 | F30: 元 | I30: =SUM(I27:I29) -> 680.315
A31: 二 | B31: 管理费 | E31: （一）* 4% | F31: 元 | I31: =I30*$K$2 -> 0
A32: 三 | B32: 利润 | E32: （一+二）* 5% | F32: 元 | I32: =(I31+I30)*5% -> 34.01575
A33: 四 | B33: 税金 | E33: （一+二+三）* 3.43% | F33: 元 | I33: =SUM(I30:I32)*$M$2 -> 0
A34: 五 | B34: 单位造价合计 | E34: （一+二+三+四） | F34: 元 | I34: =SUM(I30:I33) -> 714.33075
A36: 综合单价分析表（每款门窗、幕墙、栏杆都需填报）（此表为门窗的示范表格，请根据各项目特征自行修改主材、辅材、其他费用名称及单位）
A37: 项目： | B37: 铝板 | G37: 综合单价： | H37: =H60 -> 854.51189 | I37: 元/㎡
A38: 序号 | B38: 项目名称 | C38: 材料名称 | D38: 数量 | E38: 单位 | F38: 损耗 | G38: 单价（元） | H38: 合价（元） | I38: 备注 | K38: 面积 | L38: 含量/㎡
A39: 1、 | B39: 主材 | C39: 2.5mm厚氟碳喷涂铝单板 | D39: 1 | E39: kg | F39: 1.03 | G39: 305 | H39: =D39*F39*G39 -> 314.15 | I39: 高士达、蓝天七色 | K39: 1.63 | L39: =1/K39 -> 0.61349693
C40: 50*50*4热镀锌角钢 | D40: =L41*M41*L39 -> 12.932515 | E40: kg | F40: 1.03 | G40: =8.7*1.03 -> 8.961 | H40: =D40*F40*G40 -> 119.36492 | I40: 国产优质 | K40: 胶缝长度 | L40: 50*50*4钢米重 | M40: 米 | N40: 膨胀螺栓
B41: 小计一 | H41: =SUM(H39:H40) -> 433.51492 | K41: 2 | L41: 3.1 | M41: 6.8 | N41: 16
A42: 2、 | B42: 辅材及其他 | C42: M10*100膨胀螺栓 | D42: =N41*L39 -> 9.8159509 | E42: 套 | F42: 1.03 | G42: 2.1 | H42: =D42*F42*G42 -> 21.231902 | I42: 国产优质
C43: 硅酮耐候密封胶(500ml/支) | D43: =K43*1000000/500*L39 -> 1.4723926 | E43: 支 | F43: 1.03 | G43: 20 | H43: =D43*F43*G43 -> 30.331288 | I43: 白云、之江 | K43: 0.0012 | L43: m³
C44: ∅5泡沫棒 | D44: =K41*L39 -> 1.2269939 | E44: ㎡ | F44: 1.03 | G44: 0.86 | H44: =D44*F44*G44 -> 1.0868712 | I44: 国产优质 | J44: 1.03 | K44: =(O36+O37)*4 -> 0
C45: 其它辅材 | D45: 1 | E45: ㎡ | F45: 1 | G45: 15 | H45: =D45*F45*G45 -> 15
C46: 防雷处理 | D46: 1 | E46: ㎡ | F46: 1 | G46: 1.5 | H46: =D46*F46*G46 -> 1.5
C47: 成品保护 | D47: 1 | E47: ㎡ | F47: 1 | G47: 5 | H47: =D47*F47*G47 -> 5
C48: 成品保洁 | D48: 1 | E48: ㎡ | F48: 1 | G48: 8 | H48: =D48*F48*G48 -> 8
C49: 试验费 | D49: 1 | E49: ㎡ | F49: 1 | G49: 5 | H49: =D49*F49*G49 -> 5
C50: 运输费 | D50: 1 | E50: ㎡ | F50: 1 | G50: 15 | H50: =D50*F50*G50 -> 15
C51: 安装人工费 | D51: 1 | E51: ㎡ | F51: 1 | G51: 130 | H51: =D51*F51*G51 -> 130
C52: 加工人工费 | D52: 1 | E52: ㎡ | F52: 1 | G52: 30 | H52: =D52*F52*G52 -> 30
C53: 措施费 | D53: 1 | E53: ㎡ | F53: 1 | G53: 15 | H53: =G53*D53*F53 -> 15 | J53: =SUM(H42:H48)+H41 -> 515.66498
B54: 小计二 | H54: =SUM(H42:H53) -> 277.15006
A55: 3.1、 | B55: 管理費 | D55: 5 | E55: % | G55: =H41+H54 -> 710.66498 | H55: =D55*G55/100 -> 35.533249
A56: 3.2、 | B56: 利润 | D56: 3 | E56: % | G56: =H41+H54+H55 -> 746.19823 | H56: =G56*D56/100 -> 22.385947
A57: 3.3、 | B57: 稅金 | D57: 9 | E57: % | G57: =H41+H54+H55+H56 -> 768.58418 | H57: =G57*D57/100 -> 69.172576
A58: 3.4、 | B58: 总包管理配合费 | D58: 2 | E58: % | G58: =H41+H54+H55+H56+H57 -> 837.75675 | H58: =G58*D58/100 -> 16.755135
B59: 小计三 | H59: =SUM(H55:H58) -> 143.84691
C60: 总计（小计一~小计三）： | H60: =+H41+H54+H59 -> 854.51189

Sheet 栏杆
A1: 综合单价分析表1.7
A2: 分项名称： | D2: 铝合金栏杆(H=1100mm） | I2: 计量单位 | J2: m/元
A3: 序号 | B3: 项目名称 | E3: 材质、规格 | F3: 单位 | G3: 单位 含量 | H3: 单价(元) | I3: 合计(元) | J3: 备注 | K3: 3.16
A4: 一 | B4: 直接费 | C4: 材 料 费 | D4: 铝合金型材扶手，表面氟碳喷涂 | F4: kg | G4: =K4*1.06 -> 0.85754 | H4: =VLOOKUP(D4,[31]材料表!$B$4:$G$80,4,0) -> 33.5 | I4: =G4*H4 -> 28.72759 | K4: =0.38+0.429 -> 0.809
D5: 铝合金型材立柱，表面氟碳喷涂 | F5: kg | G5: =M5/K3*1.06 -> 7.1557967 | H5: =VLOOKUP(D5,[31]材料表!$B$4:$G$80,4,0) -> 33.5 | I5: =G5*H5 -> 239.71919 | K5: 0.785 | L5: =1*22+1.035*5 -> 27.175 | M5: =K5*L5 -> 21.332375
D6: 铝合金型材横梁，表面氟碳喷涂 | F6: kg | G6: =K6*1.06 -> 0.80984 | H6: =VLOOKUP(D6,[31]材料表!$B$4:$G$80,4,0) -> 33.5 | I6: =G6*H6 -> 27.12964 | K6: =0.61+0.154 -> 0.764
D7: 铝合金型材盖板，表面氟碳喷涂 | F7: kg | G7: =K7*1.06 -> 2.36698 | H7: =VLOOKUP(D7,[31]材料表!$B$4:$G$80,4,0) -> 33.5 | I7: =G7*H7 -> 79.29383 | K7: =2.233 -> 2.233
D8: 200*80*8后置埋件 | E8: =VLOOKUP(D8,[31]材料表!$B$4:$G$80,2,0) -> 200*80*8 | F8: =VLOOKUP(D8,[31]材料表!$B$4:$G$80,3,0) -> 块 | G8: =K8/K3 -> 1.5822785 | H8: =VLOOKUP(D8,[31]材料表!$B$4:$G$80,4,0) -> 7.5 | I8: =G8*H8 -> 11.867089 | J8: =VLOOKUP(D8,[31]材料表!$B$4:$G$80,5,0) -> 6.5 | K8: 5
D9: M12*160化学锚栓 | E9: =VLOOKUP(D9,[31]材料表!$B$4:$G$80,2,0) -> M12*160 | F9: =VLOOKUP(D9,[31]材料表!$B$4:$G$80,3,0) -> 套 | G9: =G8*2*1.05 -> 3.3227848 | H9: =VLOOKUP(D9,[31]材料表!$B$4:$G$80,4,0) -> 3.5 | I9: =G9*H9 -> 11.629747 | J9: =VLOOKUP(D9,[31]材料表!$B$4:$G$80,5,0) -> 3.5
D10: M8不锈钢螺栓 | F10: 套 | G10: =K10/K3*1.05 -> 3.3227848 | H10: 1.7 | I10: =G10*H10 -> 5.6487342 | K10: =2*5 -> 10
D11: M6不锈钢螺栓 | F11: 套 | G11: =G10 -> 3.3227848 | H11: 1 | I11: =G11*H11 -> 3.3227848
D12: 6mm厚镀锌钢连接件 | F12: 套 | G12: =G8 -> 1.5822785 | H12: 3.5 | I12: =G12*H12 -> 5.5379747
D13: 2mm厚安装镀锌片 | F13: 块 | G13: =22/K3 -> 6.9620253 | H13: 1.25 | I13: =G13*H13 -> 8.7025316 | K13: =462.31*0.00785 -> 3.6291335 | L13: 0.05 | M13: =K13*L13 -> 0.18145667 | N13: =M13*8 -> 1.4516534
D14: 其他材料 | F14: =VLOOKUP(D14,[31]材料表!$B$4:$G$80,3,0) -> 项 | G14: 1 | H14: =VLOOKUP(D14,[31]材料表!$B$4:$G$80,4,0) -> 5 | I14: =G14*H14 -> 5
D28: 合计 | I28: =SUM(I4:I27) -> 426.57911
C29: 人工费 | F29: 元 | I29: 70
C30: 机械费 | F30: 元 | I30: 5
B31: 本项小计 | F31: 元 | I31: =SUM(I28:I30) -> 501.57911
A32: 二 | B32: 管理费 | E32: （一）* 4% | F32: 元 | I32: =I31*$K$2 -> 0
A33: 三 | B33: 利润 | E33: （一+二）* 5% | F33: 元 | I33: =(I32+I31)*5% -> 25.078955
A34: 四 | B34: 税金 | E34: （一+二+三）* 3.43% | F34: 元 | I34: =SUM(I31:I33)*$M$2 -> 0
A35: 五 | B35: 单位造价合计 | E35: （一+二+三+四） | F35: 元 | I35: =SUM(I31:I34) -> 526.65806

Sheet MS65F

Sheet WM1127
B2: MS65F系列（注胶角码） | D2: 24mm | E2: 表面处理 | F2: 静电粉末喷涂 | I2: N0.1 | J2: 副框线重速求表
B3: 代号 | C3: 门窗尺寸 | D3: 宽度 | E3: 高度 | F3: 面积 | G3: 樘数 | H3: 总面积 | J3: 宽度:mm | K3: 高度:mm | L3: 壁厚:mm | M3: 线重
B4: =MID(CELL("filename",Q13),FIND("]",CELL("filename",Q13))+1,30) -> WM1127 | C4: 洞口尺寸 | D4: 1100 | E4: 2650 | F4: 2.785 | G4: 1 | H4: =F4*G4 -> 2.785 | J4: 40 | K4: 20 | L4: 1.5 | M4: =ROUND(((J4*K4)-(J4-2*L4)*(K4-2*L4))*7.8/1000,3) -> 1.334
C5: 附框内口尺寸 | D5: =D4-70 -> 1030 | E5: =E4-70 -> 2580 | F5: =D5*E5/10^6 -> 2.6574 | G5: 1 | H5: =F5*G5 -> 2.6574 | J5: 40 | K5: 20 | L5: 2 | M5: =ROUND(((J5*K5)-(J5-2*L5)*(K5-2*L5))*7.8/1000,3) -> 1.747
C6: 主框尺寸 | D6: =D4-80 -> 1020 | E6: =E4-80 -> 2570 | F6: =D6*E6/10^6 -> 2.6214 | G6: 1 | H6: =F6*G6 -> 2.6214 | J6: 40 | K6: 20 | L6: 2 | M6: =ROUND(((J6*K6)-(J6-2*L6)*(K6-2*L6))*7.8/1000,3) -> 1.747
B7: 钢副框（热） | C7: 宽度 | D7: 宽数量 | E7: 高度 | F7: 高数量 | G7: 线重 | H7: 单价 | I7: 总价 | J7: 80 | K7: 40 | L7: 2 | M7: =ROUND(((J7*K7)-(J7-2*L7)*(K7-2*L7))*7.8/1000,3) -> 3.619
B8: 40*20*2.0 | C8: =D4-30 -> 1070 | D8: 2 | E8: =E4-30 -> 2620 | F8: 2 | G8: 1.747 | H8: =材料价格!B3 -> 7.5 | I8: =ROUND((C8*D8+E8*F8)*G8*H8/1000*1.1,2) -> 106.37 | J8: 40 | K8: 20 | L8: 1.4 | M8: =ROUND(((J8*K8)-(J8-2*L8)*(K8-2*L8))*2.71/1000,3) -> 0.434
B9: 40*20*2.0 | G9: 1.747 | H9: =H8 -> 7.5 | I9: =ROUND((C9*D9+E9*F9)*G9*H9/1000*1.1,2) -> 0 | M9: =ROUND(((J9*K9)-(J9-2*L9)*(K9-2*L9))*7.8/1000,3) -> 0
B10: 80*40*2 | G10: 3.619 | H10: =H9 -> 7.5 | I10: =ROUND((C10*D10+E10*F10)*G10*H10/1000*1.1,2) -> 0 | M10: =ROUND(((J10*K10)-(J10-2*L10)*(K10-2*L10))*7.8/1000,3) -> 0
B11: 50*50*2.0 | G11: 2.995 | H11: =H10 -> 7.5 | I11: =ROUND((C11*D11+E11*F11)*G11*H11/1000*1.1,2) -> 0 | M11: =ROUND(((J11*K11)-(J11-2*L11)*(K11-2*L11))*7.8/1000,3) -> 0
B12: 副框平米用量 | C12: =((I9+I10+I8+I11)/H8)/F4 -> 5.0925194 | D12: （Kg/m2) | E12: =(I9+I10+I8+I11)/F4 -> 38.193896 | F12: （元/m2) | H12: =ROUND(SUM(I8:I11)/H8,2) -> 14.18 | I12: =SUM(I8:I11) -> 106.37
B13: 型材名称 | C13: 代号 | D13: 横 | E13: 竖 | F13: 周长 | G13: 数量 | H13: 线重 | I13: 重量
B14: 平开窗框 | C14: SDF2894 | D14: =D6 -> 1020 | E14: =E6-E108 -> 520 | F14: =ROUND((D14+E14)*2/1000,4) -> 3.08 | G14: 1 | H14: 1.47 | I14: =ROUND(F14*G14*H14,3)*1.5 -> 6.792
F15: =ROUND((D15+E15)*2/1000,4) -> 0 | H15: =H14 -> 1.47 | I15: =ROUND(F15*G15*H15,3) -> 0
F16: =ROUND((D16+E16)*2/1000,4) -> 0 | H16: =H15 -> 1.47 | I16: =ROUND(F16*G16*H16,3) -> 0
F17: =ROUND((D17+E17)*2/1000,4) -> 0 | H17: =H16 -> 1.47 | I17: =ROUND(F17*G17*H17,3) -> 0
F18: =ROUND((D18+E18)*2/1000,4) -> 0 | H18: =H17 -> 1.47 | I18: =ROUND(F18*G18*H18,3) -> 0
F19: =ROUND((D19+E19)*2/1000,4) -> 0 | H19: =H18 -> 1.47 | I19: =ROUND(F19*G19*H19,3) -> 0
F20: =ROUND((D20+E20)*2/1000,4) -> 0 | H20: =H19 -> 1.47 | I20: =ROUND(F20*G20*H20,3) -> 0
F21: =ROUND((D21+E21)*2/1000,4) -> 0 | H21: =H20 -> 1.47 | I21: =ROUND(F21*G21*H21,3) -> 0
B22: 型材总长度 | C22: =SUMPRODUCT(F14:F21*G14:G21) -> 3.08 | D22: 型材总重量 | E22: =SUM(I14:I21)*1.1 -> 7.4712 | F22: 型材单价 | G22: =(C$218+C$219)/1000 -> 46.0815 | H22: 型材总价 | I22: =ROUND(E22*G22,2) -> 344.28 | J22: =SUM(G14:G21) -> 1
B23: 外侧装饰面长 | C23: 207.36 | D23: 外侧装饰面积 | E23: =ROUND(C22*(C23/1000),2) -> 0.64 | F23: 喷涂单价 | G23: 10 | H23: 喷涂总价 | I23: =E23*G23 -> 6.4
B24: 内侧装饰面长 | C24: 169.96 | D24: 内侧装饰面积 | E24: =ROUND(C22*(C24/1000),2) -> 0.52 | F24: 喷涂单价 | G24: 10 | H24: 喷涂总价 | I24: =E24*G24 -> 5.2
B25: 型材名称 | C25: 代号 | D25: 横 | E25: 竖 | F25: 周长 | G25: 数量 | H25: 线重 | I25: 重量 | J25: 宽 | K25: 高 | L25: 宽缩尺 | M25: 高缩尺 | N25: 代号
B26: 内平开窗扇 | C26: SDF2885 | D26: =J26-IF(L26=1,44,IF(L26=2,30,IF(L26=3,16,0))) -> 0 | E26: =K26-IF(M26=1,44,IF(M26=2,30,IF(M26=3,16,0))) -> 0 | F26: =ROUND((D26+E26)*2/1000,4) -> 0 | H26: 1.62 | I26: =IF(AND(D26>0,E26>0,F26>0),F26*G26*H26,0) -> 0 | N26: 1.框-框 | O26: 普通扇
D27: =J27-IF(L27=1,44,IF(L27=2,30,IF(L27=3,16,0))) -> 0 | E27: =K27-IF(M27=1,44,IF(M27=2,30,IF(M27=3,16,0))) -> 0 | F27: =ROUND((D27+E27)*2/1000,4) -> 0 | H27: =H26 -> 1.62 | I27: =IF(AND(D27>0,E27>0,F27>0),F27*G27*H27,0) -> 0 | N27: 2.框-中梃 | O27: 钢化扇
D28: =J28-IF(L28=1,44,IF(L28=2,30,IF(L28=3,16,0))) -> 0 | E28: =K28-IF(M28=1,44,IF(M28=2,30,IF(M28=3,16,0))) -> 0 | F28: =ROUND((D28+E28)*2/1000,4) -> 0 | H28: =H27 -> 1.62 | I28: =IF(AND(D28>0,E28>0,F28>0),F28*G28*H28,0) -> 0 | N28: 3.中梃-中梃 | O28: 钢化扇
D29: =J29-IF(L29=1,44,IF(L29=2,30,IF(L29=3,16,0))) -> 0 | E29: =K29-IF(M29=1,44,IF(M29=2,30,IF(M29=3,16,0))) -> 0 | F29: =ROUND((D29+E29)*2/1000,4) -> 0 | H29: =H28 -> 1.62 | I29: =IF(AND(D29>0,E29>0,F29>0),F29*G29*H29,0) -> 0
D30: =J30-IF(L30=1,44,IF(L30=2,30,IF(L30=3,16,0))) -> 0 | E30: =K30-IF(M30=1,44,IF(M30=2,30,IF(M30=3,16,0))) -> 0 | F30: =ROUND((D30+E30)*2/1000,4) -> 0 | H30: =H29 -> 1.62 | I30: =IF(AND(D30>0,E30>0,F30>0),F30*G30*H30,0) -> 0
B31: 型材总长度 | C31: =SUMPRODUCT(F26:F30*G26:G30) -> 0 | D31: 型材总重量 | E31: =SUM(I26:I30)*1.1 -> 0 | F31: 型材单价 | G31: =(C$218+C$221)/1000 -> 46.0815 | H31: 型材总价 | I31: =ROUND(E31*G31,2) -> 0 | J31: =SUM(G26:G30) -> 0
B32: 外侧装饰面长 | C32: 183.32 | D32: 外侧装饰面积 | E32: =ROUND(C31*(C32/1000),2) -> 0 | F32: 喷涂单价 | G32: =G$23 -> 10 | H32: 喷涂总价 | I32: =E32*G32 -> 0
B33: 内侧装饰面长 | C33: 257.82 | D33: 内侧装饰面积 | E33: =ROUND(C31*(C33/1000),2) -> 0 | F33: 喷涂单价 | G33: =G$24 -> 10 | H33: 喷涂总价 | I33: =E33*G33 -> 0
B34: 型材名称 | C34: 代号 | D34: 横 | E34: 竖 | F34: 周长 | G34: 数量 | H34: 线重 | I34: 重量 | J34: 宽 | K34: 高 | L34: （宽）缩尺 | M34: （高）缩尺 | N34: 代号
B35: 外平开窗扇 | C35: SDF2806 | D35: =J35-IF(L35=1,44,IF(L35=2,30,IF(L35=3,16,IF(L35=11,118,IF(L35=12,100,IF(L35=13,76.8,0)))))) -> 0 | E35: =K35-IF(M35=1,44,IF(M35=2,30,IF(M35=3,16,IF(M35=11,118,IF(M35=12,100,IF(M35=13,76.8,0)))))) -> 0 | F35: =ROUND((D35+E35)*2/1000,4) -> 0 | H35: 1.814 | I35: =ROUND(F35*G35*H35,3) -> 0 | N35: 1.框-框
D36: =J36-IF(L36=1,44,IF(L36=2,30,IF(L36=3,16,IF(L36=11,118,IF(L36=12,100,IF(L36=13,76.8,0)))))) -> 0 | E36: =K36-IF(M36=1,44,IF(M36=2,30,IF(M36=3,16,IF(M36=11,118,IF(M36=12,100,IF(M36=13,76.8,0)))))) -> 0 | F36: =ROUND((D36+E36)*2/1000,4) -> 0 | H36: =H35 -> 1.814 | I36: =ROUND(F36*G36*H36,3) -> 0 | N36: 2.框-中梃
D37: =J37-IF(L37=1,44,IF(L37=2,30,IF(L37=3,16,IF(L37=11,118,IF(L37=12,100,IF(L37=13,76.8,0)))))) -> 0 | E37: =K37-IF(M37=1,44,IF(M37=2,30,IF(M37=3,16,IF(M37=11,118,IF(M37=12,100,IF(M37=13,76.8,0)))))) -> 0 | F37: =ROUND((D37+E37)*2/1000,4) -> 0 | H37: =H36 -> 1.814 | I37: =ROUND(F37*G37*H37,3) -> 0 | N37: 3.中梃-中梃
B38: 型材总长度 | C38: =SUMPRODUCT(F35:F37*G35:G37) -> 0 | D38: 型材总重量 | E38: =SUM(I35:I37)*1.1 -> 0 | F38: 型材单价 | G38: =(C$218+C$219)/1000 -> 46.0815 | H38: 型材总价 | I38: =ROUND(E38*G38,2) -> 0 | J38: =SUM(G35:G37) -> 0 | N38: 11.转.框-框
B39: 外侧装饰面长 | C39: 320.14 | D39: 外侧装饰面积 | E39: =ROUND(C38*(C39/1000),2) -> 0 | F39: 喷涂单价 | G39: =G$23 -> 10 | H39: 喷涂总价 | I39: =E39*G39 -> 0 | N39: 12.转.框-中梃
B40: 内侧装饰面长 | C40: 156.99 | D40: 内侧装饰面积 | E40: =ROUND(C38*(C40/1000),2) -> 0 | F40: 喷涂单价 | G40: =G$24 -> 10 | H40: 喷涂总价 | I40: =E40*G40 -> 0 | N40: 13.转.中梃-中梃
B41: 型材名称 | C41: 代号 | D41: 横 | E41: 竖 | F41: 周长 | G41: 数量 | H41: 线重 | I41: 重量 | J41: 宽 | K41: 高 | L41: （宽）缩尺 | M41: （高）缩尺 | N41: 代号
B42: 转换料 | C42: SDF3162 (扇转换） | D42: =J42-IF(L42=1,46,IF(L42=2,34.5,IF(L42=3,23))) -> 0 | E42: =K42-IF(M42=1,46,IF(M42=2,34.5,IF(M42=3,23))) -> 0 | F42: =ROUND((D42+E42)*2/1000,4) -> 0 | H42: 1.26 | I42: =ROUND(F42*G42*H42,3) -> 0 | N42: 1.框-框
D43: =J43-IF(L43=1,46,IF(L43=2,34.5,IF(L43=3,23))) -> 0 | E43: =K43-IF(M43=1,46,IF(M43=2,34.5,IF(M43=3,23))) -> 0 | F43: =ROUND((D43+E43)*2/1000,4) -> 0 | H43: =H42 -> 1.26 | I43: =ROUND(F43*G43*H43,3) -> 0 | N43: 2.框-中梃
D44: =J44-IF(L44=1,46,IF(L44=2,34.5,IF(L44=3,23))) -> 0 | E44: =K44-IF(M44=1,46,IF(M44=2,34.5,IF(M44=3,23))) -> 0 | F44: =ROUND((D44+E44)*2/1000,4) -> 0 | H44: =H43 -> 1.26 | I44: =ROUND(F44*G44*H44,3) -> 0 | N44: 3.中梃-中梃
C45: SDF3162 (固定转换） | D45: =J45-IF(L45=1,46,IF(L45=2,34.5,IF(L45=3,23))) -> 0 | E45: =K45-IF(M45=1,46,IF(M45=2,34.5,IF(M45=3,23))) -> 0 | F45: =ROUND((D45+E45)*2/1000,4) -> 0 | H45: =H44 -> 1.26 | I45: =ROUND(F45*G45*H45,3) -> 0 | N45: 1.框-框
D46: =J46-IF(L46=1,46,IF(L46=2,34.5,IF(L46=3,23))) -> 0 | E46: =K46-IF(M46=1,46,IF(M46=2,34.5,IF(M46=3,23))) -> 0 | F46: =ROUND((D46+E46)*2/1000,4) -> 0 | H46: =H45 -> 1.26 | I46: =ROUND(F46*G46*H46,3) -> 0 | N46: 2.框-中梃
D47: =J47-IF(L47=1,46,IF(L47=2,34.5,IF(L47=3,23))) -> 0 | E47: =K47-IF(M47=1,46,IF(M47=2,34.5,IF(M47=3,23))) -> 0 | F47: =ROUND((D47+E47)*2/1000,4) -> 0 | H47: =H46 -> 1.26 | I47: =ROUND(F47*G47*H47,3) -> 0 | N47: 3.中梃-中梃
B48: 型材总长度 | C48: =SUMPRODUCT(F42:F47*G42:G47) -> 0 | D48: 型材总重量 | E48: =SUM(I42:I47)*1.1 -> 0 | F48: 型材单价 | G48: =(C$218+C$219)/1000 -> 46.0815 | H48: 型材总价 | I48: =ROUND(E48*G48,2) -> 0 | J48: =SUM(G42:G47) -> 0
B49: 外侧装饰面长 | C49: 132.48 | D49: 外侧装饰面积 | E49: =ROUND(C48*(C49/1000),2) -> 0 | F49: 喷涂单价 | G49: =G$23 -> 10 | H49: 喷涂总价 | I49: =E49*G49 -> 0
B50: 内侧装饰面长 | C50: 202.06 | D50: 内侧装饰面积 | E50: =ROUND(C48*(C50/1000),2) -> 0 | F50: 喷涂单价 | G50: =G$24 -> 10 | H50: 喷涂总价 | I50: =E50*G50 -> 0
B51: 型材名称 | C51: 代号 | D51: 横 | E51: 横数量 | F51: 竖 | G51: 竖数量 | H51: 线重 | I51: 重量 | J51: 宽 | K51: 高 | L51: （宽）缩尺 | M51: （高）缩尺 | N51: 代号
B52: 窗中梃 | C52: SDF3160 | D52: =J52-IF(L52=1,46,IF(L52=2,32,IF(L52=3,18,0))) -> 0 | F52: =K52-IF(M52=1,46,IF(M52=2,32,IF(M52=3,118,0))) -> 0 | H52: 1.638 | I52: =ROUND((D52*E52+F52*G52)/1000*H52,3) -> 0 | N52: 1.框-框
D53: =J53-IF(L53=1,46,IF(L53=2,32,IF(L53=3,18,0))) -> 0 | F53: =K53-IF(M53=1,46,IF(M53=2,32,IF(M53=3,118,0))) -> 0 | H53: =H52 -> 1.638 | I53: =ROUND((D53*E53+F53*G53)/1000*H53,3) -> 0 | N53: 2.框-中梃
D54: =J54-IF(L54=1,46,IF(L54=2,32,IF(L54=3,18,0))) -> 0 | F54: =K54-IF(M54=1,46,IF(M54=2,32,IF(M54=3,118,0))) -> 0 | H54: =H53 -> 1.638 | I54: =ROUND((D54*E54+F54*G54)/1000*H54,3) -> 0 | N54: 3.中梃-中梃
D55: =J55-IF(L55=1,46,IF(L55=2,32,IF(L55=3,18,0))) -> 0 | F55: =K55-IF(M55=1,46,IF(M55=2,32,IF(M55=3,118,0))) -> 0 | H55: =H54 -> 1.638 | I55: =ROUND((D55*E55+F55*G55)/1000*H55,3) -> 0
B56: 型材总长度 | C56: =SUMPRODUCT(D52:D55*E52:E55+F52:F55*G52:G55)/1000 -> 0 | D56: 型材总重量 | E56: =SUM(I52:I55)*1.1 -> 0 | F56: 型材单价 | G56: =(C$218+C$219)/1000 -> 46.0815 | H56: 型材总价 | I56: =ROUND(E56*G56,2) -> 0 | J56: =SUM(E52:E55)+SUM(G52:G55) -> 0
B57: 外侧装饰面长 | C57: 265.53 | D57: 外侧装饰面积 | E57: =ROUND(C56*(C57/1000),2) -> 0 | F57: 喷涂单价 | G57: =G$23 -> 10 | H57: 喷涂总价 | I57: =E57*G57 -> 0
B58: 内侧装饰面长 | C58: 173.62 | D58: 内侧装饰面积 | E58: =ROUND(C56*(C58/1000),2) -> 0 | F58: 喷涂单价 | G58: =G$24 -> 10 | H58: 喷涂总价 | I58: =E58*G58 -> 0
B59: 型材名称 | C59: 代号 | D59: 竖/横 | G59: 竖/横数量 | H59: 线重 | I59: 重量
B60: 加强中梃 | C60: SDF2808 | H60: 1.934 | I60: =ROUND(D60*G60*H60/1000,3) -> 0
H61: 1.934 | I61: =ROUND(D61*G61*H61/1000,3) -> 0
C62: SDF2809 | H62: 2.313 | I62: =ROUND(D62*G62*H62/1000,3) -> 0
H63: 2.313 | I63: =ROUND(D63*G63*H63/1000,3) -> 0
B64: 型材总长度 | C64: =SUMPRODUCT(D60:F63*G60:G63)/1000 -> 0 | D64: 型材总重量 | E64: =SUM(I60:I63)*1.1 -> 0 | F64: 型材单价 | G64: =(C$218+C$219)/1000 -> 46.0815 | H64: 型材总价 | I64: =ROUND(E64*G64,2) -> 0 | J64: =SUM(G60:G63) -> 0
B65: 外侧装饰面长 | C65: 337.92 | D65: 外侧装饰面积 | E65: =ROUND(C64*(C65/1000),2) -> 0 | F65: 喷涂单价 | G65: =G$23 -> 10 | H65: 喷涂总价 | I65: =E65*G65 -> 0
B66: 内侧装饰面长 | C66: 175.93 | D66: 内侧装饰面积 | E66: =ROUND(C64*(C66/1000),2) -> 0 | F66: 喷涂单价 | G66: =G$24 -> 10 | H66: 喷涂总价 | I66: =E66*G66 -> 0
B67: 型材名称 | C67: 代号 | D67: 横 | E67: 竖 | F67: 周长 | G67: 数量 | H67: 线重 | I67: 重量 | J67: 宽 | K67: 高 | L67: 宽缩尺 | M67: 高缩尺 | N67: 代号
B68: 固定压线 | C68: 普（SDL2280） | D68: =J68-IF(L68=1,72,IF(L68=2,54,IF(L68=3,26,IF(L68=11,102.8,IF(L68=12,88.8,IF(L68=13,74.8,0)))))) -> 948 | E68: =K68-IF(M68=1,72,IF(M68=2,24,IF(M68=3,26,IF(M68=11,102.8,IF(M68=12,88.8,IF(M68=13,74.8,0)))))) -> 448 | F68: =2*(D68+E68)/1000 -> 2.792 | G68: 1 | H68: 0.224 | I68: =ROUND(F68*G68*H68,3)*1.5 -> 0.9375 | J68: =D14 -> 1020 | K68: =E14 -> 520 | L68: 1 | M68: 1 | N68: 1.框-框
D69: =J69-IF(L69=1,72,IF(L69=2,54,IF(L69=3,26,IF(L69=11,102.8,IF(L69=12,88.8,IF(L69=13,74.8,0)))))) -> 0 | E69: =K69-IF(M69=1,72,IF(M69=2,24,IF(M69=3,26,IF(M69=11,102.8,IF(M69=12,88.8,IF(M69=13,74.8,0)))))) -> 0 | F69: =2*(D69+E69)/1000 -> 0 | H69: =H68 -> 0.224 | I69: =ROUND(F69*G69*H69,3) -> 0 | N69: 2.框-中梃
D70: =J70-IF(L70=1,72,IF(L70=2,54,IF(L70=3,26,IF(L70=11,102.8,IF(L70=12,88.8,IF(L70=13,74.8,0)))))) -> 0 | E70: =K70-IF(M70=1,72,IF(M70=2,24,IF(M70=3,26,IF(M70=11,102.8,IF(M70=12,88.8,IF(M70=13,74.8,0)))))) -> 0 | F70: =2*(D70+E70)/1000 -> 0 | H70: =H69 -> 0.224 | I70: =ROUND(F70*G70*H70,3) -> 0 | N70: 3.中梃-中梃
D71: =J71-IF(L71=1,72,IF(L71=2,54,IF(L71=3,26,IF(L71=11,102.8,IF(L71=12,88.8,IF(L71=13,74.8,0)))))) -> 0 | E71: =K71-IF(M71=1,72,IF(M71=2,24,IF(M71=3,26,IF(M71=11,102.8,IF(M71=12,88.8,IF(M71=13,74.8,0)))))) -> 0 | F71: =2*(D71+E71)/1000 -> 0 | H71: =H70 -> 0.224 | I71: =ROUND(F71*G71*H71,3) -> 0 | N71: 11.转.框-框
D72: =J72-IF(L72=1,72,IF(L72=2,54,IF(L72=3,26,IF(L72=11,102.8,IF(L72=12,88.8,IF(L72=13,74.8,0)))))) -> 0 | E72: =K72-IF(M72=1,72,IF(M72=2,24,IF(M72=3,26,IF(M72=11,102.8,IF(M72=12,88.8,IF(M72=13,74.8,0)))))) -> 0 | F72: =2*(D72+E72)/1000 -> 0 | H72: =H71 -> 0.224 | I72: =ROUND(F72*G72*H72,3) -> 0 | N72: 12.转.框-中梃
D73: =J73-IF(L73=1,72,IF(L73=2,54,IF(L73=3,26,IF(L73=11,102.8,IF(L73=12,88.8,IF(L73=13,74.8,0)))))) -> 0 | E73: =K73-IF(M73=1,72,IF(M73=2,24,IF(M73=3,26,IF(M73=11,102.8,IF(M73=12,88.8,IF(M73=13,74.8,0)))))) -> 0 | F73: =2*(D73+E73)/1000 -> 0 | H73: =H70 -> 0.224 | I73: =ROUND(F73*G73*H73,3) -> 0 | N73: 13.转.中梃-中梃
D74: =J74-IF(L74=1,72,IF(L74=2,54,IF(L74=3,26,IF(L74=11,102.8,IF(L74=12,88.8,IF(L74=13,74.8,0)))))) -> 0 | E74: =K74-IF(M74=1,72,IF(M74=2,24,IF(M74=3,26,IF(M74=11,102.8,IF(M74=12,88.8,IF(M74=13,74.8,0)))))) -> 0 | F74: =2*(D74+E74)/1000 -> 0 | H74: =H73 -> 0.224 | I74: =ROUND(F74*G74*H74,3) -> 0
C75: 钢（SDL2280） | D75: =J75-IF(L75=1,72,IF(L75=2,54,IF(L75=3,26,IF(L75=11,102.8,IF(L75=12,88.8,IF(L75=13,74.8,0)))))) -> 0 | E75: =K75-IF(M75=1,72,IF(M75=2,24,IF(M75=3,26,IF(M75=11,102.8,IF(M75=12,88.8,IF(M75=13,74.8,0)))))) -> 0 | F75: =2*(D75+E75)/1000 -> 0 | H75: =H74 -> 0.224 | I75: =ROUND(F75*G75*H75,3) -> 0 | N75: g钢化固定
D76: =J76-IF(L76=1,72,IF(L76=2,54,IF(L76=3,26,IF(L76=11,102.8,IF(L76=12,88.8,IF(L76=13,74.8,0)))))) -> 0 | E76: =K76-IF(M76=1,72,IF(M76=2,24,IF(M76=3,26,IF(M76=11,102.8,IF(M76=12,88.8,IF(M76=13,74.8,0)))))) -> 0 | F76: =2*(D76+E76)/1000 -> 0 | H76: =H72 -> 0.224 | I76: =ROUND(F76*G76*H76,3) -> 0 | N76: g钢化固定
D77: =J77-IF(L77=1,72,IF(L77=2,54,IF(L77=3,26,IF(L77=11,102.8,IF(L77=12,88.8,IF(L77=13,74.8,0)))))) -> 0 | E77: =K77-IF(M77=1,72,IF(M77=2,24,IF(M77=3,26,IF(M77=11,102.8,IF(M77=12,88.8,IF(M77=13,74.8,0)))))) -> 0 | F77: =2*(D77+E77)/1000 -> 0 | H77: =H76 -> 0.224 | I77: =ROUND(F77*G77*H77,3) -> 0 | N77: g钢化固定
D78: =J78-IF(L78=1,72,IF(L78=2,54,IF(L78=3,26,IF(L78=11,102.8,IF(L78=12,88.8,IF(L78=13,74.8,0)))))) -> 0 | E78: =K78-IF(M78=1,72,IF(M78=2,24,IF(M78=3,26,IF(M78=11,102.8,IF(M78=12,88.8,IF(M78=13,74.8,0)))))) -> 0 | F78: =2*(D78+E78)/1000 -> 0 | H78: =H77 -> 0.224 | I78: =ROUND(F78*G78*H78,3) -> 0 | N78: g钢化固定
D79: =J79-IF(L79=1,72,IF(L79=2,54,IF(L79=3,26,IF(L79=11,102.8,IF(L79=12,88.8,IF(L79=13,74.8,0)))))) -> 0 | E79: =K79-IF(M79=1,72,IF(M79=2,24,IF(M79=3,26,IF(M79=11,102.8,IF(M79=12,88.8,IF(M79=13,74.8,0)))))) -> 0 | F79: =2*(D79+E79)/1000 -> 0 | H79: =H78 -> 0.224 | I79: =ROUND(F79*G79*H79,3) -> 0 | N79: g钢化固定
D80: =J80-IF(L80=1,72,IF(L80=2,54,IF(L80=3,26,IF(L80=11,102.8,IF(L80=12,88.8,IF(L80=13,74.8,0)))))) -> 0 | E80: =K80-IF(M80=1,72,IF(M80=2,24,IF(M80=3,26,IF(M80=11,102.8,IF(M80=12,88.8,IF(M80=13,74.8,0)))))) -> 0 | F80: =2*(D80+E80)/1000 -> 0 | H80: =H79 -> 0.224 | I80: =ROUND(F80*G80*H80,3) -> 0 | N80: g钢化固定
D81: =J81-IF(L81=1,72,IF(L81=2,54,IF(L81=3,26,IF(L81=11,102.8,IF(L81=12,88.8,IF(L81=13,74.8,0)))))) -> 0 | E81: =K81-IF(M81=1,72,IF(M81=2,24,IF(M81=3,26,IF(M81=11,102.8,IF(M81=12,88.8,IF(M81=13,74.8,0)))))) -> 0 | F81: =2*(D81+E81)/1000 -> 0 | H81: =H80 -> 0.224 | I81: =ROUND(F81*G81*H81,3) -> 0 | N81: 超大钢化固定6mm
C82: 夹胶钢（SDL2280） | D82: =J82-IF(L82=1,72,IF(L82=2,54,IF(L82=3,26,IF(L82=11,102.8,IF(L82=12,88.8,IF(L82=13,74.8,0)))))) -> 0 | E82: =K82-IF(M82=1,72,IF(M82=2,24,IF(M82=3,26,IF(M82=11,102.8,IF(M82=12,88.8,IF(M82=13,74.8,0)))))) -> 0 | F82: =2*(D82+E82)/1000 -> 0 | H82: =H81 -> 0.224 | I82: =ROUND(F82*G82*H82,3) -> 0
D83: =J83-IF(L83=1,72,IF(L83=2,54,IF(L83=3,26,IF(L83=11,102.8,IF(L83=12,88.8,IF(L83=13,74.8,0)))))) -> 0 | E83: =K83-IF(M83=1,72,IF(M83=2,24,IF(M83=3,26,IF(M83=11,102.8,IF(M83=12,88.8,IF(M83=13,74.8,0)))))) -> 0 | F83: =2*(D83+E83)/1000 -> 0 | H83: =H82 -> 0.224 | I83: =ROUND(F83*G83*H83,3) -> 0
D84: =J84-IF(L84=1,72,IF(L84=2,54,IF(L84=3,26,IF(L84=11,102.8,IF(L84=12,88.8,IF(L84=13,74.8,0)))))) -> 0 | E84: =K84-IF(M84=1,72,IF(M84=2,24,IF(M84=3,26,IF(M84=11,102.8,IF(M84=12,88.8,IF(M84=13,74.8,0)))))) -> 0 | F84: =2*(D84+E84)/1000 -> 0 | H84: =H83 -> 0.224 | I84: =ROUND(F84*G84*H84,3) -> 0
D85: =J85-IF(L85=1,72,IF(L85=2,54,IF(L85=3,26,IF(L85=11,102.8,IF(L85=12,88.8,IF(L85=13,74.8,0)))))) -> 0 | E85: =K85-IF(M85=1,72,IF(M85=2,24,IF(M85=3,26,IF(M85=11,102.8,IF(M85=12,88.8,IF(M85=13,74.8,0)))))) -> 0 | F85: =2*(D85+E85)/1000 -> 0 | H85: =H84 -> 0.224 | I85: =ROUND(F85*G85*H85,3) -> 0
D86: =J86-IF(L86=1,72,IF(L86=2,54,IF(L86=3,26,IF(L86=11,102.8,IF(L86=12,88.8,IF(L86=13,74.8,0)))))) -> 0 | E86: =K86-IF(M86=1,72,IF(M86=2,24,IF(M86=3,26,IF(M86=11,102.8,IF(M86=12,88.8,IF(M86=13,74.8,0)))))) -> 0 | F86: =2*(D86+E86)/1000 -> 0 | H86: =H85 -> 0.224 | I86: =ROUND(F86*G86*H86,3) -> 0
D87: =J87-IF(L87=1,72,IF(L87=2,54,IF(L87=3,26,IF(L87=11,102.8,IF(L87=12,88.8,IF(L87=13,74.8,0)))))) -> 0 | E87: =K87-IF(M87=1,72,IF(M87=2,24,IF(M87=3,26,IF(M87=11,102.8,IF(M87=12,88.8,IF(M87=13,74.8,0)))))) -> 0 | F87: =2*(D87+E87)/1000 -> 0 | H87: =H86 -> 0.224 | I87: =ROUND(F87*G87*H87,3) -> 0
B88: 型材总长度 | C88: =SUMPRODUCT(F68:F87*G68:G87) -> 2.792 | D88: 型材总重量 | E88: =SUM(I68:I87)*1.1 -> 1.03125 | F88: 型材单价 | G88: =(C$218+C$222)/1000 -> 39.7815 | H88: 型材总价 | I88: =ROUND(E88*G88,2) -> 41.02
B89: 外侧装饰面长 | C89: 181.72 | D89: 外侧装饰面积 | E89: =ROUND(C88*(C89/1000),2) -> 0.51 | F89: 喷涂单价 | G89: =G$23 -> 10 | H89: 喷涂总价 | I89: =E89*G89 -> 5.1
B90: 内侧装饰面长 | D90: 内侧装饰面积 | E90: =ROUND(C88*(C90/1000),2) -> 0 | F90: 喷涂单价 | G90: =G$24 -> 10 | H90: 喷涂总价 | I90: =E90*G90 -> 0
B91: 型材名称 | C91: 代号 | D91: 横 | E91: 竖 | F91: 周长 | G91: 数量 | H91: 线重 | I91: 重量
B92: 内开窗扇压线 | C92: SDL2281 | D92: =D26-90 -> -90 | E92: =E26-90 -> -90 | F92: =2*(D92+E92)/1000 -> -0.36 | G92: =G26 -> 0 | H92: 0.271 | I92: =ROUND(F92*G92*H92,3) -> 0
D93: =D27-90 -> -90 | E93: =E27-90 -> -90 | F93: =2*(D93+E93)/1000 -> -0.36 | G93: =G27 -> 0 | H93: =H92 -> 0.271 | I93: =ROUND(F93*G93*H93,3) -> 0
D94: =D28-90 -> -90 | E94: =E28-90 -> -90 | F94: =2*(D94+E94)/1000 -> -0.36 | G94: =G28 -> 0 | H94: =H93 -> 0.271 | I94: =ROUND(F94*G94*H94,3) -> 0
D95: =D29-90 -> -90 | E95: =E29-90 -> -90 | F95: =2*(D95+E95)/1000 -> -0.36 | G95: =G29 -> 0 | H95: =H94 -> 0.271 | I95: =ROUND(F95*G95*H95,3) -> 0
D96: =D30-90 -> -90 | E96: =E30-90 -> -90 | F96: =2*(D96+E96)/1000 -> -0.36 | G96: =G30 -> 0 | H96: =H95 -> 0.271 | I96: =ROUND(F96*G96*H96,3) -> 0
B97: 型材总长度 | C97: =SUMPRODUCT(F92:F96*G92:G96) -> 0 | D97: 型材总重量 | E97: =SUM(I92:I96)*1.1 -> 0 | F97: 型材单价 | G97: =(C$218+C$222)/1000 -> 39.7815 | H97: 型材总价 | I97: =ROUND(E97*G97,2) -> 0
B98: 外侧装饰面长 | C98: 186.72 | D98: 外侧装饰面积 | E98: =ROUND(C97*(C98/1000),2) -> 0 | F98: 喷涂单价 | G98: =G$23 -> 10 | H98: 喷涂总价 | I98: =E98*G98 -> 0
B99: 内侧装饰面长 | C99: 0 | D99: 内侧装饰面积 | E99: =ROUND(C97*(C99/1000),2) -> 0 | F99: 喷涂单价 | G99: =G$24 -> 10 | H99: 喷涂总价 | I99: =E99*G99 -> 0
B100: 型材名称 | C100: 代号 | D100: 横 | E100: 竖 | F100: 周长 | G100: 数量 | H100: 线重 | I100: 重量
B101: 外开窗扇压线 | C101: =C92 -> SDL2281 | D101: =D35-122 -> -122 | E101: =E35-122 -> -122 | F101: =2*(D101+E101)/1000 -> -0.488 | G101: =G35 -> 0 | H101: =H96 -> 0.271 | I101: =ROUND(F101*G101*H101,3) -> 0
...

Sheet C1014
B2: MS65F系列（注胶角码） | D2: 24mm | E2: 表面处理 | F2: 静电粉末喷涂 | I2: N0.1 | J2: 副框线重速求表
B3: 代号 | C3: 门窗尺寸 | D3: 宽度 | E3: 高度 | F3: 面积 | G3: 樘数 | H3: 总面积 | J3: 宽度:mm | K3: 高度:mm | L3: 壁厚:mm | M3: 线重
B4: =MID(CELL("filename",Q13),FIND("]",CELL("filename",Q13))+1,30) -> C1014 | C4: 洞口尺寸 | D4: 1000 | E4: 1400 | F4: 1.1 | G4: 1 | H4: =F4*G4 -> 1.1 | J4: 40 | K4: 20 | L4: 1.5 | M4: =ROUND(((J4*K4)-(J4-2*L4)*(K4-2*L4))*7.8/1000,3) -> 1.334
C5: 附框内口尺寸 | D5: =D4-70 -> 930 | E5: =E4-70 -> 1330 | F5: =D5*E5/10^6 -> 1.2369 | G5: 1 | H5: =F5*G5 -> 1.2369 | J5: 40 | K5: 20 | L5: 2 | M5: =ROUND(((J5*K5)-(J5-2*L5)*(K5-2*L5))*7.8/1000,3) -> 1.747
C6: 主框尺寸 | D6: =D4-80 -> 920 | E6: =E4-80 -> 1320 | F6: =D6*E6/10^6 -> 1.2144 | G6: 1 | H6: =F6*G6 -> 1.2144 | J6: 40 | K6: 20 | L6: 2 | M6: =ROUND(((J6*K6)-(J6-2*L6)*(K6-2*L6))*7.8/1000,3) -> 1.747
B7: 钢副框（热） | C7: 宽度 | D7: 宽数量 | E7: 高度 | F7: 高数量 | G7: 线重 | H7: 单价 | I7: 总价 | J7: 80 | K7: 40 | L7: 2 | M7: =ROUND(((J7*K7)-(J7-2*L7)*(K7-2*L7))*7.8/1000,3) -> 3.619
B8: 40*20*2.0 | C8: =D4-30 -> 970 | D8: 2 | E8: =E4-30 -> 1370 | F8: 2 | G8: 1.747 | H8: =材料价格!B3 -> 7.5 | I8: =ROUND((C8*D8+E8*F8)*G8*H8/1000*1.1,2) -> 67.45 | J8: 40 | K8: 20 | L8: 1.4 | M8: =ROUND(((J8*K8)-(J8-2*L8)*(K8-2*L8))*2.71/1000,3) -> 0.434
B9: 40*20*2.0 | G9: 1.747 | H9: =H8 -> 7.5 | I9: =ROUND((C9*D9+E9*F9)*G9*H9/1000*1.1,2) -> 0 | M9: =ROUND(((J9*K9)-(J9-2*L9)*(K9-2*L9))*7.8/1000,3) -> 0
B10: 80*40*2 | G10: 3.619 | H10: =H9 -> 7.5 | I10: =ROUND((C10*D10+E10*F10)*G10*H10/1000*1.1,2) -> 0 | M10: =ROUND(((J10*K10)-(J10-2*L10)*(K10-2*L10))*7.8/1000,3) -> 0
B11: 50*50*2.0 | G11: 2.995 | H11: =H10 -> 7.5 | I11: =ROUND((C11*D11+E11*F11)*G11*H11/1000*1.1,2) -> 0 | M11: =ROUND(((J11*K11)-(J11-2*L11)*(K11-2*L11))*7.8/1000,3) -> 0
B12: 副框平米用量 | C12: =((I9+I10+I8+I11)/H8)/F4 -> 8.1757576 | D12: （Kg/m2) | E12: =(I9+I10+I8+I11)/F4 -> 61.318182 | F12: （元/m2) | H12: =ROUND(SUM(I8:I11)/H8,2) -> 8.99 | I12: =SUM(I8:I11) -> 67.45
B13: 型材名称 | C13: 代号 | D13: 横 | E13: 竖 | F13: 周长 | G13: 数量 | H13: 线重 | I13: 重量
B14: 平开窗框 | C14: SDF2894 | D14: =D6 -> 920 | E14: =E6 -> 1320 | F14: =ROUND((D14+E14)*2/1000,4) -> 4.48 | G14: 1 | H14: 1.47 | I14: =ROUND(F14*G14*H14,3)*3 -> 19.758
F15: =ROUND((D15+E15)*2/1000,4) -> 0 | H15: =H14 -> 1.47 | I15: =ROUND(F15*G15*H15,3) -> 0
F16: =ROUND((D16+E16)*2/1000,4) -> 0 | H16: =H15 -> 1.47 | I16: =ROUND(F16*G16*H16,3) -> 0
F17: =ROUND((D17+E17)*2/1000,4) -> 0 | H17: =H16 -> 1.47 | I17: =ROUND(F17*G17*H17,3) -> 0
F18: =ROUND((D18+E18)*2/1000,4) -> 0 | H18: =H17 -> 1.47 | I18: =ROUND(F18*G18*H18,3) -> 0
F19: =ROUND((D19+E19)*2/1000,4) -> 0 | H19: =H18 -> 1.47 | I19: =ROUND(F19*G19*H19,3) -> 0
F20: =ROUND((D20+E20)*2/1000,4) -> 0 | H20: =H19 -> 1.47 | I20: =ROUND(F20*G20*H20,3) -> 0
F21: =ROUND((D21+E21)*2/1000,4) -> 0 | H21: =H20 -> 1.47 | I21: =ROUND(F21*G21*H21,3) -> 0
B22: 型材总长度 | C22: =SUMPRODUCT(F14:F21*G14:G21) -> 4.48 | D22: 型材总重量 | E22: =SUM(I14:I21)*1.1 -> 21.7338 | F22: 型材单价 | G22: =(C$218+C$219)/1000 -> 46.0815 | H22: 型材总价 | I22: =ROUND(E22*G22,2) -> 1001.53 | J22: =SUM(G14:G21) -> 1
B23: 外侧装饰面长 | C23: 207.36 | D23: 外侧装饰面积 | E23: =ROUND(C22*(C23/1000),2) -> 0.93 | F23: 喷涂单价 | G23: 10 | H23: 喷涂总价 | I23: =E23*G23 -> 9.3
B24: 内侧装饰面长 | C24: 169.96 | D24: 内侧装饰面积 | E24: =ROUND(C22*(C24/1000),2) -> 0.76 | F24: 喷涂单价 | G24: 10 | H24: 喷涂总价 | I24: =E24*G24 -> 7.6
B25: 型材名称 | C25: 代号 | D25: 横 | E25: 竖 | F25: 周长 | G25: 数量 | H25: 线重 | I25: 重量 | J25: 宽 | K25: 高 | L25: 宽缩尺 | M25: 高缩尺 | N25: 代号
B26: 内平开窗扇 | C26: SDF2885 | D26: =J26-IF(L26=1,44,IF(L26=2,30,IF(L26=3,16,0))) -> 0 | E26: =K26-IF(M26=1,44,IF(M26=2,30,IF(M26=3,16,0))) -> 0 | F26: =ROUND((D26+E26)*2/1000,4) -> 0 | H26: 1.62 | I26: =IF(AND(D26>0,E26>0,F26>0),F26*G26*H26,0) -> 0 | N26: 1.框-框 | O26: 普通扇
D27: =J27-IF(L27=1,44,IF(L27=2,30,IF(L27=3,16,0))) -> 0 | E27: =K27-IF(M27=1,44,IF(M27=2,30,IF(M27=3,16,0))) -> 0 | F27: =ROUND((D27+E27)*2/1000,4) -> 0 | H27: =H26 -> 1.62 | I27: =IF(AND(D27>0,E27>0,F27>0),F27*G27*H27,0) -> 0 | N27: 2.框-中梃 | O27: 钢化扇
D28: =J28-IF(L28=1,44,IF(L28=2,30,IF(L28=3,16,0))) -> 0 | E28: =K28-IF(M28=1,44,IF(M28=2,30,IF(M28=3,16,0))) -> 0 | F28: =ROUND((D28+E28)*2/1000,4) -> 0 | H28: =H27 -> 1.62 | I28: =IF(AND(D28>0,E28>0,F28>0),F28*G28*H28,0) -> 0 | N28: 3.中梃-中梃 | O28: 钢化扇
D29: =J29-IF(L29=1,44,IF(L29=2,30,IF(L29=3,16,0))) -> 0 | E29: =K29-IF(M29=1,44,IF(M29=2,30,IF(M29=3,16,0))) -> 0 | F29: =ROUND((D29+E29)*2/1000,4) -> 0 | H29: =H28 -> 1.62 | I29: =IF(AND(D29>0,E29>0,F29>0),F29*G29*H29,0) -> 0
D30: =J30-IF(L30=1,44,IF(L30=2,30,IF(L30=3,16,0))) -> 0 | E30: =K30-IF(M30=1,44,IF(M30=2,30,IF(M30=3,16,0))) -> 0 | F30: =ROUND((D30+E30)*2/1000,4) -> 0 | H30: =H29 -> 1.62 | I30: =IF(AND(D30>0,E30>0,F30>0),F30*G30*H30,0) -> 0
B31: 型材总长度 | C31: =SUMPRODUCT(F26:F30*G26:G30) -> 0 | D31: 型材总重量 | E31: =SUM(I26:I30)*1.1 -> 0 | F31: 型材单价 | G31: =(C$218+C$221)/1000 -> 46.0815 | H31: 型材总价 | I31: =ROUND(E31*G31,2) -> 0 | J31: =SUM(G26:G30) -> 0
B32: 外侧装饰面长 | C32: 183.32 | D32: 外侧装饰面积 | E32: =ROUND(C31*(C32/1000),2) -> 0 | F32: 喷涂单价 | G32: =G$23 -> 10 | H32: 喷涂总价 | I32: =E32*G32 -> 0
B33: 内侧装饰面长 | C33: 257.82 | D33: 内侧装饰面积 | E33: =ROUND(C31*(C33/1000),2) -> 0 | F33: 喷涂单价 | G33: =G$24 -> 10 | H33: 喷涂总价 | I33: =E33*G33 -> 0
B34: 型材名称 | C34: 代号 | D34: 横 | E34: 竖 | F34: 周长 | G34: 数量 | H34: 线重 | I34: 重量 | J34: 宽 | K34: 高 | L34: （宽）缩尺 | M34: （高）缩尺 | N34: 代号
B35: 外平开窗扇 | C35: SDF2806 | D35: =J35-IF(L35=1,44,IF(L35=2,30,IF(L35=3,16,IF(L35=11,118,IF(L35=12,100,IF(L35=13,76.8,0)))))) -> 0 | E35: =K35-IF(M35=1,44,IF(M35=2,30,IF(M35=3,16,IF(M35=11,118,IF(M35=12,100,IF(M35=13,76.8,0)))))) -> 0 | F35: =ROUND((D35+E35)*2/1000,4) -> 0 | H35: 1.814 | I35: =ROUND(F35*G35*H35,3) -> 0 | N35: 1.框-框
D36: =J36-IF(L36=1,44,IF(L36=2,30,IF(L36=3,16,IF(L36=11,118,IF(L36=12,100,IF(L36=13,76.8,0)))))) -> 0 | E36: =K36-IF(M36=1,44,IF(M36=2,30,IF(M36=3,16,IF(M36=11,118,IF(M36=12,100,IF(M36=13,76.8,0)))))) -> 0 | F36: =ROUND((D36+E36)*2/1000,4) -> 0 | H36: =H35 -> 1.814 | I36: =ROUND(F36*G36*H36,3) -> 0 | N36: 2.框-中梃
D37: =J37-IF(L37=1,44,IF(L37=2,30,IF(L37=3,16,IF(L37=11,118,IF(L37=12,100,IF(L37=13,76.8,0)))))) -> 0 | E37: =K37-IF(M37=1,44,IF(M37=2,30,IF(M37=3,16,IF(M37=11,118,IF(M37=12,100,IF(M37=13,76.8,0)))))) -> 0 | F37: =ROUND((D37+E37)*2/1000,4) -> 0 | H37: =H36 -> 1.814 | I37: =ROUND(F37*G37*H37,3) -> 0 | N37: 3.中梃-中梃
B38: 型材总长度 | C38: =SUMPRODUCT(F35:F37*G35:G37) -> 0 | D38: 型材总重量 | E38: =SUM(I35:I37)*1.1 -> 0 | F38: 型材单价 | G38: =(C$218+C$219)/1000 -> 46.0815 | H38: 型材总价 | I38: =ROUND(E38*G38,2) -> 0 | J38: =SUM(G35:G37) -> 0 | N38: 11.转.框-框
B39: 外侧装饰面长 | C39: 320.14 | D39: 外侧装饰面积 | E39: =ROUND(C38*(C39/1000),2) -> 0 | F39: 喷涂单价 | G39: =G$23 -> 10 | H39: 喷涂总价 | I39: =E39*G39 -> 0 | N39: 12.转.框-中梃
B40: 内侧装饰面长 | C40: 156.99 | D40: 内侧装饰面积 | E40: =ROUND(C38*(C40/1000),2) -> 0 | F40: 喷涂单价 | G40: =G$24 -> 10 | H40: 喷涂总价 | I40: =E40*G40 -> 0 | N40: 13.转.中梃-中梃
B41: 型材名称 | C41: 代号 | D41: 横 | E41: 竖 | F41: 周长 | G41: 数量 | H41: 线重 | I41: 重量 | J41: 宽 | K41: 高 | L41: （宽）缩尺 | M41: （高）缩尺 | N41: 代号
B42: 转换料 | C42: SDF3162 (扇转换） | D42: =J42-IF(L42=1,46,IF(L42=2,34.5,IF(L42=3,23))) -> 0 | E42: =K42-IF(M42=1,46,IF(M42=2,34.5,IF(M42=3,23))) -> 0 | F42: =ROUND((D42+E42)*2/1000,4) -> 0 | H42: 1.26 | I42: =ROUND(F42*G42*H42,3) -> 0 | N42: 1.框-框
D43: =J43-IF(L43=1,46,IF(L43=2,34.5,IF(L43=3,23))) -> 0 | E43: =K43-IF(M43=1,46,IF(M43=2,34.5,IF(M43=3,23))) -> 0 | F43: =ROUND((D43+E43)*2/1000,4) -> 0 | H43: =H42 -> 1.26 | I43: =ROUND(F43*G43*H43,3) -> 0 | N43: 2.框-中梃
D44: =J44-IF(L44=1,46,IF(L44=2,34.5,IF(L44=3,23))) -> 0 | E44: =K44-IF(M44=1,46,IF(M44=2,34.5,IF(M44=3,23))) -> 0 | F44: =ROUND((D44+E44)*2/1000,4) -> 0 | H44: =H43 -> 1.26 | I44: =ROUND(F44*G44*H44,3) -> 0 | N44: 3.中梃-中梃
C45: SDF3162 (固定转换） | D45: =J45-IF(L45=1,46,IF(L45=2,34.5,IF(L45=3,23))) -> 0 | E45: =K45-IF(M45=1,46,IF(M45=2,34.5,IF(M45=3,23))) -> 0 | F45: =ROUND((D45+E45)*2/1000,4) -> 0 | H45: =H44 -> 1.26 | I45: =ROUND(F45*G45*H45,3) -> 0 | N45: 1.框-框
D46: =J46-IF(L46=1,46,IF(L46=2,34.5,IF(L46=3,23))) -> 0 | E46: =K46-IF(M46=1,46,IF(M46=2,34.5,IF(M46=3,23))) -> 0 | F46: =ROUND((D46+E46)*2/1000,4) -> 0 | H46: =H45 -> 1.26 | I46: =ROUND(F46*G46*H46,3) -> 0 | N46: 2.框-中梃
D47: =J47-IF(L47=1,46,IF(L47=2,34.5,IF(L47=3,23))) -> 0 | E47: =K47-IF(M47=1,46,IF(M47=2,34.5,IF(M47=3,23))) -> 0 | F47: =ROUND((D47+E47)*2/1000,4) -> 0 | H47: =H46 -> 1.26 | I47: =ROUND(F47*G47*H47,3) -> 0 | N47: 3.中梃-中梃
B48: 型材总长度 | C48: =SUMPRODUCT(F42:F47*G42:G47) -> 0 | D48: 型材总重量 | E48: =SUM(I42:I47)*1.1 -> 0 | F48: 型材单价 | G48: =(C$218+C$219)/1000 -> 46.0815 | H48: 型材总价 | I48: =ROUND(E48*G48,2) -> 0 | J48: =SUM(G42:G47) -> 0
B49: 外侧装饰面长 | C49: 132.48 | D49: 外侧装饰面积 | E49: =ROUND(C48*(C49/1000),2) -> 0 | F49: 喷涂单价 | G49: =G$23 -> 10 | H49: 喷涂总价 | I49: =E49*G49 -> 0
B50: 内侧装饰面长 | C50: 202.06 | D50: 内侧装饰面积 | E50: =ROUND(C48*(C50/1000),2) -> 0 | F50: 喷涂单价 | G50: =G$24 -> 10 | H50: 喷涂总价 | I50: =E50*G50 -> 0
B51: 型材名称 | C51: 代号 | D51: 横 | E51: 横数量 | F51: 竖 | G51: 竖数量 | H51: 线重 | I51: 重量 | J51: 宽 | K51: 高 | L51: （宽）缩尺 | M51: （高）缩尺 | N51: 代号
B52: 窗中梃 | C52: SDF3160 | D52: =J52-IF(L52=1,46,IF(L52=2,32,IF(L52=3,18,0))) -> 0 | F52: =K52-IF(M52=1,46,IF(M52=2,32,IF(M52=3,118,0))) -> 1274 | G52: 1 | H52: 1.638 | I52: =ROUND((D52*E52+F52*G52)/1000*H52,3) -> 2.087 | K52: =E14 -> 1320 | M52: 1 | N52: 1.框-框
D53: =J53-IF(L53=1,46,IF(L53=2,32,IF(L53=3,18,0))) -> 0 | F53: =K53-IF(M53=1,46,IF(M53=2,32,IF(M53=3,118,0))) -> 0 | H53: =H52 -> 1.638 | I53: =ROUND((D53*E53+F53*G53)/1000*H53,3) -> 0 | N53: 2.框-中梃
D54: =J54-IF(L54=1,46,IF(L54=2,32,IF(L54=3,18,0))) -> 0 | F54: =K54-IF(M54=1,46,IF(M54=2,32,IF(M54=3,118,0))) -> 0 | H54: =H53 -> 1.638 | I54: =ROUND((D54*E54+F54*G54)/1000*H54,3) -> 0 | N54: 3.中梃-中梃
D55: =J55-IF(L55=1,46,IF(L55=2,32,IF(L55=3,18,0))) -> 0 | F55: =K55-IF(M55=1,46,IF(M55=2,32,IF(M55=3,118,0))) -> 0 | H55: =H54 -> 1.638 | I55: =ROUND((D55*E55+F55*G55)/1000*H55,3) -> 0
B56: 型材总长度 | C56: =SUMPRODUCT(D52:D55*E52:E55+F52:F55*G52:G55)/1000 -> 1.274 | D56: 型材总重量 | E56: =SUM(I52:I55)*1.1 -> 2.2957 | F56: 型材单价 | G56: =(C$218+C$219)/1000 -> 46.0815 | H56: 型材总价 | I56: =ROUND(E56*G56,2) -> 105.79 | J56: =SUM(E52:E55)+SUM(G52:G55) -> 1
B57: 外侧装饰面长 | C57: 265.53 | D57: 外侧装饰面积 | E57: =ROUND(C56*(C57/1000),2) -> 0.34 | F57: 喷涂单价 | G57: =G$23 -> 10 | H57: 喷涂总价 | I57: =E57*G57 -> 3.4
B58: 内侧装饰面长 | C58: 173.62 | D58: 内侧装饰面积 | E58: =ROUND(C56*(C58/1000),2) -> 0.22 | F58: 喷涂单价 | G58: =G$24 -> 10 | H58: 喷涂总价 | I58: =E58*G58 -> 2.2
B59: 型材名称 | C59: 代号 | D59: 竖/横 | G59: 竖/横数量 | H59: 线重 | I59: 重量
B60: 加强中梃 | C60: SDF2808 | H60: 1.934 | I60: =ROUND(D60*G60*H60/1000,3) -> 0
H61: 1.934 | I61: =ROUND(D61*G61*H61/1000,3) -> 0
C62: SDF2809 | H62: 2.313 | I62: =ROUND(D62*G62*H62/1000,3) -> 0
H63: 2.313 | I63: =ROUND(D63*G63*H63/1000,3) -> 0
B64: 型材总长度 | C64: =SUMPRODUCT(D60:F63*G60:G63)/1000 -> 0 | D64: 型材总重量 | E64: =SUM(I60:I63)*1.1 -> 0 | F64: 型材单价 | G64: =(C$218+C$219)/1000 -> 46.0815 | H64: 型材总价 | I64: =ROUND(E64*G64,2) -> 0 | J64: =SUM(G60:G63) -> 0
B65: 外侧装饰面长 | C65: 337.92 | D65: 外侧装饰面积 | E65: =ROUND(C64*(C65/1000),2) -> 0 | F65: 喷涂单价 | G65: =G$23 -> 10 | H65: 喷涂总价 | I65: =E65*G65 -> 0
B66: 内侧装饰面长 | C66: 175.93 | D66: 内侧装饰面积 | E66: =ROUND(C64*(C66/1000),2) -> 0 | F66: 喷涂单价 | G66: =G$24 -> 10 | H66: 喷涂总价 | I66: =E66*G66 -> 0
B67: 型材名称 | C67: 代号 | D67: 横 | E67: 竖 | F67: 周长 | G67: 数量 | H67: 线重 | I67: 重量 | J67: 宽 | K67: 高 | L67: 宽缩尺 | M67: 高缩尺 | N67: 代号
B68: 固定压线 | C68: 普（SDL2280） | D68: =J68-IF(L68=1,72,IF(L68=2,54,IF(L68=3,26,IF(L68=11,102.8,IF(L68=12,88.8,IF(L68=13,74.8,0)))))) -> 406 | E68: =K68-IF(M68=1,72,IF(M68=2,24,IF(M68=3,26,IF(M68=11,102.8,IF(M68=12,88.8,IF(M68=13,74.8,0)))))) -> 1248 | F68: =2*(D68+E68)/1000 -> 3.308 | G68: 2 | H68: 0.224 | I68: =ROUND(F68*G68*H68,3)*2 -> 2.964 | J68: =D14/2 -> 460 | K68: =E14 -> 1320 | L68: 2 | M68: 1 | N68: 1.框-框
D69: =J69-IF(L69=1,72,IF(L69=2,54,IF(L69=3,26,IF(L69=11,102.8,IF(L69=12,88.8,IF(L69=13,74.8,0)))))) -> 0 | E69: =K69-IF(M69=1,72,IF(M69=2,24,IF(M69=3,26,IF(M69=11,102.8,IF(M69=12,88.8,IF(M69=13,74.8,0)))))) -> 0 | F69: =2*(D69+E69)/1000 -> 0 | H69: =H68 -> 0.224 | I69: =ROUND(F69*G69*H69,3) -> 0 | N69: 2.框-中梃
D70: =J70-IF(L70=1,72,IF(L70=2,54,IF(L70=3,26,IF(L70=11,102.8,IF(L70=12,88.8,IF(L70=13,74.8,0)))))) -> 0 | E70: =K70-IF(M70=1,72,IF(M70=2,24,IF(M70=3,26,IF(M70=11,102.8,IF(M70=12,88.8,IF(M70=13,74.8,0)))))) -> 0 | F70: =2*(D70+E70)/1000 -> 0 | H70: =H69 -> 0.224 | I70: =ROUND(F70*G70*H70,3) -> 0 | N70: 3.中梃-中梃
D71: =J71-IF(L71=1,72,IF(L71=2,54,IF(L71=3,26,IF(L71=11,102.8,IF(L71=12,88.8,IF(L71=13,74.8,0)))))) -> 0 | E71: =K71-IF(M71=1,72,IF(M71=2,24,IF(M71=3,26,IF(M71=11,102.8,IF(M71=12,88.8,IF(M71=13,74.8,0)))))) -> 0 | F71: =2*(D71+E71)/1000 -> 0 | H71: =H70 -> 0.224 | I71: =ROUND(F71*G71*H71,3) -> 0 | N71: 11.转.框-框
D72: =J72-IF(L72=1,72,IF(L72=2,54,IF(L72=3,26,IF(L72=11,102.8,IF(L72=12,88.8,IF(L72=13,74.8,0)))))) -> 0 | E72: =K72-IF(M72=1,72,IF(M72=2,24,IF(M72=3,26,IF(M72=11,102.8,IF(M72=12,88.8,IF(M72=13,74.8,0)))))) -> 0 | F72: =2*(D72+E72)/1000 -> 0 | H72: =H71 -> 0.224 | I72: =ROUND(F72*G72*H72,3) -> 0 | N72: 12.转.框-中梃
D73: =J73-IF(L73=1,72,IF(L73=2,54,IF(L73=3,26,IF(L73=11,102.8,IF(L73=12,88.8,IF(L73=13,74.8,0)))))) -> 0 | E73: =K73-IF(M73=1,72,IF(M73=2,24,IF(M73=3,26,IF(M73=11,102.8,IF(M73=12,88.8,IF(M73=13,74.8,0)))))) -> 0 | F73: =2*(D73+E73)/1000 -> 0 | H73: =H70 -> 0.224 | I73: =ROUND(F73*G73*H73,3) -> 0 | N73: 13.转.中梃-中梃
D74: =J74-IF(L74=1,72,IF(L74=2,54,IF(L74=3,26,IF(L74=11,102.8,IF(L74=12,88.8,IF(L74=13,74.8,0)))))) -> 0 | E74: =K74-IF(M74=1,72,IF(M74=2,24,IF(M74=3,26,IF(M74=11,102.8,IF(M74=12,88.8,IF(M74=13,74.8,0)))))) -> 0 | F74: =2*(D74+E74)/1000 -> 0 | H74: =H73 -> 0.224 | I74: =ROUND(F74*G74*H74,3) -> 0
C75: 钢（SDL2280） | D75: =J75-IF(L75=1,72,IF(L75=2,54,IF(L75=3,26,IF(L75=11,102.8,IF(L75=12,88.8,IF(L75=13,74.8,0)))))) -> 0 | E75: =K75-IF(M75=1,72,IF(M75=2,24,IF(M75=3,26,IF(M75=11,102.8,IF(M75=12,88.8,IF(M75=13,74.8,0)))))) -> 0 | F75: =2*(D75+E75)/1000 -> 0 | H75: =H74 -> 0.224 | I75: =ROUND(F75*G75*H75,3) -> 0 | N75: g钢化固定
D76: =J76-IF(L76=1,72,IF(L76=2,54,IF(L76=3,26,IF(L76=11,102.8,IF(L76=12,88.8,IF(L76=13,74.8,0)))))) -> 0 | E76: =K76-IF(M76=1,72,IF(M76=2,24,IF(M76=3,26,IF(M76=11,102.8,IF(M76=12,88.8,IF(M76=13,74.8,0)))))) -> 0 | F76: =2*(D76+E76)/1000 -> 0 | H76: =H72 -> 0.224 | I76: =ROUND(F76*G76*H76,3) -> 0 | N76: g钢化固定
D77: =J77-IF(L77=1,72,IF(L77=2,54,IF(L77=3,26,IF(L77=11,102.8,IF(L77=12,88.8,IF(L77=13,74.8,0)))))) -> 0 | E77: =K77-IF(M77=1,72,IF(M77=2,24,IF(M77=3,26,IF(M77=11,102.8,IF(M77=12,88.8,IF(M77=13,74.8,0)))))) -> 0 | F77: =2*(D77+E77)/1000 -> 0 | H77: =H76 -> 0.224 | I77: =ROUND(F77*G77*H77,3) -> 0 | N77: g钢化固定
D78: =J78-IF(L78=1,72,IF(L78=2,54,IF(L78=3,26,IF(L78=11,102.8,IF(L78=12,88.8,IF(L78=13,74.8,0)))))) -> 0 | E78: =K78-IF(M78=1,72,IF(M78=2,24,IF(M78=3,26,IF(M78=11,102.8,IF(M78=12,88.8,IF(M78=13,74.8,0)))))) -> 0 | F78: =2*(D78+E78)/1000 -> 0 | H78: =H77 -> 0.224 | I78: =ROUND(F78*G78*H78,3) -> 0 | N78: g钢化固定
D79: =J79-IF(L79=1,72,IF(L79=2,54,IF(L79=3,26,IF(L79=11,102.8,IF(L79=12,88.8,IF(L79=13,74.8,0)))))) -> 0 | E79: =K79-IF(M79=1,72,IF(M79=2,24,IF(M79=3,26,IF(M79=11,102.8,IF(M79=12,88.8,IF(M79=13,74.8,0)))))) -> 0 | F79: =2*(D79+E79)/1000 -> 0 | H79: =H78 -> 0.224 | I79: =ROUND(F79*G79*H79,3) -> 0 | N79: g钢化固定
D80: =J80-IF(L80=1,72,IF(L80=2,54,IF(L80=3,26,IF(L80=11,102.8,IF(L80=12,88.8,IF(L80=13,74.8,0)))))) -> 0 | E80: =K80-IF(M80=1,72,IF(M80=2,24,IF(M80=3,26,IF(M80=11,102.8,IF(M80=12,88.8,IF(M80=13,74.8,0)))))) -> 0 | F80: =2*(D80+E80)/1000 -> 0 | H80: =H79 -> 0.224 | I80: =ROUND(F80*G80*H80,3) -> 0 | N80: g钢化固定
D81: =J81-IF(L81=1,72,IF(L81=2,54,IF(L81=3,26,IF(L81=11,102.8,IF(L81=12,88.8,IF(L81=13,74.8,0)))))) -> 0 | E81: =K81-IF(M81=1,72,IF(M81=2,24,IF(M81=3,26,IF(M81=11,102.8,IF(M81=12,88.8,IF(M81=13,74.8,0)))))) -> 0 | F81: =2*(D81+E81)/1000 -> 0 | H81: =H80 -> 0.224 | I81: =ROUND(F81*G81*H81,3) -> 0 | N81: 超大钢化固定6mm
C82: 夹胶钢（SDL2280） | D82: =J82-IF(L82=1,72,IF(L82=2,54,IF(L82=3,26,IF(L82=11,102.8,IF(L82=12,88.8,IF(L82=13,74.8,0)))))) -> 0 | E82: =K82-IF(M82=1,72,IF(M82=2,24,IF(M82=3,26,IF(M82=11,102.8,IF(M82=12,88.8,IF(M82=13,74.8,0)))))) -> 0 | F82: =2*(D82+E82)/1000 -> 0 | H82: =H81 -> 0.224 | I82: =ROUND(F82*G82*H82,3) -> 0
D83: =J83-IF(L83=1,72,IF(L83=2,54,IF(L83=3,26,IF(L83=11,102.8,IF(L83=12,88.8,IF(L83=13,74.8,0)))))) -> 0 | E83: =K83-IF(M83=1,72,IF(M83=2,24,IF(M83=3,26,IF(M83=11,102.8,IF(M83=12,88.8,IF(M83=13,74.8,0)))))) -> 0 | F83: =2*(D83+E83)/1000 -> 0 | H83: =H82 -> 0.224 | I83: =ROUND(F83*G83*H83,3) -> 0
D84: =J84-IF(L84=1,72,IF(L84=2,54,IF(L84=3,26,IF(L84=11,102.8,IF(L84=12,88.8,IF(L84=13,74.8,0)))))) -> 0 | E84: =K84-IF(M84=1,72,IF(M84=2,24,IF(M84=3,26,IF(M84=11,102.8,IF(M84=12,88.8,IF(M84=13,74.8,0)))))) -> 0 | F84: =2*(D84+E84)/1000 -> 0 | H84: =H83 -> 0.224 | I84: =ROUND(F84*G84*H84,3) -> 0
D85: =J85-IF(L85=1,72,IF(L85=2,54,IF(L85=3,26,IF(L85=11,102.8,IF(L85=12,88.8,IF(L85=13,74.8,0)))))) -> 0 | E85: =K85-IF(M85=1,72,IF(M85=2,24,IF(M85=3,26,IF(M85=11,102.8,IF(M85=12,88.8,IF(M85=13,74.8,0)))))) -> 0 | F85: =2*(D85+E85)/1000 -> 0 | H85: =H84 -> 0.224 | I85: =ROUND(F85*G85*H85,3) -> 0
D86: =J86-IF(L86=1,72,IF(L86=2,54,IF(L86=3,26,IF(L86=11,102.8,IF(L86=12,88.8,IF(L86=13,74.8,0)))))) -> 0 | E86: =K86-IF(M86=1,72,IF(M86=2,24,IF(M86=3,26,IF(M86=11,102.8,IF(M86=12,88.8,IF(M86=13,74.8,0)))))) -> 0 | F86: =2*(D86+E86)/1000 -> 0 | H86: =H85 -> 0.224 | I86: =ROUND(F86*G86*H86,3) -> 0
D87: =J87-IF(L87=1,72,IF(L87=2,54,IF(L87=3,26,IF(L87=11,102.8,IF(L87=12,88.8,IF(L87=13,74.8,0)))))) -> 0 | E87: =K87-IF(M87=1,72,IF(M87=2,24,IF(M87=3,26,IF(M87=11,102.8,IF(M87=12,88.8,IF(M87=13,74.8,0)))))) -> 0 | F87: =2*(D87+E87)/1000 -> 0 | H87: =H86 -> 0.224 | I87: =ROUND(F87*G87*H87,3) -> 0
B88: 型材总长度 | C88: =SUMPRODUCT(F68:F87*G68:G87) -> 6.616 | D88: 型材总重量 | E88: =SUM(I68:I87)*1.1 -> 3.2604 | F88: 型材单价 | G88: =(C$218+C$222)/1000 -> 39.7815 | H88: 型材总价 | I88: =ROUND(E88*G88,2) -> 129.7
B89: 外侧装饰面长 | C89: 181.72 | D89: 外侧装饰面积 | E89: =ROUND(C88*(C89/1000),2) -> 1.2 | F89: 喷涂单价 | G89: =G$23 -> 10 | H89: 喷涂总价 | I89: =E89*G89 -> 12
B90: 内侧装饰面长 | D90: 内侧装饰面积 | E90: =ROUND(C88*(C90/1000),2) -> 0 | F90: 喷涂单价 | G90: =G$24 -> 10 | H90: 喷涂总价 | I90: =E90*G90 -> 0
B91: 型材名称 | C91: 代号 | D91: 横 | E91: 竖 | F91: 周长 | G91: 数量 | H91: 线重 | I91: 重量
B92: 内开窗扇压线 | C92: SDL2281 | D92: =D26-90 -> -90 | E92: =E26-90 -> -90 | F92: =2*(D92+E92)/1000 -> -0.36 | G92: =G26 -> 0 | H92: 0.271 | I92: =ROUND(F92*G92*H92,3) -> 0
D93: =D27-90 -> -90 | E93: =E27-90 -> -90 | F93: =2*(D93+E93)/1000 -> -0.36 | G93: =G27 -> 0 | H93: =H92 -> 0.271 | I93: =ROUND(F93*G93*H93,3) -> 0
D94: =D28-90 -> -90 | E94: =E28-90 -> -90 | F94: =2*(D94+E94)/1000 -> -0.36 | G94: =G28 -> 0 | H94: =H93 -> 0.271 | I94: =ROUND(F94*G94*H94,3) -> 0
D95: =D29-90 -> -90 | E95: =E29-90 -> -90 | F95: =2*(D95+E95)/1000 -> -0.36 | G95: =G29 -> 0 | H95: =H94 -> 0.271 | I95: =ROUND(F95*G95*H95,3) -> 0
D96: =D30-90 -> -90 | E96: =E30-90 -> -90 | F96: =2*(D96+E96)/1000 -> -0.36 | G96: =G30 -> 0 | H96: =H95 -> 0.271 | I96: =ROUND(F96*G96*H96,3) -> 0
B97: 型材总长度 | C97: =SUMPRODUCT(F92:F96*G92:G96) -> 0 | D97: 型材总重量 | E97: =SUM(I92:I96)*1.1 -> 0 | F97: 型材单价 | G97: =(C$218+C$222)/1000 -> 39.7815 | H97: 型材总价 | I97: =ROUND(E97*G97,2) -> 0
B98: 外侧装饰面长 | C98: 186.72 | D98: 外侧装饰面积 | E98: =ROUND(C97*(C98/1000),2) -> 0 | F98: 喷涂单价 | G98: =G$23 -> 10 | H98: 喷涂总价 | I98: =E98*G98 -> 0
B99: 内侧装饰面长 | C99: 0 | D99: 内侧装饰面积 | E99: =ROUND(C97*(C99/1000),2) -> 0 | F99: 喷涂单价 | G99: =G$24 -> 10 | H99: 喷涂总价 | I99: =E99*G99 -> 0
B100: 型材名称 | C100: 代号 | D100: 横 | E100: 竖 | F100: 周长 | G100: 数量 | H100: 线重 | I100: 重量
B101: 外开窗扇压线 | C101: =C92 -> SDL2281 | D101: =D35-122 -> -122 | E101: =E35-122 -> -122 | F101: =2*(D101+E101)/1000 -> -0.488 | G101: =G35 -> 0 | H101: =H96 -> 0.271 | I101: =ROUND(F101*G101*H101,3) -> 0
...

Sheet C1117
B2: MS65F系列（注胶角码） | D2: 24mm | E2: 表面处理 | F2: 静电粉末喷涂 | I2: N0.1 | J2: 副框线重速求表
B3: 代号 | C3: 门窗尺寸 | D3: 宽度 | E3: 高度 | F3: 面积 | G3: 樘数 | H3: 总面积 | J3: 宽度:mm | K3: 高度:mm | L3: 壁厚:mm | M3: 线重
B4: =MID(CELL("filename",Q13),FIND("]",CELL("filename",Q13))+1,30) -> C1117 | C4: 洞口尺寸 | D4: 1100 | E4: 1700 | F4: 1.74 | G4: 1 | H4: =F4*G4 -> 1.74 | J4: 40 | K4: 20 | L4: 1.5 | M4: =ROUND(((J4*K4)-(J4-2*L4)*(K4-2*L4))*7.8/1000,3) -> 1.334
C5: 附框内口尺寸 | D5: =D4-70 -> 1030 | E5: =E4-70 -> 1630 | F5: =D5*E5/10^6 -> 1.6789 | G5: 1 | H5: =F5*G5 -> 1.6789 | J5: 40 | K5: 20 | L5: 2 | M5: =ROUND(((J5*K5)-(J5-2*L5)*(K5-2*L5))*7.8/1000,3) -> 1.747
C6: 主框尺寸 | D6: =D4-80 -> 1020 | E6: =E4-80 -> 1620 | F6: =D6*E6/10^6 -> 1.6524 | G6: 1 | H6: =F6*G6 -> 1.6524 | J6: 40 | K6: 20 | L6: 2 | M6: =ROUND(((J6*K6)-(J6-2*L6)*(K6-2*L6))*7.8/1000,3) -> 1.747
B7: 钢副框（热） | C7: 宽度 | D7: 宽数量 | E7: 高度 | F7: 高数量 | G7: 线重 | H7: 单价 | I7: 总价 | J7: 80 | K7: 40 | L7: 2 | M7: =ROUND(((J7*K7)-(J7-2*L7)*(K7-2*L7))*7.8/1000,3) -> 3.619
B8: 40*20*2.0 | C8: =D4-30 -> 1070 | D8: 2 | E8: =E4-30 -> 1670 | F8: 2 | G8: 1.747 | H8: =材料价格!B3 -> 7.5 | I8: =ROUND((C8*D8+E8*F8)*G8*H8/1000*1.1,2) -> 78.98 | J8: 40 | K8: 20 | L8: 1.4 | M8: =ROUND(((J8*K8)-(J8-2*L8)*(K8-2*L8))*2.71/1000,3) -> 0.434
B9: 40*20*2.0 | G9: 1.747 | H9: =H8 -> 7.5 | I9: =ROUND((C9*D9+E9*F9)*G9*H9/1000*1.1,2) -> 0 | M9: =ROUND(((J9*K9)-(J9-2*L9)*(K9-2*L9))*7.8/1000,3) -> 0
B10: 80*40*2 | G10: 3.619 | H10: =H9 -> 7.5 | I10: =ROUND((C10*D10+E10*F10)*G10*H10/1000*1.1,2) -> 0 | M10: =ROUND(((J10*K10)-(J10-2*L10)*(K10-2*L10))*7.8/1000,3) -> 0
B11: 50*50*2.0 | G11: 2.995 | H11: =H10 -> 7.5 | I11: =ROUND((C11*D11+E11*F11)*G11*H11/1000*1.1,2) -> 0 | M11: =ROUND(((J11*K11)-(J11-2*L11)*(K11-2*L11))*7.8/1000,3) -> 0
B12: 副框平米用量 | C12: =((I9+I10+I8+I11)/H8)/F4 -> 6.0521073 | D12: （Kg/m2) | E12: =(I9+I10+I8+I11)/F4 -> 45.390805 | F12: （元/m2) | H12: =ROUND(SUM(I8:I11)/H8,2) -> 10.53 | I12: =SUM(I8:I11) -> 78.98
B13: 型材名称 | C13: 代号 | D13: 横 | E13: 竖 | F13: 周长 | G13: 数量 | H13: 线重 | I13: 重量
B14: 平开窗框 | C14: SDF2894 | D14: =D6 -> 1020 | E14: 550 | F14: =ROUND((D14+E14)*2/1000,4) -> 3.14 | G14: 1 | H14: 1.47 | I14: =ROUND(F14*G14*H14,3)*1.5 -> 6.924
D15: =D14 -> 1020 | E15: =E6-E14 -> 1070 | F15: =ROUND((D15+E15)*2/1000,4) -> 4.18 | G15: 1 | H15: =H14 -> 1.47 | I15: =ROUND(F15*G15*H15,3) -> 6.145
F16: =ROUND((D16+E16)*2/1000,4) -> 0 | H16: =H15 -> 1.47 | I16: =ROUND(F16*G16*H16,3) -> 0
F17: =ROUND((D17+E17)*2/1000,4) -> 0 | H17: =H16 -> 1.47 | I17: =ROUND(F17*G17*H17,3) -> 0
F18: =ROUND((D18+E18)*2/1000,4) -> 0 | H18: =H17 -> 1.47 | I18: =ROUND(F18*G18*H18,3) -> 0
F19: =ROUND((D19+E19)*2/1000,4) -> 0 | H19: =H18 -> 1.47 | I19: =ROUND(F19*G19*H19,3) -> 0
F20: =ROUND((D20+E20)*2/1000,4) -> 0 | H20: =H19 -> 1.47 | I20: =ROUND(F20*G20*H20,3) -> 0
F21: =ROUND((D21+E21)*2/1000,4) -> 0 | H21: =H20 -> 1.47 | I21: =ROUND(F21*G21*H21,3) -> 0
B22: 型材总长度 | C22: =SUMPRODUCT(F14:F21*G14:G21) -> 7.32 | D22: 型材总重量 | E22: =SUM(I14:I21)*1.1 -> 14.3759 | F22: 型材单价 | G22: =(C$218+C$219)/1000 -> 46.0815 | H22: 型材总价 | I22: =ROUND(E22*G22,2) -> 662.46 | J22: =SUM(G14:G21) -> 2
B23: 外侧装饰面长 | C23: 207.36 | D23: 外侧装饰面积 | E23: =ROUND(C22*(C23/1000),2) -> 1.52 | F23: 喷涂单价 | G23: 10 | H23: 喷涂总价 | I23: =E23*G23 -> 15.2
B24: 内侧装饰面长 | C24: 169.96 | D24: 内侧装饰面积 | E24: =ROUND(C22*(C24/1000),2) -> 1.24 | F24: 喷涂单价 | G24: 10 | H24: 喷涂总价 | I24: =E24*G24 -> 12.4
B25: 型材名称 | C25: 代号 | D25: 横 | E25: 竖 | F25: 周长 | G25: 数量 | H25: 线重 | I25: 重量 | J25: 宽 | K25: 高 | L25: 宽缩尺 | M25: 高缩尺 | N25: 代号
B26: 内平开窗扇 | C26: SDF2885 | D26: =J26-IF(L26=1,44,IF(L26=2,30,IF(L26=3,16,0))) -> 0 | E26: =K26-IF(M26=1,44,IF(M26=2,30,IF(M26=3,16,0))) -> 0 | F26: =ROUND((D26+E26)*2/1000,4) -> 0 | H26: 1.62 | I26: =IF(AND(D26>0,E26>0,F26>0),F26*G26*H26,0) -> 0 | N26: 1.框-框 | O26: 普通扇
D27: =J27-IF(L27=1,44,IF(L27=2,30,IF(L27=3,16,0))) -> 0 | E27: =K27-IF(M27=1,44,IF(M27=2,30,IF(M27=3,16,0))) -> 0 | F27: =ROUND((D27+E27)*2/1000,4) -> 0 | H27: =H26 -> 1.62 | I27: =IF(AND(D27>0,E27>0,F27>0),F27*G27*H27,0) -> 0 | N27: 2.框-中梃 | O27: 钢化扇
D28: =J28-IF(L28=1,44,IF(L28=2,30,IF(L28=3,16,0))) -> 0 | E28: =K28-IF(M28=1,44,IF(M28=2,30,IF(M28=3,16,0))) -> 0 | F28: =ROUND((D28+E28)*2/1000,4) -> 0 | H28: =H27 -> 1.62 | I28: =IF(AND(D28>0,E28>0,F28>0),F28*G28*H28,0) -> 0 | N28: 3.中梃-中梃 | O28: 钢化扇
D29: =J29-IF(L29=1,44,IF(L29=2,30,IF(L29=3,16,0))) -> 0 | E29: =K29-IF(M29=1,44,IF(M29=2,30,IF(M29=3,16,0))) -> 0 | F29: =ROUND((D29+E29)*2/1000,4) -> 0 | H29: =H28 -> 1.62 | I29: =IF(AND(D29>0,E29>0,F29>0),F29*G29*H29,0) -> 0
D30: =J30-IF(L30=1,44,IF(L30=2,30,IF(L30=3,16,0))) -> 0 | E30: =K30-IF(M30=1,44,IF(M30=2,30,IF(M30=3,16,0))) -> 0 | F30: =ROUND((D30+E30)*2/1000,4) -> 0 | H30: =H29 -> 1.62 | I30: =IF(AND(D30>0,E30>0,F30>0),F30*G30*H30,0) -> 0
B31: 型材总长度 | C31: =SUMPRODUCT(F26:F30*G26:G30) -> 0 | D31: 型材总重量 | E31: =SUM(I26:I30)*1.1 -> 0 | F31: 型材单价 | G31: =(C$218+C$221)/1000 -> 46.0815 | H31: 型材总价 | I31: =ROUND(E31*G31,2) -> 0 | J31: =SUM(G26:G30) -> 0
B32: 外侧装饰面长 | C32: 183.32 | D32: 外侧装饰面积 | E32: =ROUND(C31*(C32/1000),2) -> 0 | F32: 喷涂单价 | G32: =G$23 -> 10 | H32: 喷涂总价 | I32: =E32*G32 -> 0
B33: 内侧装饰面长 | C33: 257.82 | D33: 内侧装饰面积 | E33: =ROUND(C31*(C33/1000),2) -> 0 | F33: 喷涂单价 | G33: =G$24 -> 10 | H33: 喷涂总价 | I33: =E33*G33 -> 0
B34: 型材名称 | C34: 代号 | D34: 横 | E34: 竖 | F34: 周长 | G34: 数量 | H34: 线重 | I34: 重量 | J34: 宽 | K34: 高 | L34: （宽）缩尺 | M34: （高）缩尺 | N34: 代号
B35: 外平开窗扇 | C35: SDF2806 | D35: =J35-IF(L35=1,44,IF(L35=2,30,IF(L35=3,16,IF(L35=11,118,IF(L35=12,100,IF(L35=13,76.8,0)))))) -> 480 | E35: =K35-IF(M35=1,44,IF(M35=2,30,IF(M35=3,16,IF(M35=11,118,IF(M35=12,100,IF(M35=13,76.8,0)))))) -> 1026 | F35: =ROUND((D35+E35)*2/1000,4) -> 3.012 | G35: 2 | H35: 1.814 | I35: =ROUND(F35*G35*H35,3) -> 10.928 | J35: =D14/2 -> 510 | K35: =E15 -> 1070 | L35: 2 | M35: 1 | N35: 1.框-框
D36: =J36-IF(L36=1,44,IF(L36=2,30,IF(L36=3,16,IF(L36=11,118,IF(L36=12,100,IF(L36=13,76.8,0)))))) -> 0 | E36: =K36-IF(M36=1,44,IF(M36=2,30,IF(M36=3,16,IF(M36=11,118,IF(M36=12,100,IF(M36=13,76.8,0)))))) -> 0 | F36: =ROUND((D36+E36)*2/1000,4) -> 0 | H36: =H35 -> 1.814 | I36: =ROUND(F36*G36*H36,3) -> 0 | N36: 2.框-中梃
D37: =J37-IF(L37=1,44,IF(L37=2,30,IF(L37=3,16,IF(L37=11,118,IF(L37=12,100,IF(L37=13,76.8,0)))))) -> 0 | E37: =K37-IF(M37=1,44,IF(M37=2,30,IF(M37=3,16,IF(M37=11,118,IF(M37=12,100,IF(M37=13,76.8,0)))))) -> 0 | F37: =ROUND((D37+E37)*2/1000,4) -> 0 | H37: =H36 -> 1.814 | I37: =ROUND(F37*G37*H37,3) -> 0 | N37: 3.中梃-中梃
B38: 型材总长度 | C38: =SUMPRODUCT(F35:F37*G35:G37) -> 6.024 | D38: 型材总重量 | E38: =SUM(I35:I37)*1.1 -> 12.0208 | F38: 型材单价 | G38: =(C$218+C$219)/1000 -> 46.0815 | H38: 型材总价 | I38: =ROUND(E38*G38,2) -> 553.94 | J38: =SUM(G35:G37) -> 2 | N38: 11.转.框-框
B39: 外侧装饰面长 | C39: 320.14 | D39: 外侧装饰面积 | E39: =ROUND(C38*(C39/1000),2) -> 1.93 | F39: 喷涂单价 | G39: =G$23 -> 10 | H39: 喷涂总价 | I39: =E39*G39 -> 19.3 | N39: 12.转.框-中梃
B40: 内侧装饰面长 | C40: 156.99 | D40: 内侧装饰面积 | E40: =ROUND(C38*(C40/1000),2) -> 0.95 | F40: 喷涂单价 | G40: =G$24 -> 10 | H40: 喷涂总价 | I40: =E40*G40 -> 9.5 | N40: 13.转.中梃-中梃
B41: 型材名称 | C41: 代号 | D41: 横 | E41: 竖 | F41: 周长 | G41: 数量 | H41: 线重 | I41: 重量 | J41: 宽 | K41: 高 | L41: （宽）缩尺 | M41: （高）缩尺 | N41: 代号
B42: 转换料 | C42: SDF3162 (扇转换） | D42: =J42-IF(L42=1,46,IF(L42=2,34.5,IF(L42=3,23))) -> 0 | E42: =K42-IF(M42=1,46,IF(M42=2,34.5,IF(M42=3,23))) -> 0 | F42: =ROUND((D42+E42)*2/1000,4) -> 0 | H42: 1.26 | I42: =ROUND(F42*G42*H42,3) -> 0 | N42: 1.框-框
D43: =J43-IF(L43=1,46,IF(L43=2,34.5,IF(L43=3,23))) -> 0 | E43: =K43-IF(M43=1,46,IF(M43=2,34.5,IF(M43=3,23))) -> 0 | F43: =ROUND((D43+E43)*2/1000,4) -> 0 | H43: =H42 -> 1.26 | I43: =ROUND(F43*G43*H43,3) -> 0 | N43: 2.框-中梃
D44: =J44-IF(L44=1,46,IF(L44=2,34.5,IF(L44=3,23))) -> 0 | E44: =K44-IF(M44=1,46,IF(M44=2,34.5,IF(M44=3,23))) -> 0 | F44: =ROUND((D44+E44)*2/1000,4) -> 0 | H44: =H43 -> 1.26 | I44: =ROUND(F44*G44*H44,3) -> 0 | N44: 3.中梃-中梃
C45: SDF3162 (固定转换） | D45: =J45-IF(L45=1,46,IF(L45=2,34.5,IF(L45=3,23))) -> 0 | E45: =K45-IF(M45=1,46,IF(M45=2,34.5,IF(M45=3,23))) -> 0 | F45: =ROUND((D45+E45)*2/1000,4) -> 0 | H45: =H44 -> 1.26 | I45: =ROUND(F45*G45*H45,3) -> 0 | N45: 1.框-框
D46: =J46-IF(L46=1,46,IF(L46=2,34.5,IF(L46=3,23))) -> 0 | E46: =K46-IF(M46=1,46,IF(M46=2,34.5,IF(M46=3,23))) -> 0 | F46: =ROUND((D46+E46)*2/1000,4) -> 0 | H46: =H45 -> 1.26 | I46: =ROUND(F46*G46*H46,3) -> 0 | N46: 2.框-中梃
D47: =J47-IF(L47=1,46,IF(L47=2,34.5,IF(L47=3,23))) -> 0 | E47: =K47-IF(M47=1,46,IF(M47=2,34.5,IF(M47=3,23))) -> 0 | F47: =ROUND((D47+E47)*2/1000,4) -> 0 | H47: =H46 -> 1.26 | I47: =ROUND(F47*G47*H47,3) -> 0 | N47: 3.中梃-中梃
B48: 型材总长度 | C48: =SUMPRODUCT(F42:F47*G42:G47) -> 0 | D48: 型材总重量 | E48: =SUM(I42:I47)*1.1 -> 0 | F48: 型材单价 | G48: =(C$218+C$219)/1000 -> 46.0815 | H48: 型材总价 | I48: =ROUND(E48*G48,2) -> 0 | J48: =SUM(G42:G47) -> 0
B49: 外侧装饰面长 | C49: 132.48 | D49: 外侧装饰面积 | E49: =ROUND(C48*(C49/1000),2) -> 0 | F49: 喷涂单价 | G49: =G$23 -> 10 | H49: 喷涂总价 | I49: =E49*G49 -> 0
B50: 内侧装饰面长 | C50: 202.06 | D50: 内侧装饰面积 | E50: =ROUND(C48*(C50/1000),2) -> 0 | F50: 喷涂单价 | G50: =G$24 -> 10 | H50: 喷涂总价 | I50: =E50*G50 -> 0
B51: 型材名称 | C51: 代号 | D51: 横 | E51: 横数量 | F51: 竖 | G51: 竖数量 | H51: 线重 | I51: 重量 | J51: 宽 | K51: 高 | L51: （宽）缩尺 | M51: （高）缩尺 | N51: 代号
B52: 窗中梃 | C52: SDF3160 | D52: =J52-IF(L52=1,46,IF(L52=2,32,IF(L52=3,18,0))) -> 0 | F52: =K52-IF(M52=1,46,IF(M52=2,32,IF(M52=3,118,0))) -> 1024 | G52: 1 | H52: 1.638 | I52: =ROUND((D52*E52+F52*G52)/1000*H52,3) -> 1.677 | K52: =K35 -> 1070 | M52: 1 | N52: 1.框-框
D53: =J53-IF(L53=1,46,IF(L53=2,32,IF(L53=3,18,0))) -> 0 | F53: =K53-IF(M53=1,46,IF(M53=2,32,IF(M53=3,118,0))) -> 0 | H53: =H52 -> 1.638 | I53: =ROUND((D53*E53+F53*G53)/1000*H53,3) -> 0 | N53: 2.框-中梃
D54: =J54-IF(L54=1,46,IF(L54=2,32,IF(L54=3,18,0))) -> 0 | F54: =K54-IF(M54=1,46,IF(M54=2,32,IF(M54=3,118,0))) -> 0 | H54: =H53 -> 1.638 | I54: =ROUND((D54*E54+F54*G54)/1000*H54,3) -> 0 | N54: 3.中梃-中梃
D55: =J55-IF(L55=1,46,IF(L55=2,32,IF(L55=3,18,0))) -> 0 | F55: =K55-IF(M55=1,46,IF(M55=2,32,IF(M55=3,118,0))) -> 0 | H55: =H54 -> 1.638 | I55: =ROUND((D55*E55+F55*G55)/1000*H55,3) -> 0
B56: 型材总长度 | C56: =SUMPRODUCT(D52:D55*E52:E55+F52:F55*G52:G55)/1000 -> 1.024 | D56: 型材总重量 | E56: =SUM(I52:I55)*1.1 -> 1.8447 | F56: 型材单价 | G56: =(C$218+C$219)/1000 -> 46.0815 | H56: 型材总价 | I56: =ROUND(E56*G56,2) -> 85.01 | J56: =SUM(E52:E55)+SUM(G52:G55) -> 1
B57: 外侧装饰面长 | C57: 265.53 | D57: 外侧装饰面积 | E57: =ROUND(C56*(C57/1000),2) -> 0.27 | F57: 喷涂单价 | G57: =G$23 -> 10 | H57: 喷涂总价 | I57: =E57*G57 -> 2.7
B58: 内侧装饰面长 | C58: 173.62 | D58: 内侧装饰面积 | E58: =ROUND(C56*(C58/1000),2) -> 0.18 | F58: 喷涂单价 | G58: =G$24 -> 10 | H58: 喷涂总价 | I58: =E58*G58 -> 1.8
B59: 型材名称 | C59: 代号 | D59: 竖/横 | G59: 竖/横数量 | H59: 线重 | I59: 重量
B60: 加强中梃 | C60: SDF2808 | H60: 1.934 | I60: =ROUND(D60*G60*H60/1000,3) -> 0
H61: 1.934 | I61: =ROUND(D61*G61*H61/1000,3) -> 0
C62: SDF2809 | H62: 2.313 | I62: =ROUND(D62*G62*H62/1000,3) -> 0
H63: 2.313 | I63: =ROUND(D63*G63*H63/1000,3) -> 0
B64: 型材总长度 | C64: =SUMPRODUCT(D60:F63*G60:G63)/1000 -> 0 | D64: 型材总重量 | E64: =SUM(I60:I63)*1.1 -> 0 | F64: 型材单价 | G64: =(C$218+C$219)/1000 -> 46.0815 | H64: 型材总价 | I64: =ROUND(E64*G64,2) -> 0 | J64: =SUM(G60:G63) -> 0
B65: 外侧装饰面长 | C65: 337.92 | D65: 外侧装饰面积 | E65: =ROUND(C64*(C65/1000),2) -> 0 | F65: 喷涂单价 | G65: =G$23 -> 10 | H65: 喷涂总价 | I65: =E65*G65 -> 0
B66: 内侧装饰面长 | C66: 175.93 | D66: 内侧装饰面积 | E66: =ROUND(C64*(C66/1000),2) -> 0 | F66: 喷涂单价 | G66: =G$24 -> 10 | H66: 喷涂总价 | I66: =E66*G66 -> 0
B67: 型材名称 | C67: 代号 | D67: 横 | E67: 竖 | F67: 周长 | G67: 数量 | H67: 线重 | I67: 重量 | J67: 宽 | K67: 高 | L67: 宽缩尺 | M67: 高缩尺 | N67: 代号
B68: 固定压线 | C68: 普（SDL2280） | D68: =J68-IF(L68=1,72,IF(L68=2,54,IF(L68=3,26,IF(L68=11,102.8,IF(L68=12,88.8,IF(L68=13,74.8,0)))))) -> 948 | E68: =K68-IF(M68=1,72,IF(M68=2,24,IF(M68=3,26,IF(M68=11,102.8,IF(M68=12,88.8,IF(M68=13,74.8,0)))))) -> 478 | F68: =2*(D68+E68)/1000 -> 2.852 | G68: 1 | H68: 0.224 | I68: =ROUND(F68*G68*H68,3)*1.5 -> 0.9585 | J68: =D14 -> 1020 | K68: =E14 -> 550 | L68: 1 | M68: 1 | N68: 1.框-框
D69: =J69-IF(L69=1,72,IF(L69=2,54,IF(L69=3,26,IF(L69=11,102.8,IF(L69=12,88.8,IF(L69=13,74.8,0)))))) -> 0 | E69: =K69-IF(M69=1,72,IF(M69=2,24,IF(M69=3,26,IF(M69=11,102.8,IF(M69=12,88.8,IF(M69=13,74.8,0)))))) -> 0 | F69: =2*(D69+E69)/1000 -> 0 | H69: =H68 -> 0.224 | I69: =ROUND(F69*G69*H69,3) -> 0 | N69: 2.框-中梃
D70: =J70-IF(L70=1,72,IF(L70=2,54,IF(L70=3,26,IF(L70=11,102.8,IF(L70=12,88.8,IF(L70=13,74.8,0)))))) -> 0 | E70: =K70-IF(M70=1,72,IF(M70=2,24,IF(M70=3,26,IF(M70=11,102.8,IF(M70=12,88.8,IF(M70=13,74.8,0)))))) -> 0 | F70: =2*(D70+E70)/1000 -> 0 | H70: =H69 -> 0.224 | I70: =ROUND(F70*G70*H70,3) -> 0 | N70: 3.中梃-中梃
D71: =J71-IF(L71=1,72,IF(L71=2,54,IF(L71=3,26,IF(L71=11,102.8,IF(L71=12,88.8,IF(L71=13,74.8,0)))))) -> 0 | E71: =K71-IF(M71=1,72,IF(M71=2,24,IF(M71=3,26,IF(M71=11,102.8,IF(M71=12,88.8,IF(M71=13,74.8,0)))))) -> 0 | F71: =2*(D71+E71)/1000 -> 0 | H71: =H70 -> 0.224 | I71: =ROUND(F71*G71*H71,3) -> 0 | N71: 11.转.框-框
D72: =J72-IF(L72=1,72,IF(L72=2,54,IF(L72=3,26,IF(L72=11,102.8,IF(L72=12,88.8,IF(L72=13,74.8,0)))))) -> 0 | E72: =K72-IF(M72=1,72,IF(M72=2,24,IF(M72=3,26,IF(M72=11,102.8,IF(M72=12,88.8,IF(M72=13,74.8,0)))))) -> 0 | F72: =2*(D72+E72)/1000 -> 0 | H72: =H71 -> 0.224 | I72: =ROUND(F72*G72*H72,3) -> 0 | N72: 12.转.框-中梃
D73: =J73-IF(L73=1,72,IF(L73=2,54,IF(L73=3,26,IF(L73=11,102.8,IF(L73=12,88.8,IF(L73=13,74.8,0)))))) -> 0 | E73: =K73-IF(M73=1,72,IF(M73=2,24,IF(M73=3,26,IF(M73=11,102.8,IF(M73=12,88.8,IF(M73=13,74.8,0)))))) -> 0 | F73: =2*(D73+E73)/1000 -> 0 | H73: =H70 -> 0.224 | I73: =ROUND(F73*G73*H73,3) -> 0 | N73: 13.转.中梃-中梃
D74: =J74-IF(L74=1,72,IF(L74=2,54,IF(L74=3,26,IF(L74=11,102.8,IF(L74=12,88.8,IF(L74=13,74.8,0)))))) -> 0 | E74: =K74-IF(M74=1,72,IF(M74=2,24,IF(M74=3,26,IF(M74=11,102.8,IF(M74=12,88.8,IF(M74=13,74.8,0)))))) -> 0 | F74: =2*(D74+E74)/1000 -> 0 | H74: =H73 -> 0.224 | I74: =ROUND(F74*G74*H74,3) -> 0
C75: 钢（SDL2280） | D75: =J75-IF(L75=1,72,IF(L75=2,54,IF(L75=3,26,IF(L75=11,102.8,IF(L75=12,88.8,IF(L75=13,74.8,0)))))) -> 0 | E75: =K75-IF(M75=1,72,IF(M75=2,24,IF(M75=3,26,IF(M75=11,102.8,IF(M75=12,88.8,IF(M75=13,74.8,0)))))) -> 0 | F75: =2*(D75+E75)/1000 -> 0 | H75: =H74 -> 0.224 | I75: =ROUND(F75*G75*H75,3) -> 0 | N75: g钢化固定
D76: =J76-IF(L76=1,72,IF(L76=2,54,IF(L76=3,26,IF(L76=11,102.8,IF(L76=12,88.8,IF(L76=13,74.8,0)))))) -> 0 | E76: =K76-IF(M76=1,72,IF(M76=2,24,IF(M76=3,26,IF(M76=11,102.8,IF(M76=12,88.8,IF(M76=13,74.8,0)))))) -> 0 | F76: =2*(D76+E76)/1000 -> 0 | H76: =H72 -> 0.224 | I76: =ROUND(F76*G76*H76,3) -> 0 | N76: g钢化固定
D77: =J77-IF(L77=1,72,IF(L77=2,54,IF(L77=3,26,IF(L77=11,102.8,IF(L77=12,88.8,IF(L77=13,74.8,0)))))) -> 0 | E77: =K77-IF(M77=1,72,IF(M77=2,24,IF(M77=3,26,IF(M77=11,102.8,IF(M77=12,88.8,IF(M77=13,74.8,0)))))) -> 0 | F77: =2*(D77+E77)/1000 -> 0 | H77: =H76 -> 0.224 | I77: =ROUND(F77*G77*H77,3) -> 0 | N77: g钢化固定
D78: =J78-IF(L78=1,72,IF(L78=2,54,IF(L78=3,26,IF(L78=11,102.8,IF(L78=12,88.8,IF(L78=13,74.8,0)))))) -> 0 | E78: =K78-IF(M78=1,72,IF(M78=2,24,IF(M78=3,26,IF(M78=11,102.8,IF(M78=12,88.8,IF(M78=13,74.8,0)))))) -> 0 | F78: =2*(D78+E78)/1000 -> 0 | H78: =H77 -> 0.224 | I78: =ROUND(F78*G78*H78,3) -> 0 | N78: g钢化固定
D79: =J79-IF(L79=1,72,IF(L79=2,54,IF(L79=3,26,IF(L79=11,102.8,IF(L79=12,88.8,IF(L79=13,74.8,0)))))) -> 0 | E79: =K79-IF(M79=1,72,IF(M79=2,24,IF(M79=3,26,IF(M79=11,102.8,IF(M79=12,88.8,IF(M79=13,74.8,0)))))) -> 0 | F79: =2*(D79+E79)/1000 -> 0 | H79: =H78 -> 0.224 | I79: =ROUND(F79*G79*H79,3) -> 0 | N79: g钢化固定
D80: =J80-IF(L80=1,72,IF(L80=2,54,IF(L80=3,26,IF(L80=11,102.8,IF(L80=12,88.8,IF(L80=13,74.8,0)))))) -> 0 | E80: =K80-IF(M80=1,72,IF(M80=2,24,IF(M80=3,26,IF(M80=11,102.8,IF(M80=12,88.8,IF(M80=13,74.8,0)))))) -> 0 | F80: =2*(D80+E80)/1000 -> 0 | H80: =H79 -> 0.224 | I80: =ROUND(F80*G80*H80,3) -> 0 | N80: g钢化固定
D81: =J81-IF(L81=1,72,IF(L81=2,54,IF(L81=3,26,IF(L81=11,102.8,IF(L81=12,88.8,IF(L81=13,74.8,0)))))) -> 0 | E81: =K81-IF(M81=1,72,IF(M81=2,24,IF(M81=3,26,IF(M81=11,102.8,IF(M81=12,88.8,IF(M81=13,74.8,0)))))) -> 0 | F81: =2*(D81+E81)/1000 -> 0 | H81: =H80 -> 0.224 | I81: =ROUND(F81*G81*H81,3) -> 0 | N81: 超大钢化固定6mm
C82: 夹胶钢（SDL2280） | D82: =J82-IF(L82=1,72,IF(L82=2,54,IF(L82=3,26,IF(L82=11,102.8,IF(L82=12,88.8,IF(L82=13,74.8,0)))))) -> 0 | E82: =K82-IF(M82=1,72,IF(M82=2,24,IF(M82=3,26,IF(M82=11,102.8,IF(M82=12,88.8,IF(M82=13,74.8,0)))))) -> 0 | F82: =2*(D82+E82)/1000 -> 0 | H82: =H81 -> 0.224 | I82: =ROUND(F82*G82*H82,3) -> 0
D83: =J83-IF(L83=1,72,IF(L83=2,54,IF(L83=3,26,IF(L83=11,102.8,IF(L83=12,88.8,IF(L83=13,74.8,0)))))) -> 0 | E83: =K83-IF(M83=1,72,IF(M83=2,24,IF(M83=3,26,IF(M83=11,102.8,IF(M83=12,88.8,IF(M83=13,74.8,0)))))) -> 0 | F83: =2*(D83+E83)/1000 -> 0 | H83: =H82 -> 0.224 | I83: =ROUND(F83*G83*H83,3) -> 0
D84: =J84-IF(L84=1,72,IF(L84=2,54,IF(L84=3,26,IF(L84=11,102.8,IF(L84=12,88.8,IF(L84=13,74.8,0)))))) -> 0 | E84: =K84-IF(M84=1,72,IF(M84=2,24,IF(M84=3,26,IF(M84=11,102.8,IF(M84=12,88.8,IF(M84=13,74.8,0)))))) -> 0 | F84: =2*(D84+E84)/1000 -> 0 | H84: =H83 -> 0.224 | I84: =ROUND(F84*G84*H84,3) -> 0
D85: =J85-IF(L85=1,72,IF(L85=2,54,IF(L85=3,26,IF(L85=11,102.8,IF(L85=12,88.8,IF(L85=13,74.8,0)))))) -> 0 | E85: =K85-IF(M85=1,72,IF(M85=2,24,IF(M85=3,26,IF(M85=11,102.8,IF(M85=12,88.8,IF(M85=13,74.8,0)))))) -> 0 | F85: =2*(D85+E85)/1000 -> 0 | H85: =H84 -> 0.224 | I85: =ROUND(F85*G85*H85,3) -> 0
D86: =J86-IF(L86=1,72,IF(L86=2,54,IF(L86=3,26,IF(L86=11,102.8,IF(L86=12,88.8,IF(L86=13,74.8,0)))))) -> 0 | E86: =K86-IF(M86=1,72,IF(M86=2,24,IF(M86=3,26,IF(M86=11,102.8,IF(M86=12,88.8,IF(M86=13,74.8,0)))))) -> 0 | F86: =2*(D86+E86)/1000 -> 0 | H86: =H85 -> 0.224 | I86: =ROUND(F86*G86*H86,3) -> 0
D87: =J87-IF(L87=1,72,IF(L87=2,54,IF(L87=3,26,IF(L87=11,102.8,IF(L87=12,88.8,IF(L87=13,74.8,0)))))) -> 0 | E87: =K87-IF(M87=1,72,IF(M87=2,24,IF(M87=3,26,IF(M87=11,102.8,IF(M87=12,88.8,IF(M87=13,74.8,0)))))) -> 0 | F87: =2*(D87+E87)/1000 -> 0 | H87: =H86 -> 0.224 | I87: =ROUND(F87*G87*H87,3) -> 0
B88: 型材总长度 | C88: =SUMPRODUCT(F68:F87*G68:G87) -> 2.852 | D88: 型材总重量 | E88: =SUM(I68:I87)*1.1 -> 1.05435 | F88: 型材单价 | G88: =(C$218+C$222)/1000 -> 39.7815 | H88: 型材总价 | I88: =ROUND(E88*G88,2) -> 41.94
B89: 外侧装饰面长 | C89: 181.72 | D89: 外侧装饰面积 | E89: =ROUND(C88*(C89/1000),2) -> 0.52 | F89: 喷涂单价 | G89: =G$23 -> 10 | H89: 喷涂总价 | I89: =E89*G89 -> 5.2
B90: 内侧装饰面长 | D90: 内侧装饰面积 | E90: =ROUND(C88*(C90/1000),2) -> 0 | F90: 喷涂单价 | G90: =G$24 -> 10 | H90: 喷涂总价 | I90: =E90*G90 -> 0
B91: 型材名称 | C91: 代号 | D91: 横 | E91: 竖 | F91: 周长 | G91: 数量 | H91: 线重 | I91: 重量
B92: 内开窗扇压线 | C92: SDL2281 | D92: =D26-90 -> -90 | E92: =E26-90 -> -90 | F92: =2*(D92+E92)/1000 -> -0.36 | G92: =G26 -> 0 | H92: 0.271 | I92: =ROUND(F92*G92*H92,3) -> 0
D93: =D27-90 -> -90 | E93: =E27-90 -> -90 | F93: =2*(D93+E93)/1000 -> -0.36 | G93: =G27 -> 0 | H93: =H92 -> 0.271 | I93: =ROUND(F93*G93*H93,3) -> 0
D94: =D28-90 -> -90 | E94: =E28-90 -> -90 | F94: =2*(D94+E94)/1000 -> -0.36 | G94: =G28 -> 0 | H94: =H93 -> 0.271 | I94: =ROUND(F94*G94*H94,3) -> 0
D95: =D29-90 -> -90 | E95: =E29-90 -> -90 | F95: =2*(D95+E95)/1000 -> -0.36 | G95: =G29 -> 0 | H95: =H94 -> 0.271 | I95: =ROUND(F95*G95*H95,3) -> 0
D96: =D30-90 -> -90 | E96: =E30-90 -> -90 | F96: =2*(D96+E96)/1000 -> -0.36 | G96: =G30 -> 0 | H96: =H95 -> 0.271 | I96: =ROUND(F96*G96*H96,3) -> 0
B97: 型材总长度 | C97: =SUMPRODUCT(F92:F96*G92:G96) -> 0 | D97: 型材总重量 | E97: =SUM(I92:I96)*1.1 -> 0 | F97: 型材单价 | G97: =(C$218+C$222)/1000 -> 39.7815 | H97: 型材总价 | I97: =ROUND(E97*G97,2) -> 0
B98: 外侧装饰面长 | C98: 186.72 | D98: 外侧装饰面积 | E98: =ROUND(C97*(C98/1000),2) -> 0 | F98: 喷涂单价 | G98: =G$23 -> 10 | H98: 喷涂总价 | I98: =E98*G98 -> 0
B99: 内侧装饰面长 | C99: 0 | D99: 内侧装饰面积 | E99: =ROUND(C97*(C99/1000),2) -> 0 | F99: 喷涂单价 | G99: =G$24 -> 10 | H99: 喷涂总价 | I99: =E99*G99 -> 0
B100: 型材名称 | C100: 代号 | D100: 横 | E100: 竖 | F100: 周长 | G100: 数量 | H100: 线重 | I100: 重量
B101: 外开窗扇压线 | C101: =C92 -> SDL2281 | D101: =D35-122 -> 358 | E101: =E35-122 -> 904 | F101: =2*(D101+E101)/1000 -> 2.524 | G101: =G35 -> 2 | H101: =H96 -> 0.271 | I101: =ROUND(F101*G101*H101,3) -> 1.368
...

Sheet C1122
B2: MS65F系列（注胶角码） | D2: 24mm | E2: 表面处理 | F2: 静电粉末喷涂 | I2: N0.1 | J2: 副框线重速求表
B3: 代号 | C3: 门窗尺寸 | D3: 宽度 | E3: 高度 | F3: 面积 | G3: 樘数 | H3: 总面积 | J3: 宽度:mm | K3: 高度:mm | L3: 壁厚:mm | M3: 线重
B4: =MID(CELL("filename",Q13),FIND("]",CELL("filename",Q13))+1,30) -> C1122 | C4: 洞口尺寸 | D4: 1100 | E4: 2150 | F4: 2.125 | G4: 1 | H4: =F4*G4 -> 2.125 | J4: 40 | K4: 20 | L4: 1.5 | M4: =ROUND(((J4*K4)-(J4-2*L4)*(K4-2*L4))*7.8/1000,3) -> 1.334
C5: 附框内口尺寸 | D5: =D4-70 -> 1030 | E5: =E4-70 -> 2080 | F5: =D5*E5/10^6 -> 2.1424 | G5: 1 | H5: =F5*G5 -> 2.1424 | J5: 40 | K5: 20 | L5: 2 | M5: =ROUND(((J5*K5)-(J5-2*L5)*(K5-2*L5))*7.8/1000,3) -> 1.747
C6: 主框尺寸 | D6: =D4-80 -> 1020 | E6: =E4-80 -> 2070 | F6: =D6*E6/10^6 -> 2.1114 | G6: 1 | H6: =F6*G6 -> 2.1114 | J6: 40 | K6: 20 | L6: 2 | M6: =ROUND(((J6*K6)-(J6-2*L6)*(K6-2*L6))*7.8/1000,3) -> 1.747
B7: 钢副框（热） | C7: 宽度 | D7: 宽数量 | E7: 高度 | F7: 高数量 | G7: 线重 | H7: 单价 | I7: 总价 | J7: 80 | K7: 40 | L7: 2 | M7: =ROUND(((J7*K7)-(J7-2*L7)*(K7-2*L7))*7.8/1000,3) -> 3.619
B8: 40*20*2.0 | C8: =D4-30 -> 1070 | D8: 2 | E8: =E4-30 -> 2120 | F8: 2 | G8: 1.747 | H8: =材料价格!B3 -> 7.5 | I8: =ROUND((C8*D8+E8*F8)*G8*H8/1000*1.1,2) -> 91.95 | J8: 40 | K8: 20 | L8: 1.4 | M8: =ROUND(((J8*K8)-(J8-2*L8)*(K8-2*L8))*2.71/1000,3) -> 0.434
B9: 40*20*2.0 | G9: 1.747 | H9: =H8 -> 7.5 | I9: =ROUND((C9*D9+E9*F9)*G9*H9/1000*1.1,2) -> 0 | M9: =ROUND(((J9*K9)-(J9-2*L9)*(K9-2*L9))*7.8/1000,3) -> 0
B10: 80*40*2 | G10: 3.619 | H10: =H9 -> 7.5 | I10: =ROUND((C10*D10+E10*F10)*G10*H10/1000*1.1,2) -> 0 | M10: =ROUND(((J10*K10)-(J10-2*L10)*(K10-2*L10))*7.8/1000,3) -> 0
B11: 50*50*2.0 | G11: 2.995 | H11: =H10 -> 7.5 | I11: =ROUND((C11*D11+E11*F11)*G11*H11/1000*1.1,2) -> 0 | M11: =ROUND(((J11*K11)-(J11-2*L11)*(K11-2*L11))*7.8/1000,3) -> 0
B12: 副框平米用量 | C12: =((I9+I10+I8+I11)/H8)/F4 -> 5.7694118 | D12: （Kg/m2) | E12: =(I9+I10+I8+I11)/F4 -> 43.270588 | F12: （元/m2) | H12: =ROUND(SUM(I8:I11)/H8,2) -> 12.26 | I12: =SUM(I8:I11) -> 91.95
B13: 型材名称 | C13: 代号 | D13: 横 | E13: 竖 | F13: 周长 | G13: 数量 | H13: 线重 | I13: 重量
B14: 平开窗框 | C14: SDF2894 | D14: =D6 -> 1020 | E14: 550 | F14: =ROUND((D14+E14)*2/1000,4) -> 3.14 | G14: 1 | H14: 1.47 | I14: =ROUND(F14*G14*H14,3)*1.5 -> 6.924
D15: =D14 -> 1020 | E15: =E6-E14 -> 1520 | F15: =ROUND((D15+E15)*2/1000,4) -> 5.08 | G15: 1 | H15: =H14 -> 1.47 | I15: =ROUND(F15*G15*H15,3) -> 7.468
F16: =ROUND((D16+E16)*2/1000,4) -> 0 | H16: =H15 -> 1.47 | I16: =ROUND(F16*G16*H16,3) -> 0
F17: =ROUND((D17+E17)*2/1000,4) -> 0 | H17: =H16 -> 1.47 | I17: =ROUND(F17*G17*H17,3) -> 0
F18: =ROUND((D18+E18)*2/1000,4) -> 0 | H18: =H17 -> 1.47 | I18: =ROUND(F18*G18*H18,3) -> 0
F19: =ROUND((D19+E19)*2/1000,4) -> 0 | H19: =H18 -> 1.47 | I19: =ROUND(F19*G19*H19,3) -> 0
F20: =ROUND((D20+E20)*2/1000,4) -> 0 | H20: =H19 -> 1.47 | I20: =ROUND(F20*G20*H20,3) -> 0
F21: =ROUND((D21+E21)*2/1000,4) -> 0 | H21: =H20 -> 1.47 | I21: =ROUND(F21*G21*H21,3) -> 0
B22: 型材总长度 | C22: =SUMPRODUCT(F14:F21*G14:G21) -> 8.22 | D22: 型材总重量 | E22: =SUM(I14:I21)*1.1 -> 15.8312 | F22: 型材单价 | G22: =(C$218+C$219)/1000 -> 46.0815 | H22: 型材总价 | I22: =ROUND(E22*G22,2) -> 729.53 | J22: =SUM(G14:G21) -> 2
B23: 外侧装饰面长 | C23: 207.36 | D23: 外侧装饰面积 | E23: =ROUND(C22*(C23/1000),2) -> 1.7 | F23: 喷涂单价 | G23: 10 | H23: 喷涂总价 | I23: =E23*G23 -> 17
B24: 内侧装饰面长 | C24: 169.96 | D24: 内侧装饰面积 | E24: =ROUND(C22*(C24/1000),2) -> 1.4 | F24: 喷涂单价 | G24: 10 | H24: 喷涂总价 | I24: =E24*G24 -> 14
B25: 型材名称 | C25: 代号 | D25: 横 | E25: 竖 | F25: 周长 | G25: 数量 | H25: 线重 | I25: 重量 | J25: 宽 | K25: 高 | L25: 宽缩尺 | M25: 高缩尺 | N25: 代号
B26: 内平开窗扇 | C26: SDF2885 | D26: =J26-IF(L26=1,44,IF(L26=2,30,IF(L26=3,16,0))) -> 0 | E26: =K26-IF(M26=1,44,IF(M26=2,30,IF(M26=3,16,0))) -> 0 | F26: =ROUND((D26+E26)*2/1000,4) -> 0 | H26: 1.62 | I26: =IF(AND(D26>0,E26>0,F26>0),F26*G26*H26,0) -> 0 | N26: 1.框-框 | O26: 普通扇
D27: =J27-IF(L27=1,44,IF(L27=2,30,IF(L27=3,16,0))) -> 0 | E27: =K27-IF(M27=1,44,IF(M27=2,30,IF(M27=3,16,0))) -> 0 | F27: =ROUND((D27+E27)*2/1000,4) -> 0 | H27: =H26 -> 1.62 | I27: =IF(AND(D27>0,E27>0,F27>0),F27*G27*H27,0) -> 0 | N27: 2.框-中梃 | O27: 钢化扇
D28: =J28-IF(L28=1,44,IF(L28=2,30,IF(L28=3,16,0))) -> 0 | E28: =K28-IF(M28=1,44,IF(M28=2,30,IF(M28=3,16,0))) -> 0 | F28: =ROUND((D28+E28)*2/1000,4) -> 0 | H28: =H27 -> 1.62 | I28: =IF(AND(D28>0,E28>0,F28>0),F28*G28*H28,0) -> 0 | N28: 3.中梃-中梃 | O28: 钢化扇
D29: =J29-IF(L29=1,44,IF(L29=2,30,IF(L29=3,16,0))) -> 0 | E29: =K29-IF(M29=1,44,IF(M29=2,30,IF(M29=3,16,0))) -> 0 | F29: =ROUND((D29+E29)*2/1000,4) -> 0 | H29: =H28 -> 1.62 | I29: =IF(AND(D29>0,E29>0,F29>0),F29*G29*H29,0) -> 0
D30: =J30-IF(L30=1,44,IF(L30=2,30,IF(L30=3,16,0))) -> 0 | E30: =K30-IF(M30=1,44,IF(M30=2,30,IF(M30=3,16,0))) -> 0 | F30: =ROUND((D30+E30)*2/1000,4) -> 0 | H30: =H29 -> 1.62 | I30: =IF(AND(D30>0,E30>0,F30>0),F30*G30*H30,0) -> 0
B31: 型材总长度 | C31: =SUMPRODUCT(F26:F30*G26:G30) -> 0 | D31: 型材总重量 | E31: =SUM(I26:I30)*1.1 -> 0 | F31: 型材单价 | G31: =(C$218+C$221)/1000 -> 46.0815 | H31: 型材总价 | I31: =ROUND(E31*G31,2) -> 0 | J31: =SUM(G26:G30) -> 0
B32: 外侧装饰面长 | C32: 183.32 | D32: 外侧装饰面积 | E32: =ROUND(C31*(C32/1000),2) -> 0 | F32: 喷涂单价 | G32: =G$23 -> 10 | H32: 喷涂总价 | I32: =E32*G32 -> 0
B33: 内侧装饰面长 | C33: 257.82 | D33: 内侧装饰面积 | E33: =ROUND(C31*(C33/1000),2) -> 0 | F33: 喷涂单价 | G33: =G$24 -> 10 | H33: 喷涂总价 | I33: =E33*G33 -> 0
B34: 型材名称 | C34: 代号 | D34: 横 | E34: 竖 | F34: 周长 | G34: 数量 | H34: 线重 | I34: 重量 | J34: 宽 | K34: 高 | L34: （宽）缩尺 | M34: （高）缩尺 | N34: 代号
B35: 外平开窗扇 | C35: SDF2806 | D35: =J35-IF(L35=1,44,IF(L35=2,30,IF(L35=3,16,IF(L35=11,118,IF(L35=12,100,IF(L35=13,76.8,0)))))) -> 410 | E35: =K35-IF(M35=1,44,IF(M35=2,30,IF(M35=3,16,IF(M35=11,118,IF(M35=12,100,IF(M35=13,76.8,0)))))) -> 1000 | F35: =ROUND((D35+E35)*2/1000,4) -> 2.82 | G35: 2 | H35: 1.814 | I35: =ROUND(F35*G35*H35,3) -> 10.231 | J35: =D14/2 -> 510 | K35: 1100 | L35: 12 | M35: 12 | N35: 1.框-框
D36: =J36-IF(L36=1,44,IF(L36=2,30,IF(L36=3,16,IF(L36=11,118,IF(L36=12,100,IF(L36=13,76.8,0)))))) -> 0 | E36: =K36-IF(M36=1,44,IF(M36=2,30,IF(M36=3,16,IF(M36=11,118,IF(M36=12,100,IF(M36=13,76.8,0)))))) -> 0 | F36: =ROUND((D36+E36)*2/1000,4) -> 0 | H36: =H35 -> 1.814 | I36: =ROUND(F36*G36*H36,3) -> 0 | N36: 2.框-中梃
D37: =J37-IF(L37=1,44,IF(L37=2,30,IF(L37=3,16,IF(L37=11,118,IF(L37=12,100,IF(L37=13,76.8,0)))))) -> 0 | E37: =K37-IF(M37=1,44,IF(M37=2,30,IF(M37=3,16,IF(M37=11,118,IF(M37=12,100,IF(M37=13,76.8,0)))))) -> 0 | F37: =ROUND((D37+E37)*2/1000,4) -> 0 | H37: =H36 -> 1.814 | I37: =ROUND(F37*G37*H37,3) -> 0 | N37: 3.中梃-中梃
B38: 型材总长度 | C38: =SUMPRODUCT(F35:F37*G35:G37) -> 5.64 | D38: 型材总重量 | E38: =SUM(I35:I37)*1.1 -> 11.2541 | F38: 型材单价 | G38: =(C$218+C$219)/1000 -> 46.0815 | H38: 型材总价 | I38: =ROUND(E38*G38,2) -> 518.61 | J38: =SUM(G35:G37) -> 2 | N38: 11.转.框-框
B39: 外侧装饰面长 | C39: 320.14 | D39: 外侧装饰面积 | E39: =ROUND(C38*(C39/1000),2) -> 1.81 | F39: 喷涂单价 | G39: =G$23 -> 10 | H39: 喷涂总价 | I39: =E39*G39 -> 18.1 | N39: 12.转.框-中梃
B40: 内侧装饰面长 | C40: 156.99 | D40: 内侧装饰面积 | E40: =ROUND(C38*(C40/1000),2) -> 0.89 | F40: 喷涂单价 | G40: =G$24 -> 10 | H40: 喷涂总价 | I40: =E40*G40 -> 8.9 | N40: 13.转.中梃-中梃
B41: 型材名称 | C41: 代号 | D41: 横 | E41: 竖 | F41: 周长 | G41: 数量 | H41: 线重 | I41: 重量 | J41: 宽 | K41: 高 | L41: （宽）缩尺 | M41: （高）缩尺 | N41: 代号
B42: 转换料 | C42: SDF3162 (扇转换） | D42: =J42-IF(L42=1,46,IF(L42=2,34.5,IF(L42=3,23))) -> 475.5 | E42: =K42-IF(M42=1,46,IF(M42=2,34.5,IF(M42=3,23))) -> 1065.5 | F42: =ROUND((D42+E42)*2/1000,4) -> 3.082 | G42: =G35 -> 2 | H42: 1.26 | I42: =ROUND(F42*G42*H42,3) -> 7.767 | J42: =J35 -> 510 | K42: =K35 -> 1100 | L42: 2 | M42: 2 | N42: 1.框-框
D43: =J43-IF(L43=1,46,IF(L43=2,34.5,IF(L43=3,23))) -> 0 | E43: =K43-IF(M43=1,46,IF(M43=2,34.5,IF(M43=3,23))) -> 0 | F43: =ROUND((D43+E43)*2/1000,4) -> 0 | H43: =H42 -> 1.26 | I43: =ROUND(F43*G43*H43,3) -> 0 | N43: 2.框-中梃
D44: =J44-IF(L44=1,46,IF(L44=2,34.5,IF(L44=3,23))) -> 0 | E44: =K44-IF(M44=1,46,IF(M44=2,34.5,IF(M44=3,23))) -> 0 | F44: =ROUND((D44+E44)*2/1000,4) -> 0 | H44: =H43 -> 1.26 | I44: =ROUND(F44*G44*H44,3) -> 0 | N44: 3.中梃-中梃
C45: SDF3162 (固定转换） | D45: =J45-IF(L45=1,46,IF(L45=2,34.5,IF(L45=3,23))) -> 0 | E45: =K45-IF(M45=1,46,IF(M45=2,34.5,IF(M45=3,23))) -> 0 | F45: =ROUND((D45+E45)*2/1000,4) -> 0 | H45: =H44 -> 1.26 | I45: =ROUND(F45*G45*H45,3) -> 0 | N45: 1.框-框
D46: =J46-IF(L46=1,46,IF(L46=2,34.5,IF(L46=3,23))) -> 0 | E46: =K46-IF(M46=1,46,IF(M46=2,34.5,IF(M46=3,23))) -> 0 | F46: =ROUND((D46+E46)*2/1000,4) -> 0 | H46: =H45 -> 1.26 | I46: =ROUND(F46*G46*H46,3) -> 0 | N46: 2.框-中梃
D47: =J47-IF(L47=1,46,IF(L47=2,34.5,IF(L47=3,23))) -> 0 | E47: =K47-IF(M47=1,46,IF(M47=2,34.5,IF(M47=3,23))) -> 0 | F47: =ROUND((D47+E47)*2/1000,4) -> 0 | H47: =H46 -> 1.26 | I47: =ROUND(F47*G47*H47,3) -> 0 | N47: 3.中梃-中梃
B48: 型材总长度 | C48: =SUMPRODUCT(F42:F47*G42:G47) -> 6.164 | D48: 型材总重量 | E48: =SUM(I42:I47)*1.1 -> 8.5437 | F48: 型材单价 | G48: =(C$218+C$219)/1000 -> 46.0815 | H48: 型材总价 | I48: =ROUND(E48*G48,2) -> 393.71 | J48: =SUM(G42:G47) -> 2
B49: 外侧装饰面长 | C49: 132.48 | D49: 外侧装饰面积 | E49: =ROUND(C48*(C49/1000),2) -> 0.82 | F49: 喷涂单价 | G49: =G$23 -> 10 | H49: 喷涂总价 | I49: =E49*G49 -> 8.2
B50: 内侧装饰面长 | C50: 202.06 | D50: 内侧装饰面积 | E50: =ROUND(C48*(C50/1000),2) -> 1.25 | F50: 喷涂单价 | G50: =G$24 -> 10 | H50: 喷涂总价 | I50: =E50*G50 -> 12.5
B51: 型材名称 | C51: 代号 | D51: 横 | E51: 横数量 | F51: 竖 | G51: 竖数量 | H51: 线重 | I51: 重量 | J51: 宽 | K51: 高 | L51: （宽）缩尺 | M51: （高）缩尺 | N51: 代号
B52: 窗中梃 | C52: SDF3160 | D52: =J52-IF(L52=1,46,IF(L52=2,32,IF(L52=3,18,0))) -> 478 | E52: 2 | F52: =K52-IF(M52=1,46,IF(M52=2,32,IF(M52=3,118,0))) -> 0 | H52: 1.638 | I52: =ROUND((D52*E52+F52*G52)/1000*H52,3) -> 1.566 | J52: =D14/2 -> 510 | L52: 2 | N52: 1.框-框
D53: =J53-IF(L53=1,46,IF(L53=2,32,IF(L53=3,18,0))) -> 0 | F53: =K53-IF(M53=1,46,IF(M53=2,32,IF(M53=3,118,0))) -> 0 | H53: =H52 -> 1.638 | I53: =ROUND((D53*E53+F53*G53)/1000*H53,3) -> 0 | N53: 2.框-中梃
D54: =J54-IF(L54=1,46,IF(L54=2,32,IF(L54=3,18,0))) -> 0 | F54: =K54-IF(M54=1,46,IF(M54=2,32,IF(M54=3,118,0))) -> 0 | H54: =H53 -> 1.638 | I54: =ROUND((D54*E54+F54*G54)/1000*H54,3) -> 0 | N54: 3.中梃-中梃
D55: =J55-IF(L55=1,46,IF(L55=2,32,IF(L55=3,18,0))) -> 0 | F55: =K55-IF(M55=1,46,IF(M55=2,32,IF(M55=3,118,0))) -> 0 | H55: =H54 -> 1.638 | I55: =ROUND((D55*E55+F55*G55)/1000*H55,3) -> 0
B56: 型材总长度 | C56: =SUMPRODUCT(D52:D55*E52:E55+F52:F55*G52:G55)/1000 -> 0.956 | D56: 型材总重量 | E56: =SUM(I52:I55)*1.1 -> 1.7226 | F56: 型材单价 | G56: =(C$218+C$219)/1000 -> 46.0815 | H56: 型材总价 | I56: =ROUND(E56*G56,2) -> 79.38 | J56: =SUM(E52:E55)+SUM(G52:G55) -> 2
B57: 外侧装饰面长 | C57: 265.53 | D57: 外侧装饰面积 | E57: =ROUND(C56*(C57/1000),2) -> 0.25 | F57: 喷涂单价 | G57: =G$23 -> 10 | H57: 喷涂总价 | I57: =E57*G57 -> 2.5
B58: 内侧装饰面长 | C58: 173.62 | D58: 内侧装饰面积 | E58: =ROUND(C56*(C58/1000),2) -> 0.17 | F58: 喷涂单价 | G58: =G$24 -> 10 | H58: 喷涂总价 | I58: =E58*G58 -> 1.7
B59: 型材名称 | C59: 代号 | D59: 竖/横 | G59: 竖/横数量 | H59: 线重 | I59: 重量
B60: 加强中梃 | C60: SDF2808 | D60: =E15 -> 1520 | G60: 1 | H60: 1.934 | I60: =ROUND(D60*G60*H60/1000,3) -> 2.94
H61: 1.934 | I61: =ROUND(D61*G61*H61/1000,3) -> 0
C62: SDF2809 | H62: 2.313 | I62: =ROUND(D62*G62*H62/1000,3) -> 0
H63: 2.313 | I63: =ROUND(D63*G63*H63/1000,3) -> 0
B64: 型材总长度 | C64: =SUMPRODUCT(D60:F63*G60:G63)/1000 -> 1.52 | D64: 型材总重量 | E64: =SUM(I60:I63)*1.1 -> 3.234 | F64: 型材单价 | G64: =(C$218+C$219)/1000 -> 46.0815 | H64: 型材总价 | I64: =ROUND(E64*G64,2) -> 149.03 | J64: =SUM(G60:G63) -> 1
B65: 外侧装饰面长 | C65: 337.92 | D65: 外侧装饰面积 | E65: =ROUND(C64*(C65/1000),2) -> 0.51 | F65: 喷涂单价 | G65: =G$23 -> 10 | H65: 喷涂总价 | I65: =E65*G65 -> 5.1
B66: 内侧装饰面长 | C66: 175.93 | D66: 内侧装饰面积 | E66: =ROUND(C64*(C66/1000),2) -> 0.27 | F66: 喷涂单价 | G66: =G$24 -> 10 | H66: 喷涂总价 | I66: =E66*G66 -> 2.7
B67: 型材名称 | C67: 代号 | D67: 横 | E67: 竖 | F67: 周长 | G67: 数量 | H67: 线重 | I67: 重量 | J67: 宽 | K67: 高 | L67: 宽缩尺 | M67: 高缩尺 | N67: 代号
B68: 固定压线 | C68: 普（SDL2280） | D68: =J68-IF(L68=1,72,IF(L68=2,54,IF(L68=3,26,IF(L68=11,102.8,IF(L68=12,88.8,IF(L68=13,74.8,0)))))) -> 948 | E68: =K68-IF(M68=1,72,IF(M68=2,24,IF(M68=3,26,IF(M68=11,102.8,IF(M68=12,88.8,IF(M68=13,74.8,0)))))) -> 478 | F68: =2*(D68+E68)/1000 -> 2.852 | G68: 1 | H68: 0.224 | I68: =ROUND(F68*G68*H68,3)*1.5 -> 0.9585 | J68: =D14 -> 1020 | K68: =E14 -> 550 | L68: 1 | M68: 1 | N68: 1.框-框
D69: =J69-IF(L69=1,72,IF(L69=2,54,IF(L69=3,26,IF(L69=11,102.8,IF(L69=12,88.8,IF(L69=13,74.8,0)))))) -> 456 | E69: =K69-IF(M69=1,72,IF(M69=2,24,IF(M69=3,26,IF(M69=11,102.8,IF(M69=12,88.8,IF(M69=13,74.8,0)))))) -> 396 | F69: =2*(D69+E69)/1000 -> 1.704 | G69: 2 | H69: =H68 -> 0.224 | I69: =ROUND(F69*G69*H69,3) -> 0.763 | J69: =D15/2 -> 510 | K69: =E15-K35 -> 420 | L69: 2 | M69: 2 | N69: 2.框-中梃
D70: =J70-IF(L70=1,72,IF(L70=2,54,IF(L70=3,26,IF(L70=11,102.8,IF(L70=12,88.8,IF(L70=13,74.8,0)))))) -> 0 | E70: =K70-IF(M70=1,72,IF(M70=2,24,IF(M70=3,26,IF(M70=11,102.8,IF(M70=12,88.8,IF(M70=13,74.8,0)))))) -> 0 | F70: =2*(D70+E70)/1000 -> 0 | H70: =H69 -> 0.224 | I70: =ROUND(F70*G70*H70,3) -> 0 | N70: 3.中梃-中梃
D71: =J71-IF(L71=1,72,IF(L71=2,54,IF(L71=3,26,IF(L71=11,102.8,IF(L71=12,88.8,IF(L71=13,74.8,0)))))) -> 0 | E71: =K71-IF(M71=1,72,IF(M71=2,24,IF(M71=3,26,IF(M71=11,102.8,IF(M71=12,88.8,IF(M71=13,74.8,0)))))) -> 0 | F71: =2*(D71+E71)/1000 -> 0 | H71: =H70 -> 0.224 | I71: =ROUND(F71*G71*H71,3) -> 0 | N71: 11.转.框-框
D72: =J72-IF(L72=1,72,IF(L72=2,54,IF(L72=3,26,IF(L72=11,102.8,IF(L72=12,88.8,IF(L72=13,74.8,0)))))) -> 0 | E72: =K72-IF(M72=1,72,IF(M72=2,24,IF(M72=3,26,IF(M72=11,102.8,IF(M72=12,88.8,IF(M72=13,74.8,0)))))) -> 0 | F72: =2*(D72+E72)/1000 -> 0 | H72: =H71 -> 0.224 | I72: =ROUND(F72*G72*H72,3) -> 0 | N72: 12.转.框-中梃
D73: =J73-IF(L73=1,72,IF(L73=2,54,IF(L73=3,26,IF(L73=11,102.8,IF(L73=12,88.8,IF(L73=13,74.8,0)))))) -> 0 | E73: =K73-IF(M73=1,72,IF(M73=2,24,IF(M73=3,26,IF(M73=11,102.8,IF(M73=12,88.8,IF(M73=13,74.8,0)))))) -> 0 | F73: =2*(D73+E73)/1000 -> 0 | H73: =H70 -> 0.224 | I73: =ROUND(F73*G73*H73,3) -> 0 | N73: 13.转.中梃-中梃
D74: =J74-IF(L74=1,72,IF(L74=2,54,IF(L74=3,26,IF(L74=11,102.8,IF(L74=12,88.8,IF(L74=13,74.8,0)))))) -> 0 | E74: =K74-IF(M74=1,72,IF(M74=2,24,IF(M74=3,26,IF(M74=11,102.8,IF(M74=12,88.8,IF(M74=13,74.8,0)))))) -> 0 | F74: =2*(D74+E74)/1000 -> 0 | H74: =H73 -> 0.224 | I74: =ROUND(F74*G74*H74,3) -> 0
C75: 钢（SDL2280） | D75: =J75-IF(L75=1,72,IF(L75=2,54,IF(L75=3,26,IF(L75=11,102.8,IF(L75=12,88.8,IF(L75=13,74.8,0)))))) -> 0 | E75: =K75-IF(M75=1,72,IF(M75=2,24,IF(M75=3,26,IF(M75=11,102.8,IF(M75=12,88.8,IF(M75=13,74.8,0)))))) -> 0 | F75: =2*(D75+E75)/1000 -> 0 | H75: =H74 -> 0.224 | I75: =ROUND(F75*G75*H75,3) -> 0 | N75: g钢化固定
D76: =J76-IF(L76=1,72,IF(L76=2,54,IF(L76=3,26,IF(L76=11,102.8,IF(L76=12,88.8,IF(L76=13,74.8,0)))))) -> 0 | E76: =K76-IF(M76=1,72,IF(M76=2,24,IF(M76=3,26,IF(M76=11,102.8,IF(M76=12,88.8,IF(M76=13,74.8,0)))))) -> 0 | F76: =2*(D76+E76)/1000 -> 0 | H76: =H72 -> 0.224 | I76: =ROUND(F76*G76*H76,3) -> 0 | N76: g钢化固定
D77: =J77-IF(L77=1,72,IF(L77=2,54,IF(L77=3,26,IF(L77=11,102.8,IF(L77=12,88.8,IF(L77=13,74.8,0)))))) -> 0 | E77: =K77-IF(M77=1,72,IF(M77=2,24,IF(M77=3,26,IF(M77=11,102.8,IF(M77=12,88.8,IF(M77=13,74.8,0)))))) -> 0 | F77: =2*(D77+E77)/1000 -> 0 | H77: =H76 -> 0.224 | I77: =ROUND(F77*G77*H77,3) -> 0 | N77: g钢化固定
D78: =J78-IF(L78=1,72,IF(L78=2,54,IF(L78=3,26,IF(L78=11,102.8,IF(L78=12,88.8,IF(L78=13,74.8,0)))))) -> 0 | E78: =K78-IF(M78=1,72,IF(M78=2,24,IF(M78=3,26,IF(M78=11,102.8,IF(M78=12,88.8,IF(M78=13,74.8,0)))))) -> 0 | F78: =2*(D78+E78)/1000 -> 0 | H78: =H77 -> 0.224 | I78: =ROUND(F78*G78*H78,3) -> 0 | N78: g钢化固定
D79: =J79-IF(L79=1,72,IF(L79=2,54,IF(L79=3,26,IF(L79=11,102.8,IF(L79=12,88.8,IF(L79=13,74.8,0)))))) -> 0 | E79: =K79-IF(M79=1,72,IF(M79=2,24,IF(M79=3,26,IF(M79=11,102.8,IF(M79=12,88.8,IF(M79=13,74.8,0)))))) -> 0 | F79: =2*(D79+E79)/1000 -> 0 | H79: =H78 -> 0.224 | I79: =ROUND(F79*G79*H79,3) -> 0 | N79: g钢化固定
D80: =J80-IF(L80=1,72,IF(L80=2,54,IF(L80=3,26,IF(L80=11,102.8,IF(L80=12,88.8,IF(L80=13,74.8,0)))))) -> 0 | E80: =K80-IF(M80=1,72,IF(M80=2,24,IF(M80=3,26,IF(M80=11,102.8,IF(M80=12,88.8,IF(M80=13,74.8,0)))))) -> 0 | F80: =2*(D80+E80)/1000 -> 0 | H80: =H79 -> 0.224 | I80: =ROUND(F80*G80*H80,3) -> 0 | N80: g钢化固定
D81: =J81-IF(L81=1,72,IF(L81=2,54,IF(L81=3,26,IF(L81=11,102.8,IF(L81=12,88.8,IF(L81=13,74.8,0)))))) -> 0 | E81: =K81-IF(M81=1,72,IF(M81=2,24,IF(M81=3,26,IF(M81=11,102.8,IF(M81=12,88.8,IF(M81=13,74.8,0)))))) -> 0 | F81: =2*(D81+E81)/1000 -> 0 | H81: =H80 -> 0.224 | I81: =ROUND(F81*G81*H81,3) -> 0 | N81: 超大钢化固定6mm
C82: 夹胶钢（SDL2280） | D82: =J82-IF(L82=1,72,IF(L82=2,54,IF(L82=3,26,IF(L82=11,102.8,IF(L82=12,88.8,IF(L82=13,74.8,0)))))) -> 0 | E82: =K82-IF(M82=1,72,IF(M82=2,24,IF(M82=3,26,IF(M82=11,102.8,IF(M82=12,88.8,IF(M82=13,74.8,0)))))) -> 0 | F82: =2*(D82+E82)/1000 -> 0 | H82: =H81 -> 0.224 | I82: =ROUND(F82*G82*H82,3) -> 0
D83: =J83-IF(L83=1,72,IF(L83=2,54,IF(L83=3,26,IF(L83=11,102.8,IF(L83=12,88.8,IF(L83=13,74.8,0)))))) -> 0 | E83: =K83-IF(M83=1,72,IF(M83=2,24,IF(M83=3,26,IF(M83=11,102.8,IF(M83=12,88.8,IF(M83=13,74.8,0)))))) -> 0 | F83: =2*(D83+E83)/1000 -> 0 | H83: =H82 -> 0.224 | I83: =ROUND(F83*G83*H83,3) -> 0
D84: =J84-IF(L84=1,72,IF(L84=2,54,IF(L84=3,26,IF(L84=11,102.8,IF(L84=12,88.8,IF(L84=13,74.8,0)))))) -> 0 | E84: =K84-IF(M84=1,72,IF(M84=2,24,IF(M84=3,26,IF(M84=11,102.8,IF(M84=12,88.8,IF(M84=13,74.8,0)))))) -> 0 | F84: =2*(D84+E84)/1000 -> 0 | H84: =H83 -> 0.224 | I84: =ROUND(F84*G84*H84,3) -> 0
D85: =J85-IF(L85=1,72,IF(L85=2,54,IF(L85=3,26,IF(L85=11,102.8,IF(L85=12,88.8,IF(L85=13,74.8,0)))))) -> 0 | E85: =K85-IF(M85=1,72,IF(M85=2,24,IF(M85=3,26,IF(M85=11,102.8,IF(M85=12,88.8,IF(M85=13,74.8,0)))))) -> 0 | F85: =2*(D85+E85)/1000 -> 0 | H85: =H84 -> 0.224 | I85: =ROUND(F85*G85*H85,3) -> 0
D86: =J86-IF(L86=1,72,IF(L86=2,54,IF(L86=3,26,IF(L86=11,102.8,IF(L86=12,88.8,IF(L86=13,74.8,0)))))) -> 0 | E86: =K86-IF(M86=1,72,IF(M86=2,24,IF(M86=3,26,IF(M86=11,102.8,IF(M86=12,88.8,IF(M86=13,74.8,0)))))) -> 0 | F86: =2*(D86+E86)/1000 -> 0 | H86: =H85 -> 0.224 | I86: =ROUND(F86*G86*H86,3) -> 0
D87: =J87-IF(L87=1,72,IF(L87=2,54,IF(L87=3,26,IF(L87=11,102.8,IF(L87=12,88.8,IF(L87=13,74.8,0)))))) -> 0 | E87: =K87-IF(M87=1,72,IF(M87=2,24,IF(M87=3,26,IF(M87=11,102.8,IF(M87=12,88.8,IF(M87=13,74.8,0)))))) -> 0 | F87: =2*(D87+E87)/1000 -> 0 | H87: =H86 -> 0.224 | I87: =ROUND(F87*G87*H87,3) -> 0
B88: 型材总长度 | C88: =SUMPRODUCT(F68:F87*G68:G87) -> 6.26 | D88: 型材总重量 | E88: =SUM(I68:I87)*1.1 -> 1.89365 | F88: 型材单价 | G88: =(C$218+C$222)/1000 -> 39.7815 | H88: 型材总价 | I88: =ROUND(E88*G88,2) -> 75.33
B89: 外侧装饰面长 | C89: 181.72 | D89: 外侧装饰面积 | E89: =ROUND(C88*(C89/1000),2) -> 1.14 | F89: 喷涂单价 | G89: =G$23 -> 10 | H89: 喷涂总价 | I89: =E89*G89 -> 11.4
B90: 内侧装饰面长 | D90: 内侧装饰面积 | E90: =ROUND(C88*(C90/1000),2) -> 0 | F90: 喷涂单价 | G90: =G$24 -> 10 | H90: 喷涂总价 | I90: =E90*G90 -> 0
B91: 型材名称 | C91: 代号 | D91: 横 | E91: 竖 | F91: 周长 | G91: 数量 | H91: 线重 | I91: 重量
B92: 内开窗扇压线 | C92: SDL2281 | D92: =D26-90 -> -90 | E92: =E26-90 -> -90 | F92: =2*(D92+E92)/1000 -> -0.36 | G92: =G26 -> 0 | H92: 0.271 | I92: =ROUND(F92*G92*H92,3) -> 0
D93: =D27-90 -> -90 | E93: =E27-90 -> -90 | F93: =2*(D93+E93)/1000 -> -0.36 | G93: =G27 -> 0 | H93: =H92 -> 0.271 | I93: =ROUND(F93*G93*H93,3) -> 0
D94: =D28-90 -> -90 | E94: =E28-90 -> -90 | F94: =2*(D94+E94)/1000 -> -0.36 | G94: =G28 -> 0 | H94: =H93 -> 0.271 | I94: =ROUND(F94*G94*H94,3) -> 0
D95: =D29-90 -> -90 | E95: =E29-90 -> -90 | F95: =2*(D95+E95)/1000 -> -0.36 | G95: =G29 -> 0 | H95: =H94 -> 0.271 | I95: =ROUND(F95*G95*H95,3) -> 0
D96: =D30-90 -> -90 | E96: =E30-90 -> -90 | F96: =2*(D96+E96)/1000 -> -0.36 | G96: =G30 -> 0 | H96: =H95 -> 0.271 | I96: =ROUND(F96*G96*H96,3) -> 0
B97: 型材总长度 | C97: =SUMPRODUCT(F92:F96*G92:G96) -> 0 | D97: 型材总重量 | E97: =SUM(I92:I96)*1.1 -> 0 | F97: 型材单价 | G97: =(C$218+C$222)/1000 -> 39.7815 | H97: 型材总价 | I97: =ROUND(E97*G97,2) -> 0
B98: 外侧装饰面长 | C98: 186.72 | D98: 外侧装饰面积 | E98: =ROUND(C97*(C98/1000),2) -> 0 | F98: 喷涂单价 | G98: =G$23 -> 10 | H98: 喷涂总价 | I98: =E98*G98 -> 0
B99: 内侧装饰面长 | C99: 0 | D99: 内侧装饰面积 | E99: =ROUND(C97*(C99/1000),2) -> 0 | F99: 喷涂单价 | G99: =G$24 -> 10 | H99: 喷涂总价 | I99: =E99*G99 -> 0
B100: 型材名称 | C100: 代号 | D100: 横 | E100: 竖 | F100: 周长 | G100: 数量 | H100: 线重 | I100: 重量
B101: 外开窗扇压线 | C101: =C92 -> SDL2281 | D101: =D35-122 -> 288 | E101: =E35-122 -> 878 | F101: =2*(D101+E101)/1000 -> 2.332 | G101: =G35 -> 2 | H101: =H96 -> 0.271 | I101: =ROUND(F101*G101*H101,3) -> 1.264
...

Sheet C1417
B2: MS65F系列（注胶角码） | D2: 24mm | E2: 表面处理 | F2: 静电粉末喷涂 | I2: N0.1 | J2: 副框线重速求表
B3: 代号 | C3: 门窗尺寸 | D3: 宽度 | E3: 高度 | F3: 面积 | G3: 樘数 | H3: 总面积 | J3: 宽度:mm | K3: 高度:mm | L3: 壁厚:mm | M3: 线重
B4: =MID(CELL("filename",Q13),FIND("]",CELL("filename",Q13))+1,30) -> C1417 | C4: 洞口尺寸 | D4: 1400 | E4: 1700 | F4: 1.87 | G4: 1 | H4: =F4*G4 -> 1.87 | J4: 40 | K4: 20 | L4: 1.5 | M4: =ROUND(((J4*K4)-(J4-2*L4)*(K4-2*L4))*7.8/1000,3) -> 1.334
C5: 附框内口尺寸 | D5: =D4-70 -> 1330 | E5: =E4-70 -> 1630 | F5: =D5*E5/10^6 -> 2.1679 | G5: 1 | H5: =F5*G5 -> 2.1679 | J5: 40 | K5: 20 | L5: 2 | M5: =ROUND(((J5*K5)-(J5-2*L5)*(K5-2*L5))*7.8/1000,3) -> 1.747
C6: 主框尺寸 | D6: =D4-80 -> 1320 | E6: =E4-80 -> 1620 | F6: =D6*E6/10^6 -> 2.1384 | G6: 1 | H6: =F6*G6 -> 2.1384 | J6: 40 | K6: 20 | L6: 2 | M6: =ROUND(((J6*K6)-(J6-2*L6)*(K6-2*L6))*7.8/1000,3) -> 1.747
B7: 钢副框（热） | C7: 宽度 | D7: 宽数量 | E7: 高度 | F7: 高数量 | G7: 线重 | H7: 单价 | I7: 总价 | J7: 80 | K7: 40 | L7: 2 | M7: =ROUND(((J7*K7)-(J7-2*L7)*(K7-2*L7))*7.8/1000,3) -> 3.619
B8: 40*20*2.0 | C8: =D4-30 -> 1370 | D8: 2 | E8: =E4-30 -> 1670 | F8: 2 | G8: 1.747 | H8: =材料价格!B3 -> 7.5 | I8: =ROUND((C8*D8+E8*F8)*G8*H8/1000*1.1,2) -> 87.63 | J8: 40 | K8: 20 | L8: 1.4 | M8: =ROUND(((J8*K8)-(J8-2*L8)*(K8-2*L8))*2.71/1000,3) -> 0.434
B9: 40*20*2.0 | G9: 1.747 | H9: =H8 -> 7.5 | I9: =ROUND((C9*D9+E9*F9)*G9*H9/1000*1.1,2) -> 0 | M9: =ROUND(((J9*K9)-(J9-2*L9)*(K9-2*L9))*7.8/1000,3) -> 0
B10: 80*40*2 | G10: 3.619 | H10: =H9 -> 7.5 | I10: =ROUND((C10*D10+E10*F10)*G10*H10/1000*1.1,2) -> 0 | M10: =ROUND(((J10*K10)-(J10-2*L10)*(K10-2*L10))*7.8/1000,3) -> 0
B11: 50*50*2.0 | G11: 2.995 | H11: =H10 -> 7.5 | I11: =ROUND((C11*D11+E11*F11)*G11*H11/1000*1.1,2) -> 0 | M11: =ROUND(((J11*K11)-(J11-2*L11)*(K11-2*L11))*7.8/1000,3) -> 0
B12: 副框平米用量 | C12: =((I9+I10+I8+I11)/H8)/F4 -> 6.2481283 | D12: （Kg/m2) | E12: =(I9+I10+I8+I11)/F4 -> 46.860963 | F12: （元/m2) | H12: =ROUND(SUM(I8:I11)/H8,2) -> 11.68 | I12: =SUM(I8:I11) -> 87.63
B13: 型材名称 | C13: 代号 | D13: 横 | E13: 竖 | F13: 周长 | G13: 数量 | H13: 线重 | I13: 重量
B14: 平开窗框 | C14: SDF2894 | D14: =D6 -> 1320 | E14: =E6 -> 1620 | F14: =ROUND((D14+E14)*2/1000,4) -> 5.88 | G14: 1 | H14: 1.47 | I14: =ROUND(F14*G14*H14,3)*3 -> 25.932
F15: =ROUND((D15+E15)*2/1000,4) -> 0 | H15: =H14 -> 1.47 | I15: =ROUND(F15*G15*H15,3) -> 0
F16: =ROUND((D16+E16)*2/1000,4) -> 0 | H16: =H15 -> 1.47 | I16: =ROUND(F16*G16*H16,3) -> 0
F17: =ROUND((D17+E17)*2/1000,4) -> 0 | H17: =H16 -> 1.47 | I17: =ROUND(F17*G17*H17,3) -> 0
F18: =ROUND((D18+E18)*2/1000,4) -> 0 | H18: =H17 -> 1.47 | I18: =ROUND(F18*G18*H18,3) -> 0
F19: =ROUND((D19+E19)*2/1000,4) -> 0 | H19: =H18 -> 1.47 | I19: =ROUND(F19*G19*H19,3) -> 0
F20: =ROUND((D20+E20)*2/1000,4) -> 0 | H20: =H19 -> 1.47 | I20: =ROUND(F20*G20*H20,3) -> 0
F21: =ROUND((D21+E21)*2/1000,4) -> 0 | H21: =H20 -> 1.47 | I21: =ROUND(F21*G21*H21,3) -> 0
B22: 型材总长度 | C22: =SUMPRODUCT(F14:F21*G14:G21) -> 5.88 | D22: 型材总重量 | E22: =SUM(I14:I21)*1.1 -> 28.5252 | F22: 型材单价 | G22: =(C$218+C$219)/1000 -> 46.0815 | H22: 型材总价 | I22: =ROUND(E22*G22,2) -> 1314.48 | J22: =SUM(G14:G21) -> 1
B23: 外侧装饰面长 | C23: 207.36 | D23: 外侧装饰面积 | E23: =ROUND(C22*(C23/1000),2) -> 1.22 | F23: 喷涂单价 | G23: 10 | H23: 喷涂总价 | I23: =E23*G23 -> 12.2
B24: 内侧装饰面长 | C24: 169.96 | D24: 内侧装饰面积 | E24: =ROUND(C22*(C24/1000),2) -> 1 | F24: 喷涂单价 | G24: 10 | H24: 喷涂总价 | I24: =E24*G24 -> 10
B25: 型材名称 | C25: 代号 | D25: 横 | E25: 竖 | F25: 周长 | G25: 数量 | H25: 线重 | I25: 重量 | J25: 宽 | K25: 高 | L25: 宽缩尺 | M25: 高缩尺 | N25: 代号
B26: 内平开窗扇 | C26: SDF2885 | D26: =J26-IF(L26=1,44,IF(L26=2,30,IF(L26=3,16,0))) -> 0 | E26: =K26-IF(M26=1,44,IF(M26=2,30,IF(M26=3,16,0))) -> 0 | F26: =ROUND((D26+E26)*2/1000,4) -> 0 | H26: 1.62 | I26: =IF(AND(D26>0,E26>0,F26>0),F26*G26*H26,0) -> 0 | N26: 1.框-框 | O26: 普通扇
D27: =J27-IF(L27=1,44,IF(L27=2,30,IF(L27=3,16,0))) -> 0 | E27: =K27-IF(M27=1,44,IF(M27=2,30,IF(M27=3,16,0))) -> 0 | F27: =ROUND((D27+E27)*2/1000,4) -> 0 | H27: =H26 -> 1.62 | I27: =IF(AND(D27>0,E27>0,F27>0),F27*G27*H27,0) -> 0 | N27: 2.框-中梃 | O27: 钢化扇
D28: =J28-IF(L28=1,44,IF(L28=2,30,IF(L28=3,16,0))) -> 0 | E28: =K28-IF(M28=1,44,IF(M28=2,30,IF(M28=3,16,0))) -> 0 | F28: =ROUND((D28+E28)*2/1000,4) -> 0 | H28: =H27 -> 1.62 | I28: =IF(AND(D28>0,E28>0,F28>0),F28*G28*H28,0) -> 0 | N28: 3.中梃-中梃 | O28: 钢化扇
D29: =J29-IF(L29=1,44,IF(L29=2,30,IF(L29=3,16,0))) -> 0 | E29: =K29-IF(M29=1,44,IF(M29=2,30,IF(M29=3,16,0))) -> 0 | F29: =ROUND((D29+E29)*2/1000,4) -> 0 | H29: =H28 -> 1.62 | I29: =IF(AND(D29>0,E29>0,F29>0),F29*G29*H29,0) -> 0
D30: =J30-IF(L30=1,44,IF(L30=2,30,IF(L30=3,16,0))) -> 0 | E30: =K30-IF(M30=1,44,IF(M30=2,30,IF(M30=3,16,0))) -> 0 | F30: =ROUND((D30+E30)*2/1000,4) -> 0 | H30: =H29 -> 1.62 | I30: =IF(AND(D30>0,E30>0,F30>0),F30*G30*H30,0) -> 0
B31: 型材总长度 | C31: =SUMPRODUCT(F26:F30*G26:G30) -> 0 | D31: 型材总重量 | E31: =SUM(I26:I30)*1.1 -> 0 | F31: 型材单价 | G31: =(C$218+C$221)/1000 -> 46.0815 | H31: 型材总价 | I31: =ROUND(E31*G31,2) -> 0 | J31: =SUM(G26:G30) -> 0
B32: 外侧装饰面长 | C32: 183.32 | D32: 外侧装饰面积 | E32: =ROUND(C31*(C32/1000),2) -> 0 | F32: 喷涂单价 | G32: =G$23 -> 10 | H32: 喷涂总价 | I32: =E32*G32 -> 0
B33: 内侧装饰面长 | C33: 257.82 | D33: 内侧装饰面积 | E33: =ROUND(C31*(C33/1000),2) -> 0 | F33: 喷涂单价 | G33: =G$24 -> 10 | H33: 喷涂总价 | I33: =E33*G33 -> 0
B34: 型材名称 | C34: 代号 | D34: 横 | E34: 竖 | F34: 周长 | G34: 数量 | H34: 线重 | I34: 重量 | J34: 宽 | K34: 高 | L34: （宽）缩尺 | M34: （高）缩尺 | N34: 代号
B35: 外平开窗扇 | C35: SDF2806 | D35: =J35-IF(L35=1,44,IF(L35=2,30,IF(L35=3,16,IF(L35=11,118,IF(L35=12,100,IF(L35=13,76.8,0)))))) -> 0 | E35: =K35-IF(M35=1,44,IF(M35=2,30,IF(M35=3,16,IF(M35=11,118,IF(M35=12,100,IF(M35=13,76.8,0)))))) -> 0 | F35: =ROUND((D35+E35)*2/1000,4) -> 0 | H35: 1.814 | I35: =ROUND(F35*G35*H35,3) -> 0 | N35: 1.框-框
D36: =J36-IF(L36=1,44,IF(L36=2,30,IF(L36=3,16,IF(L36=11,118,IF(L36=12,100,IF(L36=13,76.8,0)))))) -> 0 | E36: =K36-IF(M36=1,44,IF(M36=2,30,IF(M36=3,16,IF(M36=11,118,IF(M36=12,100,IF(M36=13,76.8,0)))))) -> 0 | F36: =ROUND((D36+E36)*2/1000,4) -> 0 | H36: =H35 -> 1.814 | I36: =ROUND(F36*G36*H36,3) -> 0 | N36: 2.框-中梃
D37: =J37-IF(L37=1,44,IF(L37=2,30,IF(L37=3,16,IF(L37=11,118,IF(L37=12,100,IF(L37=13,76.8,0)))))) -> 0 | E37: =K37-IF(M37=1,44,IF(M37=2,30,IF(M37=3,16,IF(M37=11,118,IF(M37=12,100,IF(M37=13,76.8,0)))))) -> 0 | F37: =ROUND((D37+E37)*2/1000,4) -> 0 | H37: =H36 -> 1.814 | I37: =ROUND(F37*G37*H37,3) -> 0 | N37: 3.中梃-中梃
B38: 型材总长度 | C38: =SUMPRODUCT(F35:F37*G35:G37) -> 0 | D38: 型材总重量 | E38: =SUM(I35:I37)*1.1 -> 0 | F38: 型材单价 | G38: =(C$218+C$219)/1000 -> 46.0815 | H38: 型材总价 | I38: =ROUND(E38*G38,2) -> 0 | J38: =SUM(G35:G37) -> 0 | N38: 11.转.框-框
B39: 外侧装饰面长 | C39: 320.14 | D39: 外侧装饰面积 | E39: =ROUND(C38*(C39/1000),2) -> 0 | F39: 喷涂单价 | G39: =G$23 -> 10 | H39: 喷涂总价 | I39: =E39*G39 -> 0 | N39: 12.转.框-中梃
B40: 内侧装饰面长 | C40: 156.99 | D40: 内侧装饰面积 | E40: =ROUND(C38*(C40/1000),2) -> 0 | F40: 喷涂单价 | G40: =G$24 -> 10 | H40: 喷涂总价 | I40: =E40*G40 -> 0 | N40: 13.转.中梃-中梃
B41: 型材名称 | C41: 代号 | D41: 横 | E41: 竖 | F41: 周长 | G41: 数量 | H41: 线重 | I41: 重量 | J41: 宽 | K41: 高 | L41: （宽）缩尺 | M41: （高）缩尺 | N41: 代号
B42: 转换料 | C42: SDF3162 (扇转换） | D42: =J42-IF(L42=1,46,IF(L42=2,34.5,IF(L42=3,23))) -> 0 | E42: =K42-IF(M42=1,46,IF(M42=2,34.5,IF(M42=3,23))) -> 0 | F42: =ROUND((D42+E42)*2/1000,4) -> 0 | H42: 1.26 | I42: =ROUND(F42*G42*H42,3) -> 0 | N42: 1.框-框
D43: =J43-IF(L43=1,46,IF(L43=2,34.5,IF(L43=3,23))) -> 0 | E43: =K43-IF(M43=1,46,IF(M43=2,34.5,IF(M43=3,23))) -> 0 | F43: =ROUND((D43+E43)*2/1000,4) -> 0 | H43: =H42 -> 1.26 | I43: =ROUND(F43*G43*H43,3) -> 0 | N43: 2.框-中梃
D44: =J44-IF(L44=1,46,IF(L44=2,34.5,IF(L44=3,23))) -> 0 | E44: =K44-IF(M44=1,46,IF(M44=2,34.5,IF(M44=3,23))) -> 0 | F44: =ROUND((D44+E44)*2/1000,4) -> 0 | H44: =H43 -> 1.26 | I44: =ROUND(F44*G44*H44,3) -> 0 | N44: 3.中梃-中梃
C45: SDF3162 (固定转换） | D45: =J45-IF(L45=1,46,IF(L45=2,34.5,IF(L45=3,23))) -> 0 | E45: =K45-IF(M45=1,46,IF(M45=2,34.5,IF(M45=3,23))) -> 0 | F45: =ROUND((D45+E45)*2/1000,4) -> 0 | H45: =H44 -> 1.26 | I45: =ROUND(F45*G45*H45,3) -> 0 | N45: 1.框-框
D46: =J46-IF(L46=1,46,IF(L46=2,34.5,IF(L46=3,23))) -> 0 | E46: =K46-IF(M46=1,46,IF(M46=2,34.5,IF(M46=3,23))) -> 0 | F46: =ROUND((D46+E46)*2/1000,4) -> 0 | H46: =H45 -> 1.26 | I46: =ROUND(F46*G46*H46,3) -> 0 | N46: 2.框-中梃
D47: =J47-IF(L47=1,46,IF(L47=2,34.5,IF(L47=3,23))) -> 0 | E47: =K47-IF(M47=1,46,IF(M47=2,34.5,IF(M47=3,23))) -> 0 | F47: =ROUND((D47+E47)*2/1000,4) -> 0 | H47: =H46 -> 1.26 | I47: =ROUND(F47*G47*H47,3) -> 0 | N47: 3.中梃-中梃
B48: 型材总长度 | C48: =SUMPRODUCT(F42:F47*G42:G47) -> 0 | D48: 型材总重量 | E48: =SUM(I42:I47)*1.1 -> 0 | F48: 型材单价 | G48: =(C$218+C$219)/1000 -> 46.0815 | H48: 型材总价 | I48: =ROUND(E48*G48,2) -> 0 | J48: =SUM(G42:G47) -> 0
B49: 外侧装饰面长 | C49: 132.48 | D49: 外侧装饰面积 | E49: =ROUND(C48*(C49/1000),2) -> 0 | F49: 喷涂单价 | G49: =G$23 -> 10 | H49: 喷涂总价 | I49: =E49*G49 -> 0
B50: 内侧装饰面长 | C50: 202.06 | D50: 内侧装饰面积 | E50: =ROUND(C48*(C50/1000),2) -> 0 | F50: 喷涂单价 | G50: =G$24 -> 10 | H50: 喷涂总价 | I50: =E50*G50 -> 0
B51: 型材名称 | C51: 代号 | D51: 横 | E51: 横数量 | F51: 竖 | G51: 竖数量 | H51: 线重 | I51: 重量 | J51: 宽 | K51: 高 | L51: （宽）缩尺 | M51: （高）缩尺 | N51: 代号
B52: 窗中梃 | C52: SDF3160 | D52: =J52-IF(L52=1,46,IF(L52=2,32,IF(L52=3,18,0))) -> 0 | F52: =K52-IF(M52=1,46,IF(M52=2,32,IF(M52=3,118,0))) -> 1574 | G52: 1 | H52: 1.638 | I52: =ROUND((D52*E52+F52*G52)/1000*H52,3) -> 2.578 | K52: =E14 -> 1620 | M52: 1 | N52: 1.框-框
D53: =J53-IF(L53=1,46,IF(L53=2,32,IF(L53=3,18,0))) -> 0 | F53: =K53-IF(M53=1,46,IF(M53=2,32,IF(M53=3,118,0))) -> 0 | H53: =H52 -> 1.638 | I53: =ROUND((D53*E53+F53*G53)/1000*H53,3) -> 0 | N53: 2.框-中梃
D54: =J54-IF(L54=1,46,IF(L54=2,32,IF(L54=3,18,0))) -> 0 | F54: =K54-IF(M54=1,46,IF(M54=2,32,IF(M54=3,118,0))) -> 0 | H54: =H53 -> 1.638 | I54: =ROUND((D54*E54+F54*G54)/1000*H54,3) -> 0 | N54: 3.中梃-中梃
D55: =J55-IF(L55=1,46,IF(L55=2,32,IF(L55=3,18,0))) -> 0 | F55: =K55-IF(M55=1,46,IF(M55=2,32,IF(M55=3,118,0))) -> 0 | H55: =H54 -> 1.638 | I55: =ROUND((D55*E55+F55*G55)/1000*H55,3) -> 0
B56: 型材总长度 | C56: =SUMPRODUCT(D52:D55*E52:E55+F52:F55*G52:G55)/1000 -> 1.574 | D56: 型材总重量 | E56: =SUM(I52:I55)*1.1 -> 2.8358 | F56: 型材单价 | G56: =(C$218+C$219)/1000 -> 46.0815 | H56: 型材总价 | I56: =ROUND(E56*G56,2) -> 130.68 | J56: =SUM(E52:E55)+SUM(G52:G55) -> 1
B57: 外侧装饰面长 | C57: 265.53 | D57: 外侧装饰面积 | E57: =ROUND(C56*(C57/1000),2) -> 0.42 | F57: 喷涂单价 | G57: =G$23 -> 10 | H57: 喷涂总价 | I57: =E57*G57 -> 4.2
B58: 内侧装饰面长 | C58: 173.62 | D58: 内侧装饰面积 | E58: =ROUND(C56*(C58/1000),2) -> 0.27 | F58: 喷涂单价 | G58: =G$24 -> 10 | H58: 喷涂总价 | I58: =E58*G58 -> 2.7
B59: 型材名称 | C59: 代号 | D59: 竖/横 | G59: 竖/横数量 | H59: 线重 | I59: 重量
B60: 加强中梃 | C60: SDF2808 | H60: 1.934 | I60: =ROUND(D60*G60*H60/1000,3) -> 0
H61: 1.934 | I61: =ROUND(D61*G61*H61/1000,3) -> 0
C62: SDF2809 | H62: 2.313 | I62: =ROUND(D62*G62*H62/1000,3) -> 0
H63: 2.313 | I63: =ROUND(D63*G63*H63/1000,3) -> 0
B64: 型材总长度 | C64: =SUMPRODUCT(D60:F63*G60:G63)/1000 -> 0 | D64: 型材总重量 | E64: =SUM(I60:I63)*1.1 -> 0 | F64: 型材单价 | G64: =(C$218+C$219)/1000 -> 46.0815 | H64: 型材总价 | I64: =ROUND(E64*G64,2) -> 0 | J64: =SUM(G60:G63) -> 0
B65: 外侧装饰面长 | C65: 337.92 | D65: 外侧装饰面积 | E65: =ROUND(C64*(C65/1000),2) -> 0 | F65: 喷涂单价 | G65: =G$23 -> 10 | H65: 喷涂总价 | I65: =E65*G65 -> 0
B66: 内侧装饰面长 | C66: 175.93 | D66: 内侧装饰面积 | E66: =ROUND(C64*(C66/1000),2) -> 0 | F66: 喷涂单价 | G66: =G$24 -> 10 | H66: 喷涂总价 | I66: =E66*G66 -> 0
B67: 型材名称 | C67: 代号 | D67: 横 | E67: 竖 | F67: 周长 | G67: 数量 | H67: 线重 | I67: 重量 | J67: 宽 | K67: 高 | L67: 宽缩尺 | M67: 高缩尺 | N67: 代号
B68: 固定压线 | C68: 普（SDL2280） | D68: =J68-IF(L68=1,72,IF(L68=2,54,IF(L68=3,26,IF(L68=11,102.8,IF(L68=12,88.8,IF(L68=13,74.8,0)))))) -> 606 | E68: =K68-IF(M68=1,72,IF(M68=2,24,IF(M68=3,26,IF(M68=11,102.8,IF(M68=12,88.8,IF(M68=13,74.8,0)))))) -> 1548 | F68: =2*(D68+E68)/1000 -> 4.308 | G68: 2 | H68: 0.224 | I68: =ROUND(F68*G68*H68,3)*2 -> 3.86 | J68: =D14/2 -> 660 | K68: =E14 -> 1620 | L68: 2 | M68: 1 | N68: 1.框-框
D69: =J69-IF(L69=1,72,IF(L69=2,54,IF(L69=3,26,IF(L69=11,102.8,IF(L69=12,88.8,IF(L69=13,74.8,0)))))) -> 0 | E69: =K69-IF(M69=1,72,IF(M69=2,24,IF(M69=3,26,IF(M69=11,102.8,IF(M69=12,88.8,IF(M69=13,74.8,0)))))) -> 0 | F69: =2*(D69+E69)/1000 -> 0 | H69: =H68 -> 0.224 | I69: =ROUND(F69*G69*H69,3) -> 0 | N69: 2.框-中梃
D70: =J70-IF(L70=1,72,IF(L70=2,54,IF(L70=3,26,IF(L70=11,102.8,IF(L70=12,88.8,IF(L70=13,74.8,0)))))) -> 0 | E70: =K70-IF(M70=1,72,IF(M70=2,24,IF(M70=3,26,IF(M70=11,102.8,IF(M70=12,88.8,IF(M70=13,74.8,0)))))) -> 0 | F70: =2*(D70+E70)/1000 -> 0 | H70: =H69 -> 0.224 | I70: =ROUND(F70*G70*H70,3) -> 0 | N70: 3.中梃-中梃
D71: =J71-IF(L71=1,72,IF(L71=2,54,IF(L71=3,26,IF(L71=11,102.8,IF(L71=12,88.8,IF(L71=13,74.8,0)))))) -> 0 | E71: =K71-IF(M71=1,72,IF(M71=2,24,IF(M71=3,26,IF(M71=11,102.8,IF(M71=12,88.8,IF(M71=13,74.8,0)))))) -> 0 | F71: =2*(D71+E71)/1000 -> 0 | H71: =H70 -> 0.224 | I71: =ROUND(F71*G71*H71,3) -> 0 | N71: 11.转.框-框
D72: =J72-IF(L72=1,72,IF(L72=2,54,IF(L72=3,26,IF(L72=11,102.8,IF(L72=12,88.8,IF(L72=13,74.8,0)))))) -> 0 | E72: =K72-IF(M72=1,72,IF(M72=2,24,IF(M72=3,26,IF(M72=11,102.8,IF(M72=12,88.8,IF(M72=13,74.8,0)))))) -> 0 | F72: =2*(D72+E72)/1000 -> 0 | H72: =H71 -> 0.224 | I72: =ROUND(F72*G72*H72,3) -> 0 | N72: 12.转.框-中梃
D73: =J73-IF(L73=1,72,IF(L73=2,54,IF(L73=3,26,IF(L73=11,102.8,IF(L73=12,88.8,IF(L73=13,74.8,0)))))) -> 0 | E73: =K73-IF(M73=1,72,IF(M73=2,24,IF(M73=3,26,IF(M73=11,102.8,IF(M73=12,88.8,IF(M73=13,74.8,0)))))) -> 0 | F73: =2*(D73+E73)/1000 -> 0 | H73: =H70 -> 0.224 | I73: =ROUND(F73*G73*H73,3) -> 0 | N73: 13.转.中梃-中梃
D74: =J74-IF(L74=1,72,IF(L74=2,54,IF(L74=3,26,IF(L74=11,102.8,IF(L74=12,88.8,IF(L74=13,74.8,0)))))) -> 0 | E74: =K74-IF(M74=1,72,IF(M74=2,24,IF(M74=3,26,IF(M74=11,102.8,IF(M74=12,88.8,IF(M74=13,74.8,0)))))) -> 0 | F74: =2*(D74+E74)/1000 -> 0 | H74: =H73 -> 0.224 | I74: =ROUND(F74*G74*H74,3) -> 0
C75: 钢（SDL2280） | D75: =J75-IF(L75=1,72,IF(L75=2,54,IF(L75=3,26,IF(L75=11,102.8,IF(L75=12,88.8,IF(L75=13,74.8,0)))))) -> 0 | E75: =K75-IF(M75=1,72,IF(M75=2,24,IF(M75=3,26,IF(M75=11,102.8,IF(M75=12,88.8,IF(M75=13,74.8,0)))))) -> 0 | F75: =2*(D75+E75)/1000 -> 0 | H75: =H74 -> 0.224 | I75: =ROUND(F75*G75*H75,3) -> 0 | N75: g钢化固定
D76: =J76-IF(L76=1,72,IF(L76=2,54,IF(L76=3,26,IF(L76=11,102.8,IF(L76=12,88.8,IF(L76=13,74.8,0)))))) -> 0 | E76: =K76-IF(M76=1,72,IF(M76=2,24,IF(M76=3,26,IF(M76=11,102.8,IF(M76=12,88.8,IF(M76=13,74.8,0)))))) -> 0 | F76: =2*(D76+E76)/1000 -> 0 | H76: =H72 -> 0.224 | I76: =ROUND(F76*G76*H76,3) -> 0 | N76: g钢化固定
D77: =J77-IF(L77=1,72,IF(L77=2,54,IF(L77=3,26,IF(L77=11,102.8,IF(L77=12,88.8,IF(L77=13,74.8,0)))))) -> 0 | E77: =K77-IF(M77=1,72,IF(M77=2,24,IF(M77=3,26,IF(M77=11,102.8,IF(M77=12,88.8,IF(M77=13,74.8,0)))))) -> 0 | F77: =2*(D77+E77)/1000 -> 0 | H77: =H76 -> 0.224 | I77: =ROUND(F77*G77*H77,3) -> 0 | N77: g钢化固定
D78: =J78-IF(L78=1,72,IF(L78=2,54,IF(L78=3,26,IF(L78=11,102.8,IF(L78=12,88.8,IF(L78=13,74.8,0)))))) -> 0 | E78: =K78-IF(M78=1,72,IF(M78=2,24,IF(M78=3,26,IF(M78=11,102.8,IF(M78=12,88.8,IF(M78=13,74.8,0)))))) -> 0 | F78: =2*(D78+E78)/1000 -> 0 | H78: =H77 -> 0.224 | I78: =ROUND(F78*G78*H78,3) -> 0 | N78: g钢化固定
D79: =J79-IF(L79=1,72,IF(L79=2,54,IF(L79=3,26,IF(L79=11,102.8,IF(L79=12,88.8,IF(L79=13,74.8,0)))))) -> 0 | E79: =K79-IF(M79=1,72,IF(M79=2,24,IF(M79=3,26,IF(M79=11,102.8,IF(M79=12,88.8,IF(M79=13,74.8,0)))))) -> 0 | F79: =2*(D79+E79)/1000 -> 0 | H79: =H78 -> 0.224 | I79: =ROUND(F79*G79*H79,3) -> 0 | N79: g钢化固定
D80: =J80-IF(L80=1,72,IF(L80=2,54,IF(L80=3,26,IF(L80=11,102.8,IF(L80=12,88.8,IF(L80=13,74.8,0)))))) -> 0 | E80: =K80-IF(M80=1,72,IF(M80=2,24,IF(M80=3,26,IF(M80=11,102.8,IF(M80=12,88.8,IF(M80=13,74.8,0)))))) -> 0 | F80: =2*(D80+E80)/1000 -> 0 | H80: =H79 -> 0.224 | I80: =ROUND(F80*G80*H80,3) -> 0 | N80: g钢化固定
D81: =J81-IF(L81=1,72,IF(L81=2,54,IF(L81=3,26,IF(L81=11,102.8,IF(L81=12,88.8,IF(L81=13,74.8,0)))))) -> 0 | E81: =K81-IF(M81=1,72,IF(M81=2,24,IF(M81=3,26,IF(M81=11,102.8,IF(M81=12,88.8,IF(M81=13,74.8,0)))))) -> 0 | F81: =2*(D81+E81)/1000 -> 0 | H81: =H80 -> 0.224 | I81: =ROUND(F81*G81*H81,3) -> 0 | N81: 超大钢化固定6mm
C82: 夹胶钢（SDL2280） | D82: =J82-IF(L82=1,72,IF(L82=2,54,IF(L82=3,26,IF(L82=11,102.8,IF(L82=12,88.8,IF(L82=13,74.8,0)))))) -> 0 | E82: =K82-IF(M82=1,72,IF(M82=2,24,IF(M82=3,26,IF(M82=11,102.8,IF(M82=12,88.8,IF(M82=13,74.8,0)))))) -> 0 | F82: =2*(D82+E82)/1000 -> 0 | H82: =H81 -> 0.224 | I82: =ROUND(F82*G82*H82,3) -> 0
D83: =J83-IF(L83=1,72,IF(L83=2,54,IF(L83=3,26,IF(L83=11,102.8,IF(L83=12,88.8,IF(L83=13,74.8,0)))))) -> 0 | E83: =K83-IF(M83=1,72,IF(M83=2,24,IF(M83=3,26,IF(M83=11,102.8,IF(M83=12,88.8,IF(M83=13,74.8,0)))))) -> 0 | F83: =2*(D83+E83)/1000 -> 0 | H83: =H82 -> 0.224 | I83: =ROUND(F83*G83*H83,3) -> 0
D84: =J84-IF(L84=1,72,IF(L84=2,54,IF(L84=3,26,IF(L84=11,102.8,IF(L84=12,88.8,IF(L84=13,74.8,0)))))) -> 0 | E84: =K84-IF(M84=1,72,IF(M84=2,24,IF(M84=3,26,IF(M84=11,102.8,IF(M84=12,88.8,IF(M84=13,74.8,0)))))) -> 0 | F84: =2*(D84+E84)/1000 -> 0 | H84: =H83 -> 0.224 | I84: =ROUND(F84*G84*H84,3) -> 0
D85: =J85-IF(L85=1,72,IF(L85=2,54,IF(L85=3,26,IF(L85=11,102.8,IF(L85=12,88.8,IF(L85=13,74.8,0)))))) -> 0 | E85: =K85-IF(M85=1,72,IF(M85=2,24,IF(M85=3,26,IF(M85=11,102.8,IF(M85=12,88.8,IF(M85=13,74.8,0)))))) -> 0 | F85: =2*(D85+E85)/1000 -> 0 | H85: =H84 -> 0.224 | I85: =ROUND(F85*G85*H85,3) -> 0
D86: =J86-IF(L86=1,72,IF(L86=2,54,IF(L86=3,26,IF(L86=11,102.8,IF(L86=12,88.8,IF(L86=13,74.8,0)))))) -> 0 | E86: =K86-IF(M86=1,72,IF(M86=2,24,IF(M86=3,26,IF(M86=11,102.8,IF(M86=12,88.8,IF(M86=13,74.8,0)))))) -> 0 | F86: =2*(D86+E86)/1000 -> 0 | H86: =H85 -> 0.224 | I86: =ROUND(F86*G86*H86,3) -> 0
D87: =J87-IF(L87=1,72,IF(L87=2,54,IF(L87=3,26,IF(L87=11,102.8,IF(L87=12,88.8,IF(L87=13,74.8,0)))))) -> 0 | E87: =K87-IF(M87=1,72,IF(M87=2,24,IF(M87=3,26,IF(M87=11,102.8,IF(M87=12,88.8,IF(M87=13,74.8,0)))))) -> 0 | F87: =2*(D87+E87)/1000 -> 0 | H87: =H86 -> 0.224 | I87: =ROUND(F87*G87*H87,3) -> 0
B88: 型材总长度 | C88: =SUMPRODUCT(F68:F87*G68:G87) -> 8.616 | D88: 型材总重量 | E88: =SUM(I68:I87)*1.1 -> 4.246 | F88: 型材单价 | G88: =(C$218+C$222)/1000 -> 39.7815 | H88: 型材总价 | I88: =ROUND(E88*G88,2) -> 168.91
B89: 外侧装饰面长 | C89: 181.72 | D89: 外侧装饰面积 | E89: =ROUND(C88*(C89/1000),2) -> 1.57 | F89: 喷涂单价 | G89: =G$23 -> 10 | H89: 喷涂总价 | I89: =E89*G89 -> 15.7
B90: 内侧装饰面长 | D90: 内侧装饰面积 | E90: =ROUND(C88*(C90/1000),2) -> 0 | F90: 喷涂单价 | G90: =G$24 -> 10 | H90: 喷涂总价 | I90: =E90*G90 -> 0
B91: 型材名称 | C91: 代号 | D91: 横 | E91: 竖 | F91: 周长 | G91: 数量 | H91: 线重 | I91: 重量
B92: 内开窗扇压线 | C92: SDL2281 | D92: =D26-90 -> -90 | E92: =E26-90 -> -90 | F92: =2*(D92+E92)/1000 -> -0.36 | G92: =G26 -> 0 | H92: 0.271 | I92: =ROUND(F92*G92*H92,3) -> 0
D93: =D27-90 -> -90 | E93: =E27-90 -> -90 | F93: =2*(D93+E93)/1000 -> -0.36 | G93: =G27 -> 0 | H93: =H92 -> 0.271 | I93: =ROUND(F93*G93*H93,3) -> 0
D94: =D28-90 -> -90 | E94: =E28-90 -> -90 | F94: =2*(D94+E94)/1000 -> -0.36 | G94: =G28 -> 0 | H94: =H93 -> 0.271 | I94: =ROUND(F94*G94*H94,3) -> 0
D95: =D29-90 -> -90 | E95: =E29-90 -> -90 | F95: =2*(D95+E95)/1000 -> -0.36 | G95: =G29 -> 0 | H95: =H94 -> 0.271 | I95: =ROUND(F95*G95*H95,3) -> 0
D96: =D30-90 -> -90 | E96: =E30-90 -> -90 | F96: =2*(D96+E96)/1000 -> -0.36 | G96: =G30 -> 0 | H96: =H95 -> 0.271 | I96: =ROUND(F96*G96*H96,3) -> 0
B97: 型材总长度 | C97: =SUMPRODUCT(F92:F96*G92:G96) -> 0 | D97: 型材总重量 | E97: =SUM(I92:I96)*1.1 -> 0 | F97: 型材单价 | G97: =(C$218+C$222)/1000 -> 39.7815 | H97: 型材总价 | I97: =ROUND(E97*G97,2) -> 0
B98: 外侧装饰面长 | C98: 186.72 | D98: 外侧装饰面积 | E98: =ROUND(C97*(C98/1000),2) -> 0 | F98: 喷涂单价 | G98: =G$23 -> 10 | H98: 喷涂总价 | I98: =E98*G98 -> 0
B99: 内侧装饰面长 | C99: 0 | D99: 内侧装饰面积 | E99: =ROUND(C97*(C99/1000),2) -> 0 | F99: 喷涂单价 | G99: =G$24 -> 10 | H99: 喷涂总价 | I99: =E99*G99 -> 0
B100: 型材名称 | C100: 代号 | D100: 横 | E100: 竖 | F100: 周长 | G100: 数量 | H100: 线重 | I100: 重量
B101: 外开窗扇压线 | C101: =C92 -> SDL2281 | D101: =D35-122 -> -122 | E101: =E35-122 -> -122 | F101: =2*(D101+E101)/1000 -> -0.488 | G101: =G35 -> 0 | H101: =H96 -> 0.271 | I101: =ROUND(F101*G101*H101,3) -> 0
...

Sheet C2430
B2: MS65F系列（注胶角码） | D2: 24mm | E2: 表面处理 | F2: 静电粉末喷涂 | I2: N0.1 | J2: 副框线重速求表
B3: 代号 | C3: 门窗尺寸 | D3: 宽度 | E3: 高度 | F3: 面积 | G3: 樘数 | H3: 总面积 | J3: 宽度:mm | K3: 高度:mm | L3: 壁厚:mm | M3: 线重
B4: =MID(CELL("filename",Q13),FIND("]",CELL("filename",Q13))+1,30) -> C2430 | C4: 洞口尺寸 | D4: 2400 | E4: 3000 | F4: 6.58 | G4: 1 | H4: =F4*G4 -> 6.58 | J4: 40 | K4: 20 | L4: 1.5 | M4: =ROUND(((J4*K4)-(J4-2*L4)*(K4-2*L4))*7.8/1000,3) -> 1.334
C5: 附框内口尺寸 | D5: =D4-70 -> 2330 | E5: =E4-70 -> 2930 | F5: =D5*E5/10^6 -> 6.8269 | G5: 1 | H5: =F5*G5 -> 6.8269 | J5: 40 | K5: 20 | L5: 2 | M5: =ROUND(((J5*K5)-(J5-2*L5)*(K5-2*L5))*7.8/1000,3) -> 1.747
C6: 主框尺寸 | D6: =D4-80 -> 2320 | E6: =E4-80 -> 2920 | F6: =D6*E6/10^6 -> 6.7744 | G6: 1 | H6: =F6*G6 -> 6.7744 | J6: 40 | K6: 20 | L6: 2 | M6: =ROUND(((J6*K6)-(J6-2*L6)*(K6-2*L6))*7.8/1000,3) -> 1.747
B7: 钢副框（热） | C7: 宽度 | D7: 宽数量 | E7: 高度 | F7: 高数量 | G7: 线重 | H7: 单价 | I7: 总价 | J7: 80 | K7: 40 | L7: 2 | M7: =ROUND(((J7*K7)-(J7-2*L7)*(K7-2*L7))*7.8/1000,3) -> 3.619
B8: 40*20*2.0 | C8: =D4-30 -> 2370 | D8: 2 | E8: =E4-30 -> 2970 | F8: 2 | G8: 1.747 | H8: =材料价格!B3 -> 7.5 | I8: =ROUND((C8*D8+E8*F8)*G8*H8/1000*1.1,2) -> 153.93 | J8: 40 | K8: 20 | L8: 1.4 | M8: =ROUND(((J8*K8)-(J8-2*L8)*(K8-2*L8))*2.71/1000,3) -> 0.434
B9: 40*20*2.0 | G9: 1.747 | H9: =H8 -> 7.5 | I9: =ROUND((C9*D9+E9*F9)*G9*H9/1000*1.1,2) -> 0 | M9: =ROUND(((J9*K9)-(J9-2*L9)*(K9-2*L9))*7.8/1000,3) -> 0
B10: 80*40*2 | G10: 3.619 | H10: =H9 -> 7.5 | I10: =ROUND((C10*D10+E10*F10)*G10*H10/1000*1.1,2) -> 0 | M10: =ROUND(((J10*K10)-(J10-2*L10)*(K10-2*L10))*7.8/1000,3) -> 0
B11: 50*50*2.0 | G11: 2.995 | H11: =H10 -> 7.5 | I11: =ROUND((C11*D11+E11*F11)*G11*H11/1000*1.1,2) -> 0 | M11: =ROUND(((J11*K11)-(J11-2*L11)*(K11-2*L11))*7.8/1000,3) -> 0
B12: 副框平米用量 | C12: =((I9+I10+I8+I11)/H8)/F4 -> 3.1191489 | D12: （Kg/m2) | E12: =(I9+I10+I8+I11)/F4 -> 23.393617 | F12: （元/m2) | H12: =ROUND(SUM(I8:I11)/H8,2) -> 20.52 | I12: =SUM(I8:I11) -> 153.93
B13: 型材名称 | C13: 代号 | D13: 横 | E13: 竖 | F13: 周长 | G13: 数量 | H13: 线重 | I13: 重量
B14: 平开窗框 | C14: SDF2894 | D14: =D6 -> 2320 | E14: 1200 | F14: =ROUND((D14+E14)*2/1000,4) -> 7.04 | G14: 1 | H14: 1.47 | I14: =ROUND(F14*G14*H14,3)*2 -> 20.698
D15: =D14 -> 2320 | E15: =E6-E14 -> 1720 | F15: =ROUND((D15+E15)*2/1000,4) -> 8.08 | G15: 1 | H15: =H14 -> 1.47 | I15: =ROUND(F15*G15*H15,3) -> 11.878
F16: =ROUND((D16+E16)*2/1000,4) -> 0 | H16: =H15 -> 1.47 | I16: =ROUND(F16*G16*H16,3) -> 0
F17: =ROUND((D17+E17)*2/1000,4) -> 0 | H17: =H16 -> 1.47 | I17: =ROUND(F17*G17*H17,3) -> 0
F18: =ROUND((D18+E18)*2/1000,4) -> 0 | H18: =H17 -> 1.47 | I18: =ROUND(F18*G18*H18,3) -> 0
F19: =ROUND((D19+E19)*2/1000,4) -> 0 | H19: =H18 -> 1.47 | I19: =ROUND(F19*G19*H19,3) -> 0
F20: =ROUND((D20+E20)*2/1000,4) -> 0 | H20: =H19 -> 1.47 | I20: =ROUND(F20*G20*H20,3) -> 0
F21: =ROUND((D21+E21)*2/1000,4) -> 0 | H21: =H20 -> 1.47 | I21: =ROUND(F21*G21*H21,3) -> 0
B22: 型材总长度 | C22: =SUMPRODUCT(F14:F21*G14:G21) -> 15.12 | D22: 型材总重量 | E22: =SUM(I14:I21)*1.1 -> 35.8336 | F22: 型材单价 | G22: =(C$218+C$219)/1000 -> 46.0815 | H22: 型材总价 | I22: =ROUND(E22*G22,2) -> 1651.27 | J22: =SUM(G14:G21) -> 2
B23: 外侧装饰面长 | C23: 207.36 | D23: 外侧装饰面积 | E23: =ROUND(C22*(C23/1000),2) -> 3.14 | F23: 喷涂单价 | G23: 10 | H23: 喷涂总价 | I23: =E23*G23 -> 31.4
B24: 内侧装饰面长 | C24: 169.96 | D24: 内侧装饰面积 | E24: =ROUND(C22*(C24/1000),2) -> 2.57 | F24: 喷涂单价 | G24: 10 | H24: 喷涂总价 | I24: =E24*G24 -> 25.7
B25: 型材名称 | C25: 代号 | D25: 横 | E25: 竖 | F25: 周长 | G25: 数量 | H25: 线重 | I25: 重量 | J25: 宽 | K25: 高 | L25: 宽缩尺 | M25: 高缩尺 | N25: 代号
B26: 内平开窗扇 | C26: SDF2885 | D26: =J26-IF(L26=1,44,IF(L26=2,30,IF(L26=3,16,0))) -> 0 | E26: =K26-IF(M26=1,44,IF(M26=2,30,IF(M26=3,16,0))) -> 0 | F26: =ROUND((D26+E26)*2/1000,4) -> 0 | H26: 1.62 | I26: =IF(AND(D26>0,E26>0,F26>0),F26*G26*H26,0) -> 0 | N26: 1.框-框 | O26: 普通扇
D27: =J27-IF(L27=1,44,IF(L27=2,30,IF(L27=3,16,0))) -> 0 | E27: =K27-IF(M27=1,44,IF(M27=2,30,IF(M27=3,16,0))) -> 0 | F27: =ROUND((D27+E27)*2/1000,4) -> 0 | H27: =H26 -> 1.62 | I27: =IF(AND(D27>0,E27>0,F27>0),F27*G27*H27,0) -> 0 | N27: 2.框-中梃 | O27: 钢化扇
D28: =J28-IF(L28=1,44,IF(L28=2,30,IF(L28=3,16,0))) -> 0 | E28: =K28-IF(M28=1,44,IF(M28=2,30,IF(M28=3,16,0))) -> 0 | F28: =ROUND((D28+E28)*2/1000,4) -> 0 | H28: =H27 -> 1.62 | I28: =IF(AND(D28>0,E28>0,F28>0),F28*G28*H28,0) -> 0 | N28: 3.中梃-中梃 | O28: 钢化扇
D29: =J29-IF(L29=1,44,IF(L29=2,30,IF(L29=3,16,0))) -> 0 | E29: =K29-IF(M29=1,44,IF(M29=2,30,IF(M29=3,16,0))) -> 0 | F29: =ROUND((D29+E29)*2/1000,4) -> 0 | H29: =H28 -> 1.62 | I29: =IF(AND(D29>0,E29>0,F29>0),F29*G29*H29,0) -> 0
D30: =J30-IF(L30=1,44,IF(L30=2,30,IF(L30=3,16,0))) -> 0 | E30: =K30-IF(M30=1,44,IF(M30=2,30,IF(M30=3,16,0))) -> 0 | F30: =ROUND((D30+E30)*2/1000,4) -> 0 | H30: =H29 -> 1.62 | I30: =IF(AND(D30>0,E30>0,F30>0),F30*G30*H30,0) -> 0
B31: 型材总长度 | C31: =SUMPRODUCT(F26:F30*G26:G30) -> 0 | D31: 型材总重量 | E31: =SUM(I26:I30)*1.1 -> 0 | F31: 型材单价 | G31: =(C$218+C$221)/1000 -> 46.0815 | H31: 型材总价 | I31: =ROUND(E31*G31,2) -> 0 | J31: =SUM(G26:G30) -> 0
B32: 外侧装饰面长 | C32: 183.32 | D32: 外侧装饰面积 | E32: =ROUND(C31*(C32/1000),2) -> 0 | F32: 喷涂单价 | G32: =G$23 -> 10 | H32: 喷涂总价 | I32: =E32*G32 -> 0
B33: 内侧装饰面长 | C33: 257.82 | D33: 内侧装饰面积 | E33: =ROUND(C31*(C33/1000),2) -> 0 | F33: 喷涂单价 | G33: =G$24 -> 10 | H33: 喷涂总价 | I33: =E33*G33 -> 0
B34: 型材名称 | C34: 代号 | D34: 横 | E34: 竖 | F34: 周长 | G34: 数量 | H34: 线重 | I34: 重量 | J34: 宽 | K34: 高 | L34: （宽）缩尺 | M34: （高）缩尺 | N34: 代号
B35: 外平开窗扇 | C35: SDF2806 | D35: =J35-IF(L35=1,44,IF(L35=2,30,IF(L35=3,16,IF(L35=11,118,IF(L35=12,100,IF(L35=13,76.8,0)))))) -> 480 | E35: =K35-IF(M35=1,44,IF(M35=2,30,IF(M35=3,16,IF(M35=11,118,IF(M35=12,100,IF(M35=13,76.8,0)))))) -> 800 | F35: =ROUND((D35+E35)*2/1000,4) -> 2.56 | G35: 4 | H35: 1.814 | I35: =ROUND(F35*G35*H35,3) -> 18.575 | J35: =D15/4 -> 580 | K35: 900 | L35: 12 | M35: 12 | N35: 1.框-框
D36: =J36-IF(L36=1,44,IF(L36=2,30,IF(L36=3,16,IF(L36=11,118,IF(L36=12,100,IF(L36=13,76.8,0)))))) -> 0 | E36: =K36-IF(M36=1,44,IF(M36=2,30,IF(M36=3,16,IF(M36=11,118,IF(M36=12,100,IF(M36=13,76.8,0)))))) -> 0 | F36: =ROUND((D36+E36)*2/1000,4) -> 0 | H36: =H35 -> 1.814 | I36: =ROUND(F36*G36*H36,3) -> 0 | N36: 2.框-中梃
D37: =J37-IF(L37=1,44,IF(L37=2,30,IF(L37=3,16,IF(L37=11,118,IF(L37=12,100,IF(L37=13,76.8,0)))))) -> 0 | E37: =K37-IF(M37=1,44,IF(M37=2,30,IF(M37=3,16,IF(M37=11,118,IF(M37=12,100,IF(M37=13,76.8,0)))))) -> 0 | F37: =ROUND((D37+E37)*2/1000,4) -> 0 | H37: =H36 -> 1.814 | I37: =ROUND(F37*G37*H37,3) -> 0 | N37: 3.中梃-中梃
B38: 型材总长度 | C38: =SUMPRODUCT(F35:F37*G35:G37) -> 10.24 | D38: 型材总重量 | E38: =SUM(I35:I37)*1.1 -> 20.4325 | F38: 型材单价 | G38: =(C$218+C$219)/1000 -> 46.0815 | H38: 型材总价 | I38: =ROUND(E38*G38,2) -> 941.56 | J38: =SUM(G35:G37) -> 4 | N38: 11.转.框-框
B39: 外侧装饰面长 | C39: 320.14 | D39: 外侧装饰面积 | E39: =ROUND(C38*(C39/1000),2) -> 3.28 | F39: 喷涂单价 | G39: =G$23 -> 10 | H39: 喷涂总价 | I39: =E39*G39 -> 32.8 | N39: 12.转.框-中梃
B40: 内侧装饰面长 | C40: 156.99 | D40: 内侧装饰面积 | E40: =ROUND(C38*(C40/1000),2) -> 1.61 | F40: 喷涂单价 | G40: =G$24 -> 10 | H40: 喷涂总价 | I40: =E40*G40 -> 16.1 | N40: 13.转.中梃-中梃
B41: 型材名称 | C41: 代号 | D41: 横 | E41: 竖 | F41: 周长 | G41: 数量 | H41: 线重 | I41: 重量 | J41: 宽 | K41: 高 | L41: （宽）缩尺 | M41: （高）缩尺 | N41: 代号
B42: 转换料 | C42: SDF3162 (扇转换） | D42: =J42-IF(L42=1,46,IF(L42=2,34.5,IF(L42=3,23))) -> 545.5 | E42: =K42-IF(M42=1,46,IF(M42=2,34.5,IF(M42=3,23))) -> 865.5 | F42: =ROUND((D42+E42)*2/1000,4) -> 2.822 | G42: =G35 -> 4 | H42: 1.26 | I42: =ROUND(F42*G42*H42,3) -> 14.223 | J42: =J35 -> 580 | K42: =K35 -> 900 | L42: 2 | M42: 2 | N42: 1.框-框
D43: =J43-IF(L43=1,46,IF(L43=2,34.5,IF(L43=3,23))) -> 0 | E43: =K43-IF(M43=1,46,IF(M43=2,34.5,IF(M43=3,23))) -> 0 | F43: =ROUND((D43+E43)*2/1000,4) -> 0 | H43: =H42 -> 1.26 | I43: =ROUND(F43*G43*H43,3) -> 0 | N43: 2.框-中梃
D44: =J44-IF(L44=1,46,IF(L44=2,34.5,IF(L44=3,23))) -> 0 | E44: =K44-IF(M44=1,46,IF(M44=2,34.5,IF(M44=3,23))) -> 0 | F44: =ROUND((D44+E44)*2/1000,4) -> 0 | H44: =H43 -> 1.26 | I44: =ROUND(F44*G44*H44,3) -> 0 | N44: 3.中梃-中梃
C45: SDF3162 (固定转换） | D45: =J45-IF(L45=1,46,IF(L45=2,34.5,IF(L45=3,23))) -> 0 | E45: =K45-IF(M45=1,46,IF(M45=2,34.5,IF(M45=3,23))) -> 0 | F45: =ROUND((D45+E45)*2/1000,4) -> 0 | H45: =H44 -> 1.26 | I45: =ROUND(F45*G45*H45,3) -> 0 | N45: 1.框-框
D46: =J46-IF(L46=1,46,IF(L46=2,34.5,IF(L46=3,23))) -> 0 | E46: =K46-IF(M46=1,46,IF(M46=2,34.5,IF(M46=3,23))) -> 0 | F46: =ROUND((D46+E46)*2/1000,4) -> 0 | H46: =H45 -> 1.26 | I46: =ROUND(F46*G46*H46,3) -> 0 | N46: 2.框-中梃
D47: =J47-IF(L47=1,46,IF(L47=2,34.5,IF(L47=3,23))) -> 0 | E47: =K47-IF(M47=1,46,IF(M47=2,34.5,IF(M47=3,23))) -> 0 | F47: =ROUND((D47+E47)*2/1000,4) -> 0 | H47: =H46 -> 1.26 | I47: =ROUND(F47*G47*H47,3) -> 0 | N47: 3.中梃-中梃
B48: 型材总长度 | C48: =SUMPRODUCT(F42:F47*G42:G47) -> 11.288 | D48: 型材总重量 | E48: =SUM(I42:I47)*1.1 -> 15.6453 | F48: 型材单价 | G48: =(C$218+C$219)/1000 -> 46.0815 | H48: 型材总价 | I48: =ROUND(E48*G48,2) -> 720.96 | J48: =SUM(G42:G47) -> 4
B49: 外侧装饰面长 | C49: 132.48 | D49: 外侧装饰面积 | E49: =ROUND(C48*(C49/1000),2) -> 1.5 | F49: 喷涂单价 | G49: =G$23 -> 10 | H49: 喷涂总价 | I49: =E49*G49 -> 15
B50: 内侧装饰面长 | C50: 202.06 | D50: 内侧装饰面积 | E50: =ROUND(C48*(C50/1000),2) -> 2.28 | F50: 喷涂单价 | G50: =G$24 -> 10 | H50: 喷涂总价 | I50: =E50*G50 -> 22.8
B51: 型材名称 | C51: 代号 | D51: 横 | E51: 横数量 | F51: 竖 | G51: 竖数量 | H51: 线重 | I51: 重量 | J51: 宽 | K51: 高 | L51: （宽）缩尺 | M51: （高）缩尺 | N51: 代号
B52: 窗中梃 | C52: SDF3160 | D52: =J52-IF(L52=1,46,IF(L52=2,32,IF(L52=3,18,0))) -> 548 | E52: 4 | F52: =K52-IF(M52=1,46,IF(M52=2,32,IF(M52=3,118,0))) -> 1674 | G52: 3 | H52: 1.638 | I52: =ROUND((D52*E52+F52*G52)/1000*H52,3) -> 11.817 | J52: =J35 -> 580 | K52: =E15 -> 1720 | L52: 2 | M52: 1 | N52: 1.框-框
D53: =J53-IF(L53=1,46,IF(L53=2,32,IF(L53=3,18,0))) -> 0 | F53: =K53-IF(M53=1,46,IF(M53=2,32,IF(M53=3,118,0))) -> 0 | H53: =H52 -> 1.638 | I53: =ROUND((D53*E53+F53*G53)/1000*H53,3) -> 0 | N53: 2.框-中梃
D54: =J54-IF(L54=1,46,IF(L54=2,32,IF(L54=3,18,0))) -> 0 | F54: =K54-IF(M54=1,46,IF(M54=2,32,IF(M54=3,118,0))) -> 0 | H54: =H53 -> 1.638 | I54: =ROUND((D54*E54+F54*G54)/1000*H54,3) -> 0 | N54: 3.中梃-中梃
D55: =J55-IF(L55=1,46,IF(L55=2,32,IF(L55=3,18,0))) -> 0 | F55: =K55-IF(M55=1,46,IF(M55=2,32,IF(M55=3,118,0))) -> 0 | H55: =H54 -> 1.638 | I55: =ROUND((D55*E55+F55*G55)/1000*H55,3) -> 0
B56: 型材总长度 | C56: =SUMPRODUCT(D52:D55*E52:E55+F52:F55*G52:G55)/1000 -> 7.214 | D56: 型材总重量 | E56: =SUM(I52:I55)*1.1 -> 12.9987 | F56: 型材单价 | G56: =(C$218+C$219)/1000 -> 46.0815 | H56: 型材总价 | I56: =ROUND(E56*G56,2) -> 599 | J56: =SUM(E52:E55)+SUM(G52:G55) -> 7
B57: 外侧装饰面长 | C57: 265.53 | D57: 外侧装饰面积 | E57: =ROUND(C56*(C57/1000),2) -> 1.92 | F57: 喷涂单价 | G57: =G$23 -> 10 | H57: 喷涂总价 | I57: =E57*G57 -> 19.2
B58: 内侧装饰面长 | C58: 173.62 | D58: 内侧装饰面积 | E58: =ROUND(C56*(C58/1000),2) -> 1.25 | F58: 喷涂单价 | G58: =G$24 -> 10 | H58: 喷涂总价 | I58: =E58*G58 -> 12.5
B59: 型材名称 | C59: 代号 | D59: 竖/横 | G59: 竖/横数量 | H59: 线重 | I59: 重量
B60: 加强中梃 | C60: SDF2808 | H60: 1.934 | I60: =ROUND(D60*G60*H60/1000,3) -> 0
H61: 1.934 | I61: =ROUND(D61*G61*H61/1000,3) -> 0
C62: SDF2809 | H62: 2.313 | I62: =ROUND(D62*G62*H62/1000,3) -> 0
H63: 2.313 | I63: =ROUND(D63*G63*H63/1000,3) -> 0
B64: 型材总长度 | C64: =SUMPRODUCT(D60:F63*G60:G63)/1000 -> 0 | D64: 型材总重量 | E64: =SUM(I60:I63)*1.1 -> 0 | F64: 型材单价 | G64: =(C$218+C$219)/1000 -> 46.0815 | H64: 型材总价 | I64: =ROUND(E64*G64,2) -> 0 | J64: =SUM(G60:G63) -> 0
B65: 外侧装饰面长 | C65: 337.92 | D65: 外侧装饰面积 | E65: =ROUND(C64*(C65/1000),2) -> 0 | F65: 喷涂单价 | G65: =G$23 -> 10 | H65: 喷涂总价 | I65: =E65*G65 -> 0
B66: 内侧装饰面长 | C66: 175.93 | D66: 内侧装饰面积 | E66: =ROUND(C64*(C66/1000),2) -> 0 | F66: 喷涂单价 | G66: =G$24 -> 10 | H66: 喷涂总价 | I66: =E66*G66 -> 0
B67: 型材名称 | C67: 代号 | D67: 横 | E67: 竖 | F67: 周长 | G67: 数量 | H67: 线重 | I67: 重量 | J67: 宽 | K67: 高 | L67: 宽缩尺 | M67: 高缩尺 | N67: 代号
B68: 固定压线 | C68: 普（SDL2280） | D68: =J68-IF(L68=1,72,IF(L68=2,54,IF(L68=3,26,IF(L68=11,102.8,IF(L68=12,88.8,IF(L68=13,74.8,0)))))) -> 2248 | E68: =K68-IF(M68=1,72,IF(M68=2,24,IF(M68=3,26,IF(M68=11,102.8,IF(M68=12,88.8,IF(M68=13,74.8,0)))))) -> 1128 | F68: =2*(D68+E68)/1000 -> 6.752 | G68: 1 | H68: 0.224 | I68: =ROUND(F68*G68*H68,3)*2 -> 3.024 | J68: =D14 -> 2320 | K68: =E14 -> 1200 | L68: 1 | M68: 1 | N68: 1.框-框
D69: =J69-IF(L69=1,72,IF(L69=2,54,IF(L69=3,26,IF(L69=11,102.8,IF(L69=12,88.8,IF(L69=13,74.8,0)))))) -> 526 | E69: =K69-IF(M69=1,72,IF(M69=2,24,IF(M69=3,26,IF(M69=11,102.8,IF(M69=12,88.8,IF(M69=13,74.8,0)))))) -> 796 | F69: =2*(D69+E69)/1000 -> 2.644 | G69: 4 | H69: =H68 -> 0.224 | I69: =ROUND(F69*G69*H69,3) -> 2.369 | J69: =J35 -> 580 | K69: =E15-K35 -> 820 | L69: 2 | M69: 2 | N69: 2.框-中梃
D70: =J70-IF(L70=1,72,IF(L70=2,54,IF(L70=3,26,IF(L70=11,102.8,IF(L70=12,88.8,IF(L70=13,74.8,0)))))) -> 0 | E70: =K70-IF(M70=1,72,IF(M70=2,24,IF(M70=3,26,IF(M70=11,102.8,IF(M70=12,88.8,IF(M70=13,74.8,0)))))) -> 0 | F70: =2*(D70+E70)/1000 -> 0 | H70: =H69 -> 0.224 | I70: =ROUND(F70*G70*H70,3) -> 0 | N70: 3.中梃-中梃
D71: =J71-IF(L71=1,72,IF(L71=2,54,IF(L71=3,26,IF(L71=11,102.8,IF(L71=12,88.8,IF(L71=13,74.8,0)))))) -> 0 | E71: =K71-IF(M71=1,72,IF(M71=2,24,IF(M71=3,26,IF(M71=11,102.8,IF(M71=12,88.8,IF(M71=13,74.8,0)))))) -> 0 | F71: =2*(D71+E71)/1000 -> 0 | H71: =H70 -> 0.224 | I71: =ROUND(F71*G71*H71,3) -> 0 | N71: 11.转.框-框
D72: =J72-IF(L72=1,72,IF(L72=2,54,IF(L72=3,26,IF(L72=11,102.8,IF(L72=12,88.8,IF(L72=13,74.8,0)))))) -> 0 | E72: =K72-IF(M72=1,72,IF(M72=2,24,IF(M72=3,26,IF(M72=11,102.8,IF(M72=12,88.8,IF(M72=13,74.8,0)))))) -> 0 | F72: =2*(D72+E72)/1000 -> 0 | H72: =H71 -> 0.224 | I72: =ROUND(F72*G72*H72,3) -> 0 | N72: 12.转.框-中梃
D73: =J73-IF(L73=1,72,IF(L73=2,54,IF(L73=3,26,IF(L73=11,102.8,IF(L73=12,88.8,IF(L73=13,74.8,0)))))) -> 0 | E73: =K73-IF(M73=1,72,IF(M73=2,24,IF(M73=3,26,IF(M73=11,102.8,IF(M73=12,88.8,IF(M73=13,74.8,0)))))) -> 0 | F73: =2*(D73+E73)/1000 -> 0 | H73: =H70 -> 0.224 | I73: =ROUND(F73*G73*H73,3) -> 0 | N73: 13.转.中梃-中梃
D74: =J74-IF(L74=1,72,IF(L74=2,54,IF(L74=3,26,IF(L74=11,102.8,IF(L74=12,88.8,IF(L74=13,74.8,0)))))) -> 0 | E74: =K74-IF(M74=1,72,IF(M74=2,24,IF(M74=3,26,IF(M74=11,102.8,IF(M74=12,88.8,IF(M74=13,74.8,0)))))) -> 0 | F74: =2*(D74+E74)/1000 -> 0 | H74: =H73 -> 0.224 | I74: =ROUND(F74*G74*H74,3) -> 0
C75: 钢（SDL2280） | D75: =J75-IF(L75=1,72,IF(L75=2,54,IF(L75=3,26,IF(L75=11,102.8,IF(L75=12,88.8,IF(L75=13,74.8,0)))))) -> 0 | E75: =K75-IF(M75=1,72,IF(M75=2,24,IF(M75=3,26,IF(M75=11,102.8,IF(M75=12,88.8,IF(M75=13,74.8,0)))))) -> 0 | F75: =2*(D75+E75)/1000 -> 0 | H75: =H74 -> 0.224 | I75: =ROUND(F75*G75*H75,3) -> 0 | N75: g钢化固定
D76: =J76-IF(L76=1,72,IF(L76=2,54,IF(L76=3,26,IF(L76=11,102.8,IF(L76=12,88.8,IF(L76=13,74.8,0)))))) -> 0 | E76: =K76-IF(M76=1,72,IF(M76=2,24,IF(M76=3,26,IF(M76=11,102.8,IF(M76=12,88.8,IF(M76=13,74.8,0)))))) -> 0 | F76: =2*(D76+E76)/1000 -> 0 | H76: =H72 -> 0.224 | I76: =ROUND(F76*G76*H76,3) -> 0 | N76: g钢化固定
D77: =J77-IF(L77=1,72,IF(L77=2,54,IF(L77=3,26,IF(L77=11,102.8,IF(L77=12,88.8,IF(L77=13,74.8,0)))))) -> 0 | E77: =K77-IF(M77=1,72,IF(M77=2,24,IF(M77=3,26,IF(M77=11,102.8,IF(M77=12,88.8,IF(M77=13,74.8,0)))))) -> 0 | F77: =2*(D77+E77)/1000 -> 0 | H77: =H76 -> 0.224 | I77: =ROUND(F77*G77*H77,3) -> 0 | N77: g钢化固定
D78: =J78-IF(L78=1,72,IF(L78=2,54,IF(L78=3,26,IF(L78=11,102.8,IF(L78=12,88.8,IF(L78=13,74.8,0)))))) -> 0 | E78: =K78-IF(M78=1,72,IF(M78=2,24,IF(M78=3,26,IF(M78=11,102.8,IF(M78=12,88.8,IF(M78=13,74.8,0)))))) -> 0 | F78: =2*(D78+E78)/1000 -> 0 | H78: =H77 -> 0.224 | I78: =ROUND(F78*G78*H78,3) -> 0 | N78: g钢化固定
D79: =J79-IF(L79=1,72,IF(L79=2,54,IF(L79=3,26,IF(L79=11,102.8,IF(L79=12,88.8,IF(L79=13,74.8,0)))))) -> 0 | E79: =K79-IF(M79=1,72,IF(M79=2,24,IF(M79=3,26,IF(M79=11,102.8,IF(M79=12,88.8,IF(M79=13,74.8,0)))))) -> 0 | F79: =2*(D79+E79)/1000 -> 0 | H79: =H78 -> 0.224 | I79: =ROUND(F79*G79*H79,3) -> 0 | N79: g钢化固定
D80: =J80-IF(L80=1,72,IF(L80=2,54,IF(L80=3,26,IF(L80=11,102.8,IF(L80=12,88.8,IF(L80=13,74.8,0)))))) -> 0 | E80: =K80-IF(M80=1,72,IF(M80=2,24,IF(M80=3,26,IF(M80=11,102.8,IF(M80=12,88.8,IF(M80=13,74.8,0)))))) -> 0 | F80: =2*(D80+E80)/1000 -> 0 | H80: =H79 -> 0.224 | I80: =ROUND(F80*G80*H80,3) -> 0 | N80: g钢化固定
D81: =J81-IF(L81=1,72,IF(L81=2,54,IF(L81=3,26,IF(L81=11,102.8,IF(L81=12,88.8,IF(L81=13,74.8,0)))))) -> 0 | E81: =K81-IF(M81=1,72,IF(M81=2,24,IF(M81=3,26,IF(M81=11,102.8,IF(M81=12,88.8,IF(M81=13,74.8,0)))))) -> 0 | F81: =2*(D81+E81)/1000 -> 0 | H81: =H80 -> 0.224 | I81: =ROUND(F81*G81*H81,3) -> 0 | N81: 超大钢化固定6mm
C82: 夹胶钢（SDL2280） | D82: =J82-IF(L82=1,72,IF(L82=2,54,IF(L82=3,26,IF(L82=11,102.8,IF(L82=12,88.8,IF(L82=13,74.8,0)))))) -> 0 | E82: =K82-IF(M82=1,72,IF(M82=2,24,IF(M82=3,26,IF(M82=11,102.8,IF(M82=12,88.8,IF(M82=13,74.8,0)))))) -> 0 | F82: =2*(D82+E82)/1000 -> 0 | H82: =H81 -> 0.224 | I82: =ROUND(F82*G82*H82,3) -> 0
D83: =J83-IF(L83=1,72,IF(L83=2,54,IF(L83=3,26,IF(L83=11,102.8,IF(L83=12,88.8,IF(L83=13,74.8,0)))))) -> 0 | E83: =K83-IF(M83=1,72,IF(M83=2,24,IF(M83=3,26,IF(M83=11,102.8,IF(M83=12,88.8,IF(M83=13,74.8,0)))))) -> 0 | F83: =2*(D83+E83)/1000 -> 0 | H83: =H82 -> 0.224 | I83: =ROUND(F83*G83*H83,3) -> 0
D84: =J84-IF(L84=1,72,IF(L84=2,54,IF(L84=3,26,IF(L84=11,102.8,IF(L84=12,88.8,IF(L84=13,74.8,0)))))) -> 0 | E84: =K84-IF(M84=1,72,IF(M84=2,24,IF(M84=3,26,IF(M84=11,102.8,IF(M84=12,88.8,IF(M84=13,74.8,0)))))) -> 0 | F84: =2*(D84+E84)/1000 -> 0 | H84: =H83 -> 0.224 | I84: =ROUND(F84*G84*H84,3) -> 0
D85: =J85-IF(L85=1,72,IF(L85=2,54,IF(L85=3,26,IF(L85=11,102.8,IF(L85=12,88.8,IF(L85=13,74.8,0)))))) -> 0 | E85: =K85-IF(M85=1,72,IF(M85=2,24,IF(M85=3,26,IF(M85=11,102.8,IF(M85=12,88.8,IF(M85=13,74.8,0)))))) -> 0 | F85: =2*(D85+E85)/1000 -> 0 | H85: =H84 -> 0.224 | I85: =ROUND(F85*G85*H85,3) -> 0
D86: =J86-IF(L86=1,72,IF(L86=2,54,IF(L86=3,26,IF(L86=11,102.8,IF(L86=12,88.8,IF(L86=13,74.8,0)))))) -> 0 | E86: =K86-IF(M86=1,72,IF(M86=2,24,IF(M86=3,26,IF(M86=11,102.8,IF(M86=12,88.8,IF(M86=13,74.8,0)))))) -> 0 | F86: =2*(D86+E86)/1000 -> 0 | H86: =H85 -> 0.224 | I86: =ROUND(F86*G86*H86,3) -> 0
D87: =J87-IF(L87=1,72,IF(L87=2,54,IF(L87=3,26,IF(L87=11,102.8,IF(L87=12,88.8,IF(L87=13,74.8,0)))))) -> 0 | E87: =K87-IF(M87=1,72,IF(M87=2,24,IF(M87=3,26,IF(M87=11,102.8,IF(M87=12,88.8,IF(M87=13,74.8,0)))))) -> 0 | F87: =2*(D87+E87)/1000 -> 0 | H87: =H86 -> 0.224 | I87: =ROUND(F87*G87*H87,3) -> 0
B88: 型材总长度 | C88: =SUMPRODUCT(F68:F87*G68:G87) -> 17.328 | D88: 型材总重量 | E88: =SUM(I68:I87)*1.1 -> 5.9323 | F88: 型材单价 | G88: =(C$218+C$222)/1000 -> 39.7815 | H88: 型材总价 | I88: =ROUND(E88*G88,2) -> 236
B89: 外侧装饰面长 | C89: 181.72 | D89: 外侧装饰面积 | E89: =ROUND(C88*(C89/1000),2) -> 3.15 | F89: 喷涂单价 | G89: =G$23 -> 10 | H89: 喷涂总价 | I89: =E89*G89 -> 31.5
B90: 内侧装饰面长 | D90: 内侧装饰面积 | E90: =ROUND(C88*(C90/1000),2) -> 0 | F90: 喷涂单价 | G90: =G$24 -> 10 | H90: 喷涂总价 | I90: =E90*G90 -> 0
B91: 型材名称 | C91: 代号 | D91: 横 | E91: 竖 | F91: 周长 | G91: 数量 | H91: 线重 | I91: 重量
B92: 内开窗扇压线 | C92: SDL2281 | D92: =D26-90 -> -90 | E92: =E26-90 -> -90 | F92: =2*(D92+E92)/1000 -> -0.36 | G92: =G26 -> 0 | H92: 0.271 | I92: =ROUND(F92*G92*H92,3) -> 0
D93: =D27-90 -> -90 | E93: =E27-90 -> -90 | F93: =2*(D93+E93)/1000 -> -0.36 | G93: =G27 -> 0 | H93: =H92 -> 0.271 | I93: =ROUND(F93*G93*H93,3) -> 0
D94: =D28-90 -> -90 | E94: =E28-90 -> -90 | F94: =2*(D94+E94)/1000 -> -0.36 | G94: =G28 -> 0 | H94: =H93 -> 0.271 | I94: =ROUND(F94*G94*H94,3) -> 0
D95: =D29-90 -> -90 | E95: =E29-90 -> -90 | F95: =2*(D95+E95)/1000 -> -0.36 | G95: =G29 -> 0 | H95: =H94 -> 0.271 | I95: =ROUND(F95*G95*H95,3) -> 0
D96: =D30-90 -> -90 | E96: =E30-90 -> -90 | F96: =2*(D96+E96)/1000 -> -0.36 | G96: =G30 -> 0 | H96: =H95 -> 0.271 | I96: =ROUND(F96*G96*H96,3) -> 0
B97: 型材总长度 | C97: =SUMPRODUCT(F92:F96*G92:G96) -> 0 | D97: 型材总重量 | E97: =SUM(I92:I96)*1.1 -> 0 | F97: 型材单价 | G97: =(C$218+C$222)/1000 -> 39.7815 | H97: 型材总价 | I97: =ROUND(E97*G97,2) -> 0
B98: 外侧装饰面长 | C98: 186.72 | D98: 外侧装饰面积 | E98: =ROUND(C97*(C98/1000),2) -> 0 | F98: 喷涂单价 | G98: =G$23 -> 10 | H98: 喷涂总价 | I98: =E98*G98 -> 0
B99: 内侧装饰面长 | C99: 0 | D99: 内侧装饰面积 | E99: =ROUND(C97*(C99/1000),2) -> 0 | F99: 喷涂单价 | G99: =G$24 -> 10 | H99: 喷涂总价 | I99: =E99*G99 -> 0
B100: 型材名称 | C100: 代号 | D100: 横 | E100: 竖 | F100: 周长 | G100: 数量 | H100: 线重 | I100: 重量
B101: 外开窗扇压线 | C101: =C92 -> SDL2281 | D101: =D35-122 -> 358 | E101: =E35-122 -> 678 | F101: =2*(D101+E101)/1000 -> 2.072 | G101: =G35 -> 4 | H101: =H96 -> 0.271 | I101: =ROUND(F101*G101*H101,3) -> 2.246
...

Sheet C2735-G
B2: MS65F系列（注胶角码） | D2: 24mm | E2: 表面处理 | F2: 静电粉末喷涂 | I2: N0.1 | J2: 副框线重速求表
B3: 代号 | C3: 门窗尺寸 | D3: 宽度 | E3: 高度 | F3: 面积 | G3: 樘数 | H3: 总面积 | J3: 宽度:mm | K3: 高度:mm | L3: 壁厚:mm | M3: 线重
B4: =MID(CELL("filename",Q13),FIND("]",CELL("filename",Q13))+1,30) -> C2735-G | C4: 洞口尺寸 | D4: 2700 | E4: 3500 | F4: 8.668 | G4: 1 | H4: =F4*G4 -> 8.668 | J4: 40 | K4: 20 | L4: 1.5 | M4: =ROUND(((J4*K4)-(J4-2*L4)*(K4-2*L4))*7.8/1000,3) -> 1.334
C5: 附框内口尺寸 | D5: =D4-70 -> 2630 | E5: =E4-70 -> 3430 | F5: =D5*E5/10^6 -> 9.0209 | G5: 1 | H5: =F5*G5 -> 9.0209 | J5: 40 | K5: 20 | L5: 2 | M5: =ROUND(((J5*K5)-(J5-2*L5)*(K5-2*L5))*7.8/1000,3) -> 1.747
C6: 主框尺寸 | D6: =D4-80 -> 2620 | E6: =E4-80 -> 3420 | F6: =D6*E6/10^6 -> 8.9604 | G6: 1 | H6: =F6*G6 -> 8.9604 | J6: 40 | K6: 20 | L6: 2 | M6: =ROUND(((J6*K6)-(J6-2*L6)*(K6-2*L6))*7.8/1000,3) -> 1.747
B7: 钢副框（热） | C7: 宽度 | D7: 宽数量 | E7: 高度 | F7: 高数量 | G7: 线重 | H7: 单价 | I7: 总价 | J7: 80 | K7: 40 | L7: 2 | M7: =ROUND(((J7*K7)-(J7-2*L7)*(K7-2*L7))*7.8/1000,3) -> 3.619
B8: 40*20*2.0 | C8: =D4-30 -> 2670 | D8: 2 | E8: =E4-30 -> 3470 | F8: 2 | G8: 1.747 | H8: =材料价格!B3 -> 7.5 | I8: =ROUND((C8*D8+E8*F8)*G8*H8/1000*1.1,2) -> 176.99 | J8: 40 | K8: 20 | L8: 1.4 | M8: =ROUND(((J8*K8)-(J8-2*L8)*(K8-2*L8))*2.71/1000,3) -> 0.434
B9: 40*20*2.0 | G9: 1.747 | H9: =H8 -> 7.5 | I9: =ROUND((C9*D9+E9*F9)*G9*H9/1000*1.1,2) -> 0 | M9: =ROUND(((J9*K9)-(J9-2*L9)*(K9-2*L9))*7.8/1000,3) -> 0
B10: 80*40*2 | G10: 3.619 | H10: =H9 -> 7.5 | I10: =ROUND((C10*D10+E10*F10)*G10*H10/1000*1.1,2) -> 0 | M10: =ROUND(((J10*K10)-(J10-2*L10)*(K10-2*L10))*7.8/1000,3) -> 0
B11: 50*50*2.0 | G11: 2.995 | H11: =H10 -> 7.5 | I11: =ROUND((C11*D11+E11*F11)*G11*H11/1000*1.1,2) -> 0 | M11: =ROUND(((J11*K11)-(J11-2*L11)*(K11-2*L11))*7.8/1000,3) -> 0
B12: 副框平米用量 | C12: =((I9+I10+I8+I11)/H8)/F4 -> 2.7225042 | D12: （Kg/m2) | E12: =(I9+I10+I8+I11)/F4 -> 20.418782 | F12: （元/m2) | H12: =ROUND(SUM(I8:I11)/H8,2) -> 23.6 | I12: =SUM(I8:I11) -> 176.99
B13: 型材名称 | C13: 代号 | D13: 横 | E13: 竖 | F13: 周长 | G13: 数量 | H13: 线重 | I13: 重量
B14: 平开窗框 | C14: SDF2894 | D14: =D6 -> 2620 | E14: 1350 | F14: =ROUND((D14+E14)*2/1000,4) -> 7.94 | G14: 1 | H14: 1.47 | I14: =ROUND(F14*G14*H14,3)*2 -> 23.344
D15: =D14 -> 2620 | E15: =E6-E14 -> 2070 | F15: =ROUND((D15+E15)*2/1000,4) -> 9.38 | G15: 1 | H15: =H14 -> 1.47 | I15: =ROUND(F15*G15*H15,3) -> 13.789
F16: =ROUND((D16+E16)*2/1000,4) -> 0 | H16: =H15 -> 1.47 | I16: =ROUND(F16*G16*H16,3) -> 0
F17: =ROUND((D17+E17)*2/1000,4) -> 0 | H17: =H16 -> 1.47 | I17: =ROUND(F17*G17*H17,3) -> 0
F18: =ROUND((D18+E18)*2/1000,4) -> 0 | H18: =H17 -> 1.47 | I18: =ROUND(F18*G18*H18,3) -> 0
F19: =ROUND((D19+E19)*2/1000,4) -> 0 | H19: =H18 -> 1.47 | I19: =ROUND(F19*G19*H19,3) -> 0
F20: =ROUND((D20+E20)*2/1000,4) -> 0 | H20: =H19 -> 1.47 | I20: =ROUND(F20*G20*H20,3) -> 0
F21: =ROUND((D21+E21)*2/1000,4) -> 0 | H21: =H20 -> 1.47 | I21: =ROUND(F21*G21*H21,3) -> 0
B22: 型材总长度 | C22: =SUMPRODUCT(F14:F21*G14:G21) -> 17.32 | D22: 型材总重量 | E22: =SUM(I14:I21)*1.1 -> 40.8463 | F22: 型材单价 | G22: =(C$218+C$219)/1000 -> 46.0815 | H22: 型材总价 | I22: =ROUND(E22*G22,2) -> 1882.26 | J22: =SUM(G14:G21) -> 2
B23: 外侧装饰面长 | C23: 207.36 | D23: 外侧装饰面积 | E23: =ROUND(C22*(C23/1000),2) -> 3.59 | F23: 喷涂单价 | G23: 10 | H23: 喷涂总价 | I23: =E23*G23 -> 35.9
B24: 内侧装饰面长 | C24: 169.96 | D24: 内侧装饰面积 | E24: =ROUND(C22*(C24/1000),2) -> 2.94 | F24: 喷涂单价 | G24: 10 | H24: 喷涂总价 | I24: =E24*G24 -> 29.4
B25: 型材名称 | C25: 代号 | D25: 横 | E25: 竖 | F25: 周长 | G25: 数量 | H25: 线重 | I25: 重量 | J25: 宽 | K25: 高 | L25: 宽缩尺 | M25: 高缩尺 | N25: 代号
B26: 内平开窗扇 | C26: SDF2885 | D26: =J26-IF(L26=1,44,IF(L26=2,30,IF(L26=3,16,0))) -> 0 | E26: =K26-IF(M26=1,44,IF(M26=2,30,IF(M26=3,16,0))) -> 0 | F26: =ROUND((D26+E26)*2/1000,4) -> 0 | H26: 1.62 | I26: =IF(AND(D26>0,E26>0,F26>0),F26*G26*H26,0) -> 0 | N26: 1.框-框 | O26: 普通扇
D27: =J27-IF(L27=1,44,IF(L27=2,30,IF(L27=3,16,0))) -> 0 | E27: =K27-IF(M27=1,44,IF(M27=2,30,IF(M27=3,16,0))) -> 0 | F27: =ROUND((D27+E27)*2/1000,4) -> 0 | H27: =H26 -> 1.62 | I27: =IF(AND(D27>0,E27>0,F27>0),F27*G27*H27,0) -> 0 | N27: 2.框-中梃 | O27: 钢化扇
D28: =J28-IF(L28=1,44,IF(L28=2,30,IF(L28=3,16,0))) -> 0 | E28: =K28-IF(M28=1,44,IF(M28=2,30,IF(M28=3,16,0))) -> 0 | F28: =ROUND((D28+E28)*2/1000,4) -> 0 | H28: =H27 -> 1.62 | I28: =IF(AND(D28>0,E28>0,F28>0),F28*G28*H28,0) -> 0 | N28: 3.中梃-中梃 | O28: 钢化扇
D29: =J29-IF(L29=1,44,IF(L29=2,30,IF(L29=3,16,0))) -> 0 | E29: =K29-IF(M29=1,44,IF(M29=2,30,IF(M29=3,16,0))) -> 0 | F29: =ROUND((D29+E29)*2/1000,4) -> 0 | H29: =H28 -> 1.62 | I29: =IF(AND(D29>0,E29>0,F29>0),F29*G29*H29,0) -> 0
D30: =J30-IF(L30=1,44,IF(L30=2,30,IF(L30=3,16,0))) -> 0 | E30: =K30-IF(M30=1,44,IF(M30=2,30,IF(M30=3,16,0))) -> 0 | F30: =ROUND((D30+E30)*2/1000,4) -> 0 | H30: =H29 -> 1.62 | I30: =IF(AND(D30>0,E30>0,F30>0),F30*G30*H30,0) -> 0
B31: 型材总长度 | C31: =SUMPRODUCT(F26:F30*G26:G30) -> 0 | D31: 型材总重量 | E31: =SUM(I26:I30)*1.1 -> 0 | F31: 型材单价 | G31: =(C$218+C$221)/1000 -> 46.0815 | H31: 型材总价 | I31: =ROUND(E31*G31,2) -> 0 | J31: =SUM(G26:G30) -> 0
B32: 外侧装饰面长 | C32: 183.32 | D32: 外侧装饰面积 | E32: =ROUND(C31*(C32/1000),2) -> 0 | F32: 喷涂单价 | G32: =G$23 -> 10 | H32: 喷涂总价 | I32: =E32*G32 -> 0
B33: 内侧装饰面长 | C33: 257.82 | D33: 内侧装饰面积 | E33: =ROUND(C31*(C33/1000),2) -> 0 | F33: 喷涂单价 | G33: =G$24 -> 10 | H33: 喷涂总价 | I33: =E33*G33 -> 0
B34: 型材名称 | C34: 代号 | D34: 横 | E34: 竖 | F34: 周长 | G34: 数量 | H34: 线重 | I34: 重量 | J34: 宽 | K34: 高 | L34: （宽）缩尺 | M34: （高）缩尺 | N34: 代号
B35: 外平开窗扇 | C35: SDF2806 | D35: =J35-IF(L35=1,44,IF(L35=2,30,IF(L35=3,16,IF(L35=11,118,IF(L35=12,100,IF(L35=13,76.8,0)))))) -> 600 | E35: =K35-IF(M35=1,44,IF(M35=2,30,IF(M35=3,16,IF(M35=11,118,IF(M35=12,100,IF(M35=13,76.8,0)))))) -> 1300 | F35: =ROUND((D35+E35)*2/1000,4) -> 3.8 | G35: 2 | H35: 1.814 | I35: =ROUND(F35*G35*H35,3) -> 13.786 | J35: 700 | K35: 1400 | L35: 12 | M35: 12 | N35: 1.框-框
D36: =J36-IF(L36=1,44,IF(L36=2,30,IF(L36=3,16,IF(L36=11,118,IF(L36=12,100,IF(L36=13,76.8,0)))))) -> 0 | E36: =K36-IF(M36=1,44,IF(M36=2,30,IF(M36=3,16,IF(M36=11,118,IF(M36=12,100,IF(M36=13,76.8,0)))))) -> 0 | F36: =ROUND((D36+E36)*2/1000,4) -> 0 | H36: =H35 -> 1.814 | I36: =ROUND(F36*G36*H36,3) -> 0 | N36: 2.框-中梃
D37: =J37-IF(L37=1,44,IF(L37=2,30,IF(L37=3,16,IF(L37=11,118,IF(L37=12,100,IF(L37=13,76.8,0)))))) -> 0 | E37: =K37-IF(M37=1,44,IF(M37=2,30,IF(M37=3,16,IF(M37=11,118,IF(M37=12,100,IF(M37=13,76.8,0)))))) -> 0 | F37: =ROUND((D37+E37)*2/1000,4) -> 0 | H37: =H36 -> 1.814 | I37: =ROUND(F37*G37*H37,3) -> 0 | N37: 3.中梃-中梃
B38: 型材总长度 | C38: =SUMPRODUCT(F35:F37*G35:G37) -> 7.6 | D38: 型材总重量 | E38: =SUM(I35:I37)*1.1 -> 15.1646 | F38: 型材单价 | G38: =(C$218+C$219)/1000 -> 46.0815 | H38: 型材总价 | I38: =ROUND(E38*G38,2) -> 698.81 | J38: =SUM(G35:G37) -> 2 | N38: 11.转.框-框
B39: 外侧装饰面长 | C39: 320.14 | D39: 外侧装饰面积 | E39: =ROUND(C38*(C39/1000),2) -> 2.43 | F39: 喷涂单价 | G39: =G$23 -> 10 | H39: 喷涂总价 | I39: =E39*G39 -> 24.3 | N39: 12.转.框-中梃
B40: 内侧装饰面长 | C40: 156.99 | D40: 内侧装饰面积 | E40: =ROUND(C38*(C40/1000),2) -> 1.19 | F40: 喷涂单价 | G40: =G$24 -> 10 | H40: 喷涂总价 | I40: =E40*G40 -> 11.9 | N40: 13.转.中梃-中梃
B41: 型材名称 | C41: 代号 | D41: 横 | E41: 竖 | F41: 周长 | G41: 数量 | H41: 线重 | I41: 重量 | J41: 宽 | K41: 高 | L41: （宽）缩尺 | M41: （高）缩尺 | N41: 代号
B42: 转换料 | C42: SDF3162 (扇转换） | D42: =J42-IF(L42=1,46,IF(L42=2,34.5,IF(L42=3,23))) -> 665.5 | E42: =K42-IF(M42=1,46,IF(M42=2,34.5,IF(M42=3,23))) -> 1365.5 | F42: =ROUND((D42+E42)*2/1000,4) -> 4.062 | G42: =G35 -> 2 | H42: 1.26 | I42: =ROUND(F42*G42*H42,3) -> 10.236 | J42: =J35 -> 700 | K42: =K35 -> 1400 | L42: 2 | M42: 2 | N42: 1.框-框
D43: =J43-IF(L43=1,46,IF(L43=2,34.5,IF(L43=3,23))) -> 0 | E43: =K43-IF(M43=1,46,IF(M43=2,34.5,IF(M43=3,23))) -> 0 | F43: =ROUND((D43+E43)*2/1000,4) -> 0 | H43: =H42 -> 1.26 | I43: =ROUND(F43*G43*H43,3) -> 0 | N43: 2.框-中梃
D44: =J44-IF(L44=1,46,IF(L44=2,34.5,IF(L44=3,23))) -> 0 | E44: =K44-IF(M44=1,46,IF(M44=2,34.5,IF(M44=3,23))) -> 0 | F44: =ROUND((D44+E44)*2/1000,4) -> 0 | H44: =H43 -> 1.26 | I44: =ROUND(F44*G44*H44,3) -> 0 | N44: 3.中梃-中梃
C45: SDF3162 (固定转换） | D45: =J45-IF(L45=1,46,IF(L45=2,34.5,IF(L45=3,23))) -> 0 | E45: =K45-IF(M45=1,46,IF(M45=2,34.5,IF(M45=3,23))) -> 0 | F45: =ROUND((D45+E45)*2/1000,4) -> 0 | H45: =H44 -> 1.26 | I45: =ROUND(F45*G45*H45,3) -> 0 | N45: 1.框-框
D46: =J46-IF(L46=1,46,IF(L46=2,34.5,IF(L46=3,23))) -> 0 | E46: =K46-IF(M46=1,46,IF(M46=2,34.5,IF(M46=3,23))) -> 0 | F46: =ROUND((D46+E46)*2/1000,4) -> 0 | H46: =H45 -> 1.26 | I46: =ROUND(F46*G46*H46,3) -> 0 | N46: 2.框-中梃
D47: =J47-IF(L47=1,46,IF(L47=2,34.5,IF(L47=3,23))) -> 0 | E47: =K47-IF(M47=1,46,IF(M47=2,34.5,IF(M47=3,23))) -> 0 | F47: =ROUND((D47+E47)*2/1000,4) -> 0 | H47: =H46 -> 1.26 | I47: =ROUND(F47*G47*H47,3) -> 0 | N47: 3.中梃-中梃
B48: 型材总长度 | C48: =SUMPRODUCT(F42:F47*G42:G47) -> 8.124 | D48: 型材总重量 | E48: =SUM(I42:I47)*1.1 -> 11.2596 | F48: 型材单价 | G48: =(C$218+C$219)/1000 -> 46.0815 | H48: 型材总价 | I48: =ROUND(E48*G48,2) -> 518.86 | J48: =SUM(G42:G47) -> 2
B49: 外侧装饰面长 | C49: 132.48 | D49: 外侧装饰面积 | E49: =ROUND(C48*(C49/1000),2) -> 1.08 | F49: 喷涂单价 | G49: =G$23 -> 10 | H49: 喷涂总价 | I49: =E49*G49 -> 10.8
B50: 内侧装饰面长 | C50: 202.06 | D50: 内侧装饰面积 | E50: =ROUND(C48*(C50/1000),2) -> 1.64 | F50: 喷涂单价 | G50: =G$24 -> 10 | H50: 喷涂总价 | I50: =E50*G50 -> 16.4
B51: 型材名称 | C51: 代号 | D51: 横 | E51: 横数量 | F51: 竖 | G51: 竖数量 | H51: 线重 | I51: 重量 | J51: 宽 | K51: 高 | L51: （宽）缩尺 | M51: （高）缩尺 | N51: 代号
B52: 窗中梃 | C52: SDF3160 | D52: =J52-IF(L52=1,46,IF(L52=2,32,IF(L52=3,18,0))) -> 668 | E52: 4 | F52: =K52-IF(M52=1,46,IF(M52=2,32,IF(M52=3,118,0))) -> 0 | H52: 1.638 | I52: =ROUND((D52*E52+F52*G52)/1000*H52,3) -> 4.377 | J52: =J35 -> 700 | L52: 2 | N52: 1.框-框
D53: =J53-IF(L53=1,46,IF(L53=2,32,IF(L53=3,18,0))) -> 0 | F53: =K53-IF(M53=1,46,IF(M53=2,32,IF(M53=3,118,0))) -> 0 | H53: =H52 -> 1.638 | I53: =ROUND((D53*E53+F53*G53)/1000*H53,3) -> 0 | N53: 2.框-中梃
D54: =J54-IF(L54=1,46,IF(L54=2,32,IF(L54=3,18,0))) -> 0 | F54: =K54-IF(M54=1,46,IF(M54=2,32,IF(M54=3,118,0))) -> 0 | H54: =H53 -> 1.638 | I54: =ROUND((D54*E54+F54*G54)/1000*H54,3) -> 0 | N54: 3.中梃-中梃
D55: =J55-IF(L55=1,46,IF(L55=2,32,IF(L55=3,18,0))) -> 0 | F55: =K55-IF(M55=1,46,IF(M55=2,32,IF(M55=3,118,0))) -> 0 | H55: =H54 -> 1.638 | I55: =ROUND((D55*E55+F55*G55)/1000*H55,3) -> 0
B56: 型材总长度 | C56: =SUMPRODUCT(D52:D55*E52:E55+F52:F55*G52:G55)/1000 -> 2.672 | D56: 型材总重量 | E56: =SUM(I52:I55)*1.1 -> 4.8147 | F56: 型材单价 | G56: =(C$218+C$219)/1000 -> 46.0815 | H56: 型材总价 | I56: =ROUND(E56*G56,2) -> 221.87 | J56: =SUM(E52:E55)+SUM(G52:G55) -> 4
B57: 外侧装饰面长 | C57: 265.53 | D57: 外侧装饰面积 | E57: =ROUND(C56*(C57/1000),2) -> 0.71 | F57: 喷涂单价 | G57: =G$23 -> 10 | H57: 喷涂总价 | I57: =E57*G57 -> 7.1
B58: 内侧装饰面长 | C58: 173.62 | D58: 内侧装饰面积 | E58: =ROUND(C56*(C58/1000),2) -> 0.46 | F58: 喷涂单价 | G58: =G$24 -> 10 | H58: 喷涂总价 | I58: =E58*G58 -> 4.6
B59: 型材名称 | C59: 代号 | D59: 竖/横 | G59: 竖/横数量 | H59: 线重 | I59: 重量
B60: 加强中梃 | C60: SDF2808 | D60: =E15 -> 2070 | G60: 3 | H60: 1.934 | I60: =ROUND(D60*G60*H60/1000,3) -> 12.01
H61: 1.934 | I61: =ROUND(D61*G61*H61/1000,3) -> 0
C62: SDF2809 | H62: 2.313 | I62: =ROUND(D62*G62*H62/1000,3) -> 0
H63: 2.313 | I63: =ROUND(D63*G63*H63/1000,3) -> 0
B64: 型材总长度 | C64: =SUMPRODUCT(D60:F63*G60:G63)/1000 -> 6.21 | D64: 型材总重量 | E64: =SUM(I60:I63)*1.1 -> 13.211 | F64: 型材单价 | G64: =(C$218+C$219)/1000 -> 46.0815 | H64: 型材总价 | I64: =ROUND(E64*G64,2) -> 608.78 | J64: =SUM(G60:G63) -> 3
B65: 外侧装饰面长 | C65: 337.92 | D65: 外侧装饰面积 | E65: =ROUND(C64*(C65/1000),2) -> 2.1 | F65: 喷涂单价 | G65: =G$23 -> 10 | H65: 喷涂总价 | I65: =E65*G65 -> 21
B66: 内侧装饰面长 | C66: 175.93 | D66: 内侧装饰面积 | E66: =ROUND(C64*(C66/1000),2) -> 1.09 | F66: 喷涂单价 | G66: =G$24 -> 10 | H66: 喷涂总价 | I66: =E66*G66 -> 10.9
B67: 型材名称 | C67: 代号 | D67: 横 | E67: 竖 | F67: 周长 | G67: 数量 | H67: 线重 | I67: 重量 | J67: 宽 | K67: 高 | L67: 宽缩尺 | M67: 高缩尺 | N67: 代号
B68: 固定压线 | C68: 普（SDL2280） | D68: =J68-IF(L68=1,72,IF(L68=2,54,IF(L68=3,26,IF(L68=11,102.8,IF(L68=12,88.8,IF(L68=13,74.8,0)))))) -> 2548 | E68: =K68-IF(M68=1,72,IF(M68=2,24,IF(M68=3,26,IF(M68=11,102.8,IF(M68=12,88.8,IF(M68=13,74.8,0)))))) -> 1278 | F68: =2*(D68+E68)/1000 -> 7.652 | G68: 1 | H68: 0.224 | I68: =ROUND(F68*G68*H68,3)*2 -> 3.428 | J68: =D14 -> 2620 | K68: =E14 -> 1350 | L68: 1 | M68: 1 | N68: 1.框-框
D69: =J69-IF(L69=1,72,IF(L69=2,54,IF(L69=3,26,IF(L69=11,102.8,IF(L69=12,88.8,IF(L69=13,74.8,0)))))) -> 646 | E69: =K69-IF(M69=1,72,IF(M69=2,24,IF(M69=3,26,IF(M69=11,102.8,IF(M69=12,88.8,IF(M69=13,74.8,0)))))) -> 646 | F69: =2*(D69+E69)/1000 -> 2.584 | G69: 4 | H69: =H68 -> 0.224 | I69: =ROUND(F69*G69*H69,3) -> 2.315 | J69: =J35 -> 700 | K69: =E15-K35 -> 670 | L69: 2 | M69: 2 | N69: 2.框-中梃
D70: =J70-IF(L70=1,72,IF(L70=2,54,IF(L70=3,26,IF(L70=11,102.8,IF(L70=12,88.8,IF(L70=13,74.8,0)))))) -> 646 | E70: =K70-IF(M70=1,72,IF(M70=2,24,IF(M70=3,26,IF(M70=11,102.8,IF(M70=12,88.8,IF(M70=13,74.8,0)))))) -> 1376 | F70: =2*(D70+E70)/1000 -> 4.044 | G70: 2 | H70: =H69 -> 0.224 | I70: =ROUND(F70*G70*H70,3) -> 1.812 | J70: =J69 -> 700 | K70: =K35 -> 1400 | L70: 2 | M70: 2 | N70: 3.中梃-中梃
D71: =J71-IF(L71=1,72,IF(L71=2,54,IF(L71=3,26,IF(L71=11,102.8,IF(L71=12,88.8,IF(L71=13,74.8,0)))))) -> 0 | E71: =K71-IF(M71=1,72,IF(M71=2,24,IF(M71=3,26,IF(M71=11,102.8,IF(M71=12,88.8,IF(M71=13,74.8,0)))))) -> 0 | F71: =2*(D71+E71)/1000 -> 0 | H71: =H70 -> 0.224 | I71: =ROUND(F71*G71*H71,3) -> 0 | N71: 11.转.框-框
D72: =J72-IF(L72=1,72,IF(L72=2,54,IF(L72=3,26,IF(L72=11,102.8,IF(L72=12,88.8,IF(L72=13,74.8,0)))))) -> 0 | E72: =K72-IF(M72=1,72,IF(M72=2,24,IF(M72=3,26,IF(M72=11,102.8,IF(M72=12,88.8,IF(M72=13,74.8,0)))))) -> 0 | F72: =2*(D72+E72)/1000 -> 0 | H72: =H71 -> 0.224 | I72: =ROUND(F72*G72*H72,3) -> 0 | N72: 12.转.框-中梃
D73: =J73-IF(L73=1,72,IF(L73=2,54,IF(L73=3,26,IF(L73=11,102.8,IF(L73=12,88.8,IF(L73=13,74.8,0)))))) -> 0 | E73: =K73-IF(M73=1,72,IF(M73=2,24,IF(M73=3,26,IF(M73=11,102.8,IF(M73=12,88.8,IF(M73=13,74.8,0)))))) -> 0 | F73: =2*(D73+E73)/1000 -> 0 | H73: =H70 -> 0.224 | I73: =ROUND(F73*G73*H73,3) -> 0 | N73: 13.转.中梃-中梃
D74: =J74-IF(L74=1,72,IF(L74=2,54,IF(L74=3,26,IF(L74=11,102.8,IF(L74=12,88.8,IF(L74=13,74.8,0)))))) -> 0 | E74: =K74-IF(M74=1,72,IF(M74=2,24,IF(M74=3,26,IF(M74=11,102.8,IF(M74=12,88.8,IF(M74=13,74.8,0)))))) -> 0 | F74: =2*(D74+E74)/1000 -> 0 | H74: =H73 -> 0.224 | I74: =ROUND(F74*G74*H74,3) -> 0
C75: 钢（SDL2280） | D75: =J75-IF(L75=1,72,IF(L75=2,54,IF(L75=3,26,IF(L75=11,102.8,IF(L75=12,88.8,IF(L75=13,74.8,0)))))) -> 0 | E75: =K75-IF(M75=1,72,IF(M75=2,24,IF(M75=3,26,IF(M75=11,102.8,IF(M75=12,88.8,IF(M75=13,74.8,0)))))) -> 0 | F75: =2*(D75+E75)/1000 -> 0 | H75: =H74 -> 0.224 | I75: =ROUND(F75*G75*H75,3) -> 0 | N75: g钢化固定
D76: =J76-IF(L76=1,72,IF(L76=2,54,IF(L76=3,26,IF(L76=11,102.8,IF(L76=12,88.8,IF(L76=13,74.8,0)))))) -> 0 | E76: =K76-IF(M76=1,72,IF(M76=2,24,IF(M76=3,26,IF(M76=11,102.8,IF(M76=12,88.8,IF(M76=13,74.8,0)))))) -> 0 | F76: =2*(D76+E76)/1000 -> 0 | H76: =H72 -> 0.224 | I76: =ROUND(F76*G76*H76,3) -> 0 | N76: g钢化固定
D77: =J77-IF(L77=1,72,IF(L77=2,54,IF(L77=3,26,IF(L77=11,102.8,IF(L77=12,88.8,IF(L77=13,74.8,0)))))) -> 0 | E77: =K77-IF(M77=1,72,IF(M77=2,24,IF(M77=3,26,IF(M77=11,102.8,IF(M77=12,88.8,IF(M77=13,74.8,0)))))) -> 0 | F77: =2*(D77+E77)/1000 -> 0 | H77: =H76 -> 0.224 | I77: =ROUND(F77*G77*H77,3) -> 0 | N77: g钢化固定
D78: =J78-IF(L78=1,72,IF(L78=2,54,IF(L78=3,26,IF(L78=11,102.8,IF(L78=12,88.8,IF(L78=13,74.8,0)))))) -> 0 | E78: =K78-IF(M78=1,72,IF(M78=2,24,IF(M78=3,26,IF(M78=11,102.8,IF(M78=12,88.8,IF(M78=13,74.8,0)))))) -> 0 | F78: =2*(D78+E78)/1000 -> 0 | H78: =H77 -> 0.224 | I78: =ROUND(F78*G78*H78,3) -> 0 | N78: g钢化固定
D79: =J79-IF(L79=1,72,IF(L79=2,54,IF(L79=3,26,IF(L79=11,102.8,IF(L79=12,88.8,IF(L79=13,74.8,0)))))) -> 0 | E79: =K79-IF(M79=1,72,IF(M79=2,24,IF(M79=3,26,IF(M79=11,102.8,IF(M79=12,88.8,IF(M79=13,74.8,0)))))) -> 0 | F79: =2*(D79+E79)/1000 -> 0 | H79: =H78 -> 0.224 | I79: =ROUND(F79*G79*H79,3) -> 0 | N79: g钢化固定
D80: =J80-IF(L80=1,72,IF(L80=2,54,IF(L80=3,26,IF(L80=11,102.8,IF(L80=12,88.8,IF(L80=13,74.8,0)))))) -> 0 | E80: =K80-IF(M80=1,72,IF(M80=2,24,IF(M80=3,26,IF(M80=11,102.8,IF(M80=12,88.8,IF(M80=13,74.8,0)))))) -> 0 | F80: =2*(D80+E80)/1000 -> 0 | H80: =H79 -> 0.224 | I80: =ROUND(F80*G80*H80,3) -> 0 | N80: g钢化固定
D81: =J81-IF(L81=1,72,IF(L81=2,54,IF(L81=3,26,IF(L81=11,102.8,IF(L81=12,88.8,IF(L81=13,74.8,0)))))) -> 0 | E81: =K81-IF(M81=1,72,IF(M81=2,24,IF(M81=3,26,IF(M81=11,102.8,IF(M81=12,88.8,IF(M81=13,74.8,0)))))) -> 0 | F81: =2*(D81+E81)/1000 -> 0 | H81: =H80 -> 0.224 | I81: =ROUND(F81*G81*H81,3) -> 0 | N81: 超大钢化固定6mm
C82: 夹胶钢（SDL2280） | D82: =J82-IF(L82=1,72,IF(L82=2,54,IF(L82=3,26,IF(L82=11,102.8,IF(L82=12,88.8,IF(L82=13,74.8,0)))))) -> 0 | E82: =K82-IF(M82=1,72,IF(M82=2,24,IF(M82=3,26,IF(M82=11,102.8,IF(M82=12,88.8,IF(M82=13,74.8,0)))))) -> 0 | F82: =2*(D82+E82)/1000 -> 0 | H82: =H81 -> 0.224 | I82: =ROUND(F82*G82*H82,3) -> 0
D83: =J83-IF(L83=1,72,IF(L83=2,54,IF(L83=3,26,IF(L83=11,102.8,IF(L83=12,88.8,IF(L83=13,74.8,0)))))) -> 0 | E83: =K83-IF(M83=1,72,IF(M83=2,24,IF(M83=3,26,IF(M83=11,102.8,IF(M83=12,88.8,IF(M83=13,74.8,0)))))) -> 0 | F83: =2*(D83+E83)/1000 -> 0 | H83: =H82 -> 0.224 | I83: =ROUND(F83*G83*H83,3) -> 0
D84: =J84-IF(L84=1,72,IF(L84=2,54,IF(L84=3,26,IF(L84=11,102.8,IF(L84=12,88.8,IF(L84=13,74.8,0)))))) -> 0 | E84: =K84-IF(M84=1,72,IF(M84=2,24,IF(M84=3,26,IF(M84=11,102.8,IF(M84=12,88.8,IF(M84=13,74.8,0)))))) -> 0 | F84: =2*(D84+E84)/1000 -> 0 | H84: =H83 -> 0.224 | I84: =ROUND(F84*G84*H84,3) -> 0
D85: =J85-IF(L85=1,72,IF(L85=2,54,IF(L85=3,26,IF(L85=11,102.8,IF(L85=12,88.8,IF(L85=13,74.8,0)))))) -> 0 | E85: =K85-IF(M85=1,72,IF(M85=2,24,IF(M85=3,26,IF(M85=11,102.8,IF(M85=12,88.8,IF(M85=13,74.8,0)))))) -> 0 | F85: =2*(D85+E85)/1000 -> 0 | H85: =H84 -> 0.224 | I85: =ROUND(F85*G85*H85,3) -> 0
D86: =J86-IF(L86=1,72,IF(L86=2,54,IF(L86=3,26,IF(L86=11,102.8,IF(L86=12,88.8,IF(L86=13,74.8,0)))))) -> 0 | E86: =K86-IF(M86=1,72,IF(M86=2,24,IF(M86=3,26,IF(M86=11,102.8,IF(M86=12,88.8,IF(M86=13,74.8,0)))))) -> 0 | F86: =2*(D86+E86)/1000 -> 0 | H86: =H85 -> 0.224 | I86: =ROUND(F86*G86*H86,3) -> 0
D87: =J87-IF(L87=1,72,IF(L87=2,54,IF(L87=3,26,IF(L87=11,102.8,IF(L87=12,88.8,IF(L87=13,74.8,0)))))) -> 0 | E87: =K87-IF(M87=1,72,IF(M87=2,24,IF(M87=3,26,IF(M87=11,102.8,IF(M87=12,88.8,IF(M87=13,74.8,0)))))) -> 0 | F87: =2*(D87+E87)/1000 -> 0 | H87: =H86 -> 0.224 | I87: =ROUND(F87*G87*H87,3) -> 0
B88: 型材总长度 | C88: =SUMPRODUCT(F68:F87*G68:G87) -> 26.076 | D88: 型材总重量 | E88: =SUM(I68:I87)*1.1 -> 8.3105 | F88: 型材单价 | G88: =(C$218+C$222)/1000 -> 39.7815 | H88: 型材总价 | I88: =ROUND(E88*G88,2) -> 330.6
B89: 外侧装饰面长 | C89: 181.72 | D89: 外侧装饰面积 | E89: =ROUND(C88*(C89/1000),2) -> 4.74 | F89: 喷涂单价 | G89: =G$23 -> 10 | H89: 喷涂总价 | I89: =E89*G89 -> 47.4
B90: 内侧装饰面长 | D90: 内侧装饰面积 | E90: =ROUND(C88*(C90/1000),2) -> 0 | F90: 喷涂单价 | G90: =G$24 -> 10 | H90: 喷涂总价 | I90: =E90*G90 -> 0
B91: 型材名称 | C91: 代号 | D91: 横 | E91: 竖 | F91: 周长 | G91: 数量 | H91: 线重 | I91: 重量
B92: 内开窗扇压线 | C92: SDL2281 | D92: =D26-90 -> -90 | E92: =E26-90 -> -90 | F92: =2*(D92+E92)/1000 -> -0.36 | G92: =G26 -> 0 | H92: 0.271 | I92: =ROUND(F92*G92*H92,3) -> 0
D93: =D27-90 -> -90 | E93: =E27-90 -> -90 | F93: =2*(D93+E93)/1000 -> -0.36 | G93: =G27 -> 0 | H93: =H92 -> 0.271 | I93: =ROUND(F93*G93*H93,3) -> 0
D94: =D28-90 -> -90 | E94: =E28-90 -> -90 | F94: =2*(D94+E94)/1000 -> -0.36 | G94: =G28 -> 0 | H94: =H93 -> 0.271 | I94: =ROUND(F94*G94*H94,3) -> 0
D95: =D29-90 -> -90 | E95: =E29-90 -> -90 | F95: =2*(D95+E95)/1000 -> -0.36 | G95: =G29 -> 0 | H95: =H94 -> 0.271 | I95: =ROUND(F95*G95*H95,3) -> 0
D96: =D30-90 -> -90 | E96: =E30-90 -> -90 | F96: =2*(D96+E96)/1000 -> -0.36 | G96: =G30 -> 0 | H96: =H95 -> 0.271 | I96: =ROUND(F96*G96*H96,3) -> 0
B97: 型材总长度 | C97: =SUMPRODUCT(F92:F96*G92:G96) -> 0 | D97: 型材总重量 | E97: =SUM(I92:I96)*1.1 -> 0 | F97: 型材单价 | G97: =(C$218+C$222)/1000 -> 39.7815 | H97: 型材总价 | I97: =ROUND(E97*G97,2) -> 0
B98: 外侧装饰面长 | C98: 186.72 | D98: 外侧装饰面积 | E98: =ROUND(C97*(C98/1000),2) -> 0 | F98: 喷涂单价 | G98: =G$23 -> 10 | H98: 喷涂总价 | I98: =E98*G98 -> 0
B99: 内侧装饰面长 | C99: 0 | D99: 内侧装饰面积 | E99: =ROUND(C97*(C99/1000),2) -> 0 | F99: 喷涂单价 | G99: =G$24 -> 10 | H99: 喷涂总价 | I99: =E99*G99 -> 0
B100: 型材名称 | C100: 代号 | D100: 横 | E100: 竖 | F100: 周长 | G100: 数量 | H100: 线重 | I100: 重量
B101: 外开窗扇压线 | C101: =C92 -> SDL2281 | D101: =D35-122 -> 478 | E101: =E35-122 -> 1178 | F101: =2*(D101+E101)/1000 -> 3.312 | G101: =G35 -> 2 | H101: =H96 -> 0.271 | I101: =ROUND(F101*G101*H101,3) -> 1.795
...

Sheet WMLC2730
B2: MS65F系列（注胶角码） | D2: 24mm | E2: 表面处理 | F2: 静电粉末喷涂 | I2: N0.1 | J2: 副框线重速求表
B3: 代号 | C3: 门窗尺寸 | D3: 宽度 | E3: 高度 | F3: 面积 | G3: 樘数 | H3: 总面积 | J3: 宽度:mm | K3: 高度:mm | L3: 壁厚:mm | M3: 线重
B4: =MID(CELL("filename",Q13),FIND("]",CELL("filename",Q13))+1,30) -> WMLC2730 | C4: 洞口尺寸 | D4: 2700 | E4: 3000 | F4: 7.318 | G4: 1 | H4: =F4*G4 -> 7.318 | J4: 40 | K4: 20 | L4: 1.5 | M4: =ROUND(((J4*K4)-(J4-2*L4)*(K4-2*L4))*7.8/1000,3) -> 1.334
C5: 附框内口尺寸 | D5: =D4-70 -> 2630 | E5: =E4-70 -> 2930 | F5: =D5*E5/10^6 -> 7.7059 | G5: 1 | H5: =F5*G5 -> 7.7059 | J5: 40 | K5: 20 | L5: 2 | M5: =ROUND(((J5*K5)-(J5-2*L5)*(K5-2*L5))*7.8/1000,3) -> 1.747
C6: 主框尺寸 | D6: =D4-80 -> 2620 | E6: =E4-80 -> 2920 | F6: =D6*E6/10^6 -> 7.6504 | G6: 1 | H6: =F6*G6 -> 7.6504 | J6: 40 | K6: 20 | L6: 2 | M6: =ROUND(((J6*K6)-(J6-2*L6)*(K6-2*L6))*7.8/1000,3) -> 1.747
B7: 钢副框（热） | C7: 宽度 | D7: 宽数量 | E7: 高度 | F7: 高数量 | G7: 线重 | H7: 单价 | I7: 总价 | J7: 80 | K7: 40 | L7: 2 | M7: =ROUND(((J7*K7)-(J7-2*L7)*(K7-2*L7))*7.8/1000,3) -> 3.619
B8: 40*20*2.0 | C8: =D4-30 -> 2670 | D8: 2 | E8: =E4-30 -> 2970 | F8: 2 | G8: 1.747 | H8: =材料价格!B3 -> 7.5 | I8: =ROUND((C8*D8+E8*F8)*G8*H8/1000*1.1,2) -> 162.58 | J8: 40 | K8: 20 | L8: 1.4 | M8: =ROUND(((J8*K8)-(J8-2*L8)*(K8-2*L8))*2.71/1000,3) -> 0.434
B9: 40*20*2.0 | G9: 1.747 | H9: =H8 -> 7.5 | I9: =ROUND((C9*D9+E9*F9)*G9*H9/1000*1.1,2) -> 0 | M9: =ROUND(((J9*K9)-(J9-2*L9)*(K9-2*L9))*7.8/1000,3) -> 0
B10: 80*40*2 | G10: 3.619 | H10: =H9 -> 7.5 | I10: =ROUND((C10*D10+E10*F10)*G10*H10/1000*1.1,2) -> 0 | M10: =ROUND(((J10*K10)-(J10-2*L10)*(K10-2*L10))*7.8/1000,3) -> 0
B11: 50*50*2.0 | G11: 2.995 | H11: =H10 -> 7.5 | I11: =ROUND((C11*D11+E11*F11)*G11*H11/1000*1.1,2) -> 0 | M11: =ROUND(((J11*K11)-(J11-2*L11)*(K11-2*L11))*7.8/1000,3) -> 0
B12: 副框平米用量 | C12: =((I9+I10+I8+I11)/H8)/F4 -> 2.9621937 | D12: （Kg/m2) | E12: =(I9+I10+I8+I11)/F4 -> 22.216453 | F12: （元/m2) | H12: =ROUND(SUM(I8:I11)/H8,2) -> 21.68 | I12: =SUM(I8:I11) -> 162.58
B13: 型材名称 | C13: 代号 | D13: 横 | E13: 竖 | F13: 周长 | G13: 数量 | H13: 线重 | I13: 重量
B14: 平开窗框 | C14: SDF2894 | D14: =D6 -> 2620 | E14: 1350 | F14: =ROUND((D14+E14)*2/1000,4) -> 7.94 | G14: 1 | H14: 1.47 | I14: =ROUND(F14*G14*H14,3)*1.5 -> 17.508
D15: 625 | E15: =E6-E14 -> 1570 | F15: =ROUND((D15+E15)*2/1000,4) -> 4.39 | G15: 2 | H15: =H14 -> 1.47 | I15: =ROUND(F15*G15*H15,3) -> 12.907
F16: =ROUND((D16+E16)*2/1000,4) -> 0 | H16: =H15 -> 1.47 | I16: =ROUND(F16*G16*H16,3) -> 0
F17: =ROUND((D17+E17)*2/1000,4) -> 0 | H17: =H16 -> 1.47 | I17: =ROUND(F17*G17*H17,3) -> 0
F18: =ROUND((D18+E18)*2/1000,4) -> 0 | H18: =H17 -> 1.47 | I18: =ROUND(F18*G18*H18,3) -> 0
F19: =ROUND((D19+E19)*2/1000,4) -> 0 | H19: =H18 -> 1.47 | I19: =ROUND(F19*G19*H19,3) -> 0
F20: =ROUND((D20+E20)*2/1000,4) -> 0 | H20: =H19 -> 1.47 | I20: =ROUND(F20*G20*H20,3) -> 0
F21: =ROUND((D21+E21)*2/1000,4) -> 0 | H21: =H20 -> 1.47 | I21: =ROUND(F21*G21*H21,3) -> 0
B22: 型材总长度 | C22: =SUMPRODUCT(F14:F21*G14:G21) -> 16.72 | D22: 型材总重量 | E22: =SUM(I14:I21)*1.1 -> 33.4565 | F22: 型材单价 | G22: =(C$218+C$219)/1000 -> 46.0815 | H22: 型材总价 | I22: =ROUND(E22*G22,2) -> 1541.73 | J22: =SUM(G14:G21) -> 3
B23: 外侧装饰面长 | C23: 207.36 | D23: 外侧装饰面积 | E23: =ROUND(C22*(C23/1000),2) -> 3.47 | F23: 喷涂单价 | G23: 10 | H23: 喷涂总价 | I23: =E23*G23 -> 34.7
B24: 内侧装饰面长 | C24: 169.96 | D24: 内侧装饰面积 | E24: =ROUND(C22*(C24/1000),2) -> 2.84 | F24: 喷涂单价 | G24: 10 | H24: 喷涂总价 | I24: =E24*G24 -> 28.4
B25: 型材名称 | C25: 代号 | D25: 横 | E25: 竖 | F25: 周长 | G25: 数量 | H25: 线重 | I25: 重量 | J25: 宽 | K25: 高 | L25: 宽缩尺 | M25: 高缩尺 | N25: 代号
B26: 内平开窗扇 | C26: SDF2885 | D26: =J26-IF(L26=1,44,IF(L26=2,30,IF(L26=3,16,0))) -> 0 | E26: =K26-IF(M26=1,44,IF(M26=2,30,IF(M26=3,16,0))) -> 0 | F26: =ROUND((D26+E26)*2/1000,4) -> 0 | H26: 1.62 | I26: =IF(AND(D26>0,E26>0,F26>0),F26*G26*H26,0) -> 0 | N26: 1.框-框 | O26: 普通扇
D27: =J27-IF(L27=1,44,IF(L27=2,30,IF(L27=3,16,0))) -> 0 | E27: =K27-IF(M27=1,44,IF(M27=2,30,IF(M27=3,16,0))) -> 0 | F27: =ROUND((D27+E27)*2/1000,4) -> 0 | H27: =H26 -> 1.62 | I27: =IF(AND(D27>0,E27>0,F27>0),F27*G27*H27,0) -> 0 | N27: 2.框-中梃 | O27: 钢化扇
D28: =J28-IF(L28=1,44,IF(L28=2,30,IF(L28=3,16,0))) -> 0 | E28: =K28-IF(M28=1,44,IF(M28=2,30,IF(M28=3,16,0))) -> 0 | F28: =ROUND((D28+E28)*2/1000,4) -> 0 | H28: =H27 -> 1.62 | I28: =IF(AND(D28>0,E28>0,F28>0),F28*G28*H28,0) -> 0 | N28: 3.中梃-中梃 | O28: 钢化扇
D29: =J29-IF(L29=1,44,IF(L29=2,30,IF(L29=3,16,0))) -> 0 | E29: =K29-IF(M29=1,44,IF(M29=2,30,IF(M29=3,16,0))) -> 0 | F29: =ROUND((D29+E29)*2/1000,4) -> 0 | H29: =H28 -> 1.62 | I29: =IF(AND(D29>0,E29>0,F29>0),F29*G29*H29,0) -> 0
D30: =J30-IF(L30=1,44,IF(L30=2,30,IF(L30=3,16,0))) -> 0 | E30: =K30-IF(M30=1,44,IF(M30=2,30,IF(M30=3,16,0))) -> 0 | F30: =ROUND((D30+E30)*2/1000,4) -> 0 | H30: =H29 -> 1.62 | I30: =IF(AND(D30>0,E30>0,F30>0),F30*G30*H30,0) -> 0
B31: 型材总长度 | C31: =SUMPRODUCT(F26:F30*G26:G30) -> 0 | D31: 型材总重量 | E31: =SUM(I26:I30)*1.1 -> 0 | F31: 型材单价 | G31: =(C$218+C$221)/1000 -> 46.0815 | H31: 型材总价 | I31: =ROUND(E31*G31,2) -> 0 | J31: =SUM(G26:G30) -> 0
B32: 外侧装饰面长 | C32: 183.32 | D32: 外侧装饰面积 | E32: =ROUND(C31*(C32/1000),2) -> 0 | F32: 喷涂单价 | G32: =G$23 -> 10 | H32: 喷涂总价 | I32: =E32*G32 -> 0
B33: 内侧装饰面长 | C33: 257.82 | D33: 内侧装饰面积 | E33: =ROUND(C31*(C33/1000),2) -> 0 | F33: 喷涂单价 | G33: =G$24 -> 10 | H33: 喷涂总价 | I33: =E33*G33 -> 0
B34: 型材名称 | C34: 代号 | D34: 横 | E34: 竖 | F34: 周长 | G34: 数量 | H34: 线重 | I34: 重量 | J34: 宽 | K34: 高 | L34: （宽）缩尺 | M34: （高）缩尺 | N34: 代号
B35: 外平开窗扇 | C35: SDF2806 | D35: =J35-IF(L35=1,44,IF(L35=2,30,IF(L35=3,16,IF(L35=11,118,IF(L35=12,100,IF(L35=13,76.8,0)))))) -> 507 | E35: =K35-IF(M35=1,44,IF(M35=2,30,IF(M35=3,16,IF(M35=11,118,IF(M35=12,100,IF(M35=13,76.8,0)))))) -> 700 | F35: =ROUND((D35+E35)*2/1000,4) -> 2.414 | G35: 2 | H35: 1.814 | I35: =ROUND(F35*G35*H35,3) -> 8.758 | J35: =D15 -> 625 | K35: 800 | L35: 11 | M35: 12 | N35: 1.框-框
D36: =J36-IF(L36=1,44,IF(L36=2,30,IF(L36=3,16,IF(L36=11,118,IF(L36=12,100,IF(L36=13,76.8,0)))))) -> 0 | E36: =K36-IF(M36=1,44,IF(M36=2,30,IF(M36=3,16,IF(M36=11,118,IF(M36=12,100,IF(M36=13,76.8,0)))))) -> 0 | F36: =ROUND((D36+E36)*2/1000,4) -> 0 | H36: =H35 -> 1.814 | I36: =ROUND(F36*G36*H36,3) -> 0 | N36: 2.框-中梃
D37: =J37-IF(L37=1,44,IF(L37=2,30,IF(L37=3,16,IF(L37=11,118,IF(L37=12,100,IF(L37=13,76.8,0)))))) -> 0 | E37: =K37-IF(M37=1,44,IF(M37=2,30,IF(M37=3,16,IF(M37=11,118,IF(M37=12,100,IF(M37=13,76.8,0)))))) -> 0 | F37: =ROUND((D37+E37)*2/1000,4) -> 0 | H37: =H36 -> 1.814 | I37: =ROUND(F37*G37*H37,3) -> 0 | N37: 3.中梃-中梃
B38: 型材总长度 | C38: =SUMPRODUCT(F35:F37*G35:G37) -> 4.828 | D38: 型材总重量 | E38: =SUM(I35:I37)*1.1 -> 9.6338 | F38: 型材单价 | G38: =(C$218+C$219)/1000 -> 46.0815 | H38: 型材总价 | I38: =ROUND(E38*G38,2) -> 443.94 | J38: =SUM(G35:G37) -> 2 | N38: 11.转.框-框
B39: 外侧装饰面长 | C39: 320.14 | D39: 外侧装饰面积 | E39: =ROUND(C38*(C39/1000),2) -> 1.55 | F39: 喷涂单价 | G39: =G$23 -> 10 | H39: 喷涂总价 | I39: =E39*G39 -> 15.5 | N39: 12.转.框-中梃
B40: 内侧装饰面长 | C40: 156.99 | D40: 内侧装饰面积 | E40: =ROUND(C38*(C40/1000),2) -> 0.76 | F40: 喷涂单价 | G40: =G$24 -> 10 | H40: 喷涂总价 | I40: =E40*G40 -> 7.6 | N40: 13.转.中梃-中梃
B41: 型材名称 | C41: 代号 | D41: 横 | E41: 竖 | F41: 周长 | G41: 数量 | H41: 线重 | I41: 重量 | J41: 宽 | K41: 高 | L41: （宽）缩尺 | M41: （高）缩尺 | N41: 代号
B42: 转换料 | C42: SDF3162 (扇转换） | D42: =J42-IF(L42=1,46,IF(L42=2,34.5,IF(L42=3,23))) -> 579 | E42: =K42-IF(M42=1,46,IF(M42=2,34.5,IF(M42=3,23))) -> 765.5 | F42: =ROUND((D42+E42)*2/1000,4) -> 2.689 | G42: =G35 -> 2 | H42: 1.26 | I42: =ROUND(F42*G42*H42,3) -> 6.776 | J42: =J35 -> 625 | K42: =K35 -> 800 | L42: 1 | M42: 2 | N42: 1.框-框
D43: =J43-IF(L43=1,46,IF(L43=2,34.5,IF(L43=3,23))) -> 0 | E43: =K43-IF(M43=1,46,IF(M43=2,34.5,IF(M43=3,23))) -> 0 | F43: =ROUND((D43+E43)*2/1000,4) -> 0 | H43: =H42 -> 1.26 | I43: =ROUND(F43*G43*H43,3) -> 0 | N43: 2.框-中梃
D44: =J44-IF(L44=1,46,IF(L44=2,34.5,IF(L44=3,23))) -> 0 | E44: =K44-IF(M44=1,46,IF(M44=2,34.5,IF(M44=3,23))) -> 0 | F44: =ROUND((D44+E44)*2/1000,4) -> 0 | H44: =H43 -> 1.26 | I44: =ROUND(F44*G44*H44,3) -> 0 | N44: 3.中梃-中梃
C45: SDF3162 (固定转换） | D45: =J45-IF(L45=1,46,IF(L45=2,34.5,IF(L45=3,23))) -> 0 | E45: =K45-IF(M45=1,46,IF(M45=2,34.5,IF(M45=3,23))) -> 0 | F45: =ROUND((D45+E45)*2/1000,4) -> 0 | H45: =H44 -> 1.26 | I45: =ROUND(F45*G45*H45,3) -> 0 | N45: 1.框-框
D46: =J46-IF(L46=1,46,IF(L46=2,34.5,IF(L46=3,23))) -> 0 | E46: =K46-IF(M46=1,46,IF(M46=2,34.5,IF(M46=3,23))) -> 0 | F46: =ROUND((D46+E46)*2/1000,4) -> 0 | H46: =H45 -> 1.26 | I46: =ROUND(F46*G46*H46,3) -> 0 | N46: 2.框-中梃
D47: =J47-IF(L47=1,46,IF(L47=2,34.5,IF(L47=3,23))) -> 0 | E47: =K47-IF(M47=1,46,IF(M47=2,34.5,IF(M47=3,23))) -> 0 | F47: =ROUND((D47+E47)*2/1000,4) -> 0 | H47: =H46 -> 1.26 | I47: =ROUND(F47*G47*H47,3) -> 0 | N47: 3.中梃-中梃
